Workbook

Sheet TDC
A1: Comprobante | B1: Fec. Doc. | C1: Voucher | E1: Titular | F1: T.Doc/Nro | G1: Debe | H1: Haber | I1: Acumulado
A2: adig/1114 | B2: 45772 | C2: 2553 | D2: Glosa : TDC CLP_USD C.Contreras | E2: CAROL TATIANA CONTRERAS MUÑOZ | H2: 3070443 | I2: -3070443
A3: adig/1115 | B3: 45772 | C3: 2554 | D3: Glosa : TDC CLP Marcelo PENNA | E3: MARCELO PENNA SANTOS | H3: 494703 | I3: -3565146
A4: adig/1116 | B4: 45772 | C4: 2555 | D4: Glosa : TDC CLP JUAN CARVALLO | E4: JUAN CARVALLO JIMÉNEZ | H4: 122074 | I4: -3687220
A5: adig/1117 | B5: 45772 | C5: 2556 | D5: Glosa : TDC CLP-USD CAITLIN WHEAT | E5: CAITLIN JOY WHEAT | H5: 100022 | I5: -3787242
A6: adig/1122 | B6: 45772 | C6: 2561 | D6: Glosa : TDC CLP-USD CAtherine alaracon | E6: KATHERINNE SILVANA ALARCON ESCOBAR | H6: 806870 | I6: -4594112
A7: adig/1283 | B7: 45772 | C7: 2939 | D7: Glosa : TDC CLP/USD FRANCISCO MIRANDA | E7: FRANCISCO MIRANDA RIADI | H7: 5014 | I7: -4599126
A8: adig/1170 | B8: 45792 | C8: 2742 | D8: Glosa : Bank Transfer to CC Caitlin Wheat. | E8: CAITLIN JOY WHEAT | G8: 100022 | I8: -4499104
A9: adig/1171 | B9: 45792 | C9: 2743 | D9: Glosa : Bank Transfer to CC Carol Contreras. | E9: CAROL TATIANA CONTRERAS MUÑOZ | G9: 3070443 | I9: -1428661
A10: adig/1172 | B10: 45792 | C10: 2744 | D10: Glosa : Bank Transfer to CC Katherinne Alarcon. | E10: KATHERINNE SILVANA ALARCON ESCOBAR | G10: 806870 | I10: -621791
A11: adig/1173 | B11: 45792 | C11: 2745 | D11: Glosa : Bank Transfer to CC Francisco Miranda. | E11: FRANCISCO MIRANDA RIADI | G11: 5014 | I11: -616777
A12: adig/1174 | B12: 45792 | C12: 2746 | D12: Glosa : Bank Transfer to CC Sebastián Carvallo. | E12: JUAN CARVALLO JIMÉNEZ | G12: 72314 | I12: -544463
A13: adig/1175 | B13: 45792 | C13: 2749 | D13: Glosa : Bank Transfer to CC Marcelo Penna. | E13: MARCELO PENNA SANTOS | G13: 1901018 | I13: 1356555
A14: adig/1250 | B14: 45805 | C14: 2906 | D14: Glosa : TDC CLP-USD CAITLIN WHEAT | E14: CAITLIN JOY WHEAT | H14: 211905 | I14: 1144650
A15: adig/1251 | B15: 45805 | C15: 2907 | D15: Glosa : TDC CLP_USD C.Contreras | E15: CAROL TATIANA CONTRERAS MUÑOZ | H15: 1231423 | I15: -86773
A16: adig/1252 | B16: 45805 | C16: 2908 | D16: Glosa : Tarjeta de Credito F.Miranda | E16: FRANCISCO MIRANDA RIADI | H16: 71087 | I16: -157860
A17: adig/1253 | B17: 45805 | C17: 2909 | D17: Glosa : TDC pesos USD Katherine Alarcon | E17: KATHERINNE SILVANA ALARCON ESCOBAR | H17: 100449 | I17: -258309
A18: adig/1254 | B18: 45805 | C18: 2910 | D18: Glosa : TDC CLP/USD Marcelo PENNA | E18: MARCELO PENNA SANTOS | H18: 79021 | I18: -337330
A19: adig/1255 | B19: 45805 | C19: 2911 | D19: Glosa : TDC CLP JUAN sebastian CARVALLO | E19: JUAN CARVALLO JIMÉNEZ | H19: 161109 | I19: -498439
A20: adig/1284 | B20: 45805 | C20: 2940 | D20: Glosa : TDC CLP/USD CESAR MACHADO | E20: CESAR FELIPE MACHADO RIBEIRO LOPES | H20: 51519 | I20: -549958
A21: adig/1553 | B21: 45805 | C21: 3504 | D21: Glosa : TDC CLP JUAN sebastian CARVALLO | E21: JUAN CARVALLO JIMÉNEZ | H21: 229285 | I21: -779243
A22: adig/1196 | B22: 45810 | C22: 2822 | D22: Glosa : Prepaid PPE seguridad | E22: DEMO MAGNUS ERP | H22: 25228 | I22: -804471
A23: adig/1202 | B23: 45820 | C23: 2858 | D23: Glosa : Bank Transfer to CC Caitlin Wheat. | E23: CAITLIN JOY WHEAT | G23: 450611 | I23: -353860
A24: adig/1203 | B24: 45820 | C24: 2859 | D24: Glosa : Bank Transfer to CC Katherinne Alarcon. | E24: KATHERINNE SILVANA ALARCON ESCOBAR | G24: 100449 | I24: -253411
A25: adig/1204 | B25: 45820 | C25: 2860 | D25: Glosa : Bank Transfer to CC Francisco Miranda. | E25: FRANCISCO MIRANDA RIADI | G25: 71087 | I25: -182324
A26: adig/1205 | B26: 45820 | C26: 2861 | D26: Glosa : Bank Transfer to CC Marcelo Penna. | E26: MARCELO PENNA SANTOS | G26: 79021 | I26: -103303
A27: adig/1206 | B27: 45820 | C27: 2862 | D27: Glosa : Bank Transfer to CC Sebastián Carvallo. | E27: JUAN CARVALLO JIMÉNEZ | G27: 210396 | I27: 107093
A28: adig/1207 | B28: 45820 | C28: 2863 | D28: Glosa : Bank Transfer to CC Carol Contreras. | E28: CAROL TATIANA CONTRERAS MUÑOZ | G28: 1231423 | I28: 1338516
A29: adig/1256 | B29: 45834 | C29: 2912 | D29: Glosa : TDC CLP/USD CARLO CONTRERAS | E29: CAROL TATIANA CONTRERAS MUÑOZ | H29: 981428 | I29: 357088
A30: adig/1257 | B30: 45834 | C30: 2913 | D30: Glosa : TDC CLP/USD CESAR MACHADO | E30: CESAR FELIPE MACHADO RIBEIRO LOPES | H30: 1962244 | I30: -1605156
A31: adig/1258 | B31: 45834 | C31: 2914 | D31: Glosa : TDC CLP/USD FRANCISCO MIRANDA | E31: FRANCISCO MIRANDA RIADI | H31: 4322 | I31: -1609478
A32: adig/1259 | B32: 45834 | C32: 2915 | D32: Glosa : TDC CLP/USD JORGE MORIS | E32: JORGE MORIS JORDÁN | H32: 39636 | I32: -1649114
A33: adig/1260 | B33: 45834 | C33: 2916 | D33: Glosa : TDC CLP/USD KATHERINE ALARCON | E33: KATHERINNE SILVANA ALARCON ESCOBAR | H33: 2020460 | I33: -3669574
A34: adig/1261 | B34: 45834 | C34: 2917 | D34: Glosa : TDC CLP/USD MARCELO PENNA | E34: MARCELO PENNA SANTOS | H34: 87617 | I34: -3757191
A35: adig/1311 | B35: 45845 | C35: 3041 | D35: Glosa : Payment: ER - Carol Contreras 25.7 - Reimbursable Expense - compra cervezas happ... | 25.7 - Reimbursable Expense - compra cervezas happ... | E35: CAROL TATIANA CONTRERAS MUÑOZ | G35: 33059 | I35: -3724132
A36: adig/1312 | B36: 45848 | C36: 3049 | D36: Glosa : Bank Transfer to CC Carol Contreras. | E36: CAROL TATIANA CONTRERAS MUÑOZ | G36: 981428 | I36: -2742704
A37: adig/1313 | B37: 45848 | C37: 3050 | D37: Glosa : Bank Transfer to CC Katherinne Alarcon. | E37: KATHERINNE SILVANA ALARCON ESCOBAR | G37: 2020460 | I37: -722244
A38: adig/1314 | B38: 45848 | C38: 3051 | D38: Glosa : Bank Transfer to CC Francisco Miranda. | E38: FRANCISCO MIRANDA RIADI | G38: 20216 | I38: -702028
A39: adig/1315 | B39: 45848 | C39: 3052 | D39: Glosa : Bank Transfer to CC Marcelo Penna. | E39: MARCELO PENNA SANTOS | G39: 87617 | I39: -614411
A40: adig/1333 | B40: 45867 | C40: 3092 | D40: Glosa : TDC CLP/USD CAROl CONTRERAS | E40: CAROL TATIANA CONTRERAS MUÑOZ | H40: 1861875 | I40: -2476286
A41: adig/1334 | B41: 45867 | C41: 3093 | D41: Glosa : TDC CLP/USD KATHERINE ALARCON | E41: KATHERINNE SILVANA ALARCON ESCOBAR | H41: 830502 | I41: -3306788
A42: adig/1335 | B42: 45867 | C42: 3094 | D42: Glosa : TDC CLP JUAN sebastian CARVALLO | E42: JUAN CARVALLO JIMÉNEZ | H42: 293855 | I42: -3600643
A43: adig/1382 | B43: 45869 | C43: 3271 | D43: Glosa : RECLASIFICA GASTOS RENDICION Carol contreras | E43: CAROL TATIANA CONTRERAS MUÑOZ | H43: 1913232 | I43: -5513875
A44: adig/1383 | B44: 45869 | C44: 3272 | D44: Glosa : RECLASIFICA GASTOS RENDICION Carol contreras feb | E44: CAROL TATIANA CONTRERAS MUÑOZ | H44: 2328147 | I44: -7842022
A45: adig/1384 | B45: 45869 | C45: 3273 | D45: Glosa : RECLASIFICA GASTOS RENDICION Carol contreras mar | E45: CAROL TATIANA CONTRERAS MUÑOZ | H45: 1497172 | I45: -9339194
A46: adig/1386 | B46: 45869 | C46: 3275 | D46: Glosa : reclasifica tdc enero | E46: CAITLIN JOY WHEAT | H46: 260913 | I46: -9600107
A47: adig/1387 | B47: 45869 | C47: 3276 | D47: Glosa : RECLASIFICA TDC K. ALARCON ENERO | E47: KATHERINNE SILVANA ALARCON ESCOBAR | H47: 3388645 | I47: -12988752
A48: adig/1395 | B48: 45869 | C48: 3284 | D48: Glosa : apertura TDC F. MIRANDA ENERO | E48: FRANCISCO MIRANDA RIADI | H48: 181839 | I48: -13170591
A49: adig/1397 | B49: 45869 | C49: 3286 | D49: Glosa : APERTURA TDC J. SEBASTIAN C. ENERO | E49: JUAN CARVALLO JIMÉNEZ | H49: 650343 | I49: -13820934
A50: adig/1398 | B50: 45869 | C50: 3287 | D50: Glosa : APERTURA TDC M. PENNA ENERO | E50: MARCELO PENNA SANTOS | H50: 3652188 | I50: -17473122
A51: adig/1410 | B51: 45869 | C51: 3299 | D51: Glosa : APERTURA TDC C. W FEB | E51: CAITLIN JOY WHEAT | H51: 3872 | I51: -17476994
... A60: adig/1533 | B60: 45869 | C60: 3461 | D60: Glosa : ER - Marcelo Penna - Taxis / Trains / Buses - 25-04 Reimbursable Expense - Apr 2025 - Reimbursable | E60: MARCELO PENNA SANTOS | H60: 22780 | I60: -23579253
A61: Totales: | D61: Saldo Final Al 31/07/2025: | G61: 11241448 | H61: 34820701
A62: Saldo Final Al 31/07/2025: | D62: Cuenta: 2114 TARJETAS DE CREDITO USD | I62: -23579253
A63: Cuenta: 2114 TARJETAS DE CREDITO USD | D63: Moneda de la Cta: Dólares Americanos
A64: Moneda de la Cta: Dólares Americanos | D64: Comprobante
A65: Comprobante | B65: Fec. Doc. | C65: Voucher | D65: 0 | E65: Titular | F65: T.Doc/Nro | G65: Debe | H65: Haber | I65: Acumulado
A66: adig/1114 | B66: 45772 | C66: 2553 | D66: Glosa : TDC CLP_USD C.Contreras | E66: CONTRERAS | G66: 975.05 | I66: 975.05
A67: adig/1114 | B67: 45772 | C67: 2553 | D67: Glosa : TDC CLP_USD C.Contreras | E67: CONTRERAS | H67: 975.05 | I67: 0
A68: adig/1115 | B68: 45772 | C68: 2554 | D68: Glosa : TDC CLP Marcelo PENNA | E68: MARCELO PENNA SANTOS | G68: 1499.57 | I68: 1499.57
A69: adig/1115 | B69: 45772 | C69: 2554 | D69: Glosa : TDC CLP Marcelo PENNA | E69: MARCELO PENNA SANTOS | H69: 1499.57 | I69: 0
A70: adig/1117 | B70: 45772 | C70: 2556 | D70: Glosa : TDC CLP-USD CAITLIN WHEAT | E70: CAITLIN JOY WHEAT | H70: 249.18 | I70: -249.18
A71: adig/1122 | B71: 45772 | C71: 2561 | D71: Glosa : TDC CLP-USD CAtherine alaracon | E71: KATHERINNE SILVANA ALARCON ESCOBAR | H71: 706.36 | I71: -955.54
A72: adig/1122 | B72: 45772 | C72: 2561 | D72: Glosa : TDC CLP-USD CAtherine alaracon | E72: KATHERINNE SILVANA ALARCON ESCOBAR | G72: 706.36 | I72: -249.18
A73: adig/1283 | B73: 45772 | C73: 2939 | D73: Glosa : TDC CLP/USD FRANCISCO MIRANDA | E73: FRANCISCO MIRANDA RIADI | H73: 45.39 | I73: -294.57
A74: adig/1250 | B74: 45805 | C74: 2906 | D74: Glosa : TDC CLP-USD CAITLIN WHEAT | E74: CAITLIN JOY WHEAT | H74: 249.18 | I74: -543.75
A75: adig/1253 | B75: 45805 | C75: 2909 | D75: Glosa : TDC pesos USD Katherine Alarcon | E75: KATHERINNE SILVANA ALARCON ESCOBAR | H75: 1710.39 | I75: -2254.14
A76: adig/1254 | B76: 45805 | C76: 2910 | D76: Glosa : TDC CLP/USD Marcelo PENNA | E76: MARCELO PENNA SANTOS | H76: 46.41 | I76: -2300.55
A77: adig/1284 | B77: 45805 | C77: 2940 | D77: Glosa : TDC CLP/USD CESAR MACHADO | E77: CESAR FELIPE MACHADO RIBEIRO LOPES | H77: 1989.92 | I77: -4290.47
A78: adig/1257 | B78: 45834 | C78: 2913 | D78: Glosa : TDC CLP/USD CESAR MACHADO | E78: CESAR FELIPE MACHADO RIBEIRO LOPES | H78: 751.8 | I78: -5042.27
A79: adig/1258 | B79: 45834 | C79: 2914 | D79: Glosa : TDC CLP/USD FRANCISCO MIRANDA | E79: FRANCISCO MIRANDA RIADI | H79: 16.73 | I79: -5059
A80: adig/1260 | B80: 45834 | C80: 2916 | D80: Glosa : TDC CLP/USD KATHERINE ALARCON | E80: KATHERINNE SILVANA ALARCON ESCOBAR | H80: 664.62 | I80: -5723.62
A81: adig/1260 | B81: 45834 | C81: 2916 | D81: Glosa : TDC CLP/USD KATHERINE ALARCON | E81: KATHERINNE SILVANA ALARCON ESCOBAR | G81: 1710.39 | I81: -4013.23
A82: adig/1261 | B82: 45834 | C82: 2917 | D82: Glosa : TDC CLP/USD MARCELO PENNA | E82: MARCELO PENNA SANTOS | H82: 4.48 | I82: -4017.71
A83: adig/1334 | B83: 45867 | C83: 3093 | D83: Glosa : TDC CLP/USD KATHERINE ALARCON | E83: KATHERINNE SILVANA ALARCON ESCOBAR | H83: 664.62 | I83: -4682.33
A85: Totales: | G85: 4891.37 | H85: 9573.7
A86: Saldo Final Al 31/07/2025: | I86: -4682.33
A88: MGMayorContableOF_CtaRel

Sheet 06102025
A1: Comprobante | B1: Fec. Doc. | C1: Voucher | E1: Titular | F1: Debe | G1: Haber | H1: Acumulado
A2: plib/8 | B2: 45750 | C2: 2493 | D2: Glosa : reembolso Marcelo Penna | E2: MARCELO PENNA SANTOS | F2: 121678 | H2: 121678
A3: adig/1114 | B3: 45772 | C3: 2553 | D3: Glosa : TDC CLP_USD C.Contreras | E3: CAROL TATIANA CONTRERAS MUÑOZ | G3: 3070443 | H3: -2948765
A4: adig/1115 | B4: 45772 | C4: 2554 | D4: Glosa : TDC CLP Marcelo PENNA | E4: MARCELO PENNA SANTOS | G4: 494703 | H4: -3443468
A5: adig/1116 | B5: 45772 | C5: 2555 | D5: Glosa : TDC CLP JUAN CARVALLO | E5: JUAN CARVALLO JIMÉNEZ | G5: 122074 | H5: -3565542
A6: adig/1117 | B6: 45772 | C6: 2556 | D6: Glosa : TDC CLP-USD CAITLIN WHEAT | E6: CAITLIN JOY WHEAT | G6: 100022 | H6: -3665564
A7: adig/1122 | B7: 45772 | C7: 2561 | D7: Glosa : TDC CLP-USD CAtherine alaracon | E7: KATHERINNE SILVANA ALARCON ESCOBAR | G7: 806870 | H7: -4472434
A8: adig/1283 | B8: 45772 | C8: 2939 | D8: Glosa : TDC CLP/USD FRANCISCO MIRANDA | E8: FRANCISCO MIRANDA RIADI | G8: 5014 | H8: -4477448
A9: adig/1161 | B9: 45785 | C9: 2721 | D9: Glosa : Payment: ER - Marcelo Penna25.4 - Reimbursable Expense - Apr 2025 - Reimbursa... | E9: MARCELO PENNA SANTOS | F9: 22780 | H9: -4454668
A10: adig/1163 | B10: 45785 | C10: 2723 | D10: Glosa : Payment: ER - Katherinne Alarcon25.3 - Reimbursable Expense - Viaje Lima | 25.3 - Reimbursable Expense - Viaje Lima | E10: KATHERINNE SILVANA ALARCON ESCOBAR | F10: 15336 | H10: -4439332
A11: adig/1170 | B11: 45792 | C11: 2742 | D11: Glosa : Bank Transfer to CC Caitlin Wheat. | E11: CAITLIN JOY WHEAT | F11: 100022 | H11: -4339310
A12: adig/1171 | B12: 45792 | C12: 2743 | D12: Glosa : Bank Transfer to CC Carol Contreras. | E12: CAROL TATIANA CONTRERAS MUÑOZ | F12: 3070443 | H12: -1268867
A13: adig/1172 | B13: 45792 | C13: 2744 | D13: Glosa : Bank Transfer to CC Katherinne Alarcon. | E13: KATHERINNE SILVANA ALARCON ESCOBAR | F13: 806870 | H13: -461997
A14: adig/1173 | B14: 45792 | C14: 2745 | D14: Glosa : Bank Transfer to CC Francisco Miranda. | E14: FRANCISCO MIRANDA RIADI | F14: 5014 | H14: -456983
A15: adig/1174 | B15: 45792 | C15: 2746 | D15: Glosa : Bank Transfer to CC Sebastián Carvallo. | E15: JUAN CARVALLO JIMÉNEZ | F15: 72314 | H15: -384669
A16: adig/1175 | B16: 45792 | C16: 2749 | D16: Glosa : Bank Transfer to CC Marcelo Penna. | E16: MARCELO PENNA SANTOS | F16: 1901018 | H16: 1516349
A17: adig/1250 | B17: 45805 | C17: 2906 | D17: Glosa : TDC CLP-USD CAITLIN WHEAT | E17: CAITLIN JOY WHEAT | G17: 450611 | H17: 1065738
A18: adig/1251 | B18: 45805 | C18: 2907 | D18: Glosa : TDC CLP_USD C.Contreras | E18: CAROL TATIANA CONTRERAS MUÑOZ | G18: 1231423 | H18: -165685
A19: adig/1252 | B19: 45805 | C19: 2908 | D19: Glosa : Tarjeta de Credito F.Miranda | E19: FRANCISCO MIRANDA RIADI | G19: 71087 | H19: -236772
A20: adig/1253 | B20: 45805 | C20: 2909 | D20: Glosa : TDC pesos USD Katherine Alarcon | E20: KATHERINNE SILVANA ALARCON ESCOBAR | G20: 100449 | H20: -337221
A21: adig/1254 | B21: 45805 | C21: 2910 | D21: Glosa : TDC CLP/USD Marcelo PENNA | E21: MARCELO PENNA SANTOS | G21: 79021 | H21: -416242
A22: adig/1255 | B22: 45805 | C22: 2911 | D22: Glosa : TDC CLP JUAN sebastian CARVALLO | E22: JUAN CARVALLO JIMÉNEZ | G22: 161109 | H22: -577351
A23: adig/1284 | B23: 45805 | C23: 2940 | D23: Glosa : TDC CLP/USD CESAR MACHADO | E23: CESAR FELIPE MACHADO RIBEIRO LOPES | G23: 51519 | H23: -628870
A24: adig/1553 | B24: 45805 | C24: 3504 | D24: Glosa : TDC CLP JUAN sebastian CARVALLO | E24: JUAN CARVALLO JIMÉNEZ | G24: 229285 | H24: -858155
A25: adig/1187 | B25: 45813 | C25: 2810 | D25: Glosa : Payment: multiple itemsReembolsos Caroline Zorzi | E25: carolina zorzi | F25: 36610 | H25: -821545
A26: adig/1189 | B26: 45813 | C26: 2812 | D26: Glosa : Payment: ER - Jorge Moris25.4 - Reimbursable Expense - Vacuna Influenza | 25.4 - Reimbursable Expense - Vacuna Influenza | E26: JORGE MORIS JORDÁN | F26: 19500 | H26: -802045
A27: adig/1190 | B27: 45813 | C27: 2813 | D27: Glosa : Payment: ER - Caitlin Wheat25.5 - Reimbursable Expense - Reimbursement May 20... | 25.5 - Reimbursable Expense - Reimbursement May 20... | E27: CAITLIN JOY WHEAT | F27: 2300 | H27: -799745
A28: adig/1191 | B28: 45813 | C28: 2814 | D28: Glosa : Payment: ER - Sebastián Carvallo25.5 - Reimbursable Expense - Lundin Mining - Cand... | 25.5 - Reimbursable Expense - Lundin Mining - Cand... | E28: JUAN CARVALLO JIMÉNEZ | F28: 43000 | H28: -756745
A29: adig/1192 | B29: 45813 | C29: 2815 | D29: Glosa : Payment: ER - Marcelo Penna25.5 - Reimbursable Expense - Candelaria Site Visi... | 25.5 - Reimbursable Expense - Candelaria Site Visi... | E29: MARCELO PENNA SANTOS | F29: 20000 | H29: -736745
A30: adig/1202 | B30: 45820 | C30: 2858 | D30: Glosa : Bank Transfer to CC Caitlin Wheat. | E30: CAITLIN JOY WHEAT | F30: 450611 | H30: -286134
A31: adig/1203 | B31: 45820 | C31: 2859 | D31: Glosa : Bank Transfer to CC Katherinne Alarcon. | E31: KATHERINNE SILVANA ALARCON ESCOBAR | F31: 100449 | H31: -185685
A32: adig/1204 | B32: 45820 | C32: 2860 | D32: Glosa : Bank Transfer to CC Francisco Miranda. | E32: FRANCISCO MIRANDA RIADI | F32: 71087 | H32: -114598
A33: adig/1205 | B33: 45820 | C33: 2861 | D33: Glosa : Bank Transfer to CC Marcelo Penna. | E33: MARCELO PENNA SANTOS | F33: 79021 | H33: -35577
A34: adig/1206 | B34: 45820 | C34: 2862 | D34: Glosa : Bank Transfer to CC Sebastián Carvallo. | E34: JUAN CARVALLO JIMÉNEZ | F34: 210396 | H34: 174819
A35: adig/1207 | B35: 45820 | C35: 2863 | D35: Glosa : Bank Transfer to CC Carol Contreras. | E35: CAROL TATIANA CONTRERAS MUÑOZ | F35: 1231423 | H35: 1406242
A36: adig/1194 | B36: 45834 | C36: 2817 | D36: Glosa : Payment: ER - Jorge Moris25.6 - Reimbursable Expense - Estacionamiento Mine... | E36: JORGE MORIS JORDÁN | F36: 9000 | H36: 1415242
A37: adig/1256 | B37: 45834 | C37: 2912 | D37: Glosa : TDC CLP/USD CARLO CONTRERAS | E37: CAROL TATIANA CONTRERAS MUÑOZ | G37: 981428 | H37: 433814
A38: adig/1257 | B38: 45834 | C38: 2913 | D38: Glosa : TDC CLP/USD CESAR MACHADO | E38: CESAR FELIPE MACHADO RIBEIRO LOPES | G38: 1962244 | H38: -1528430
A39: adig/1258 | B39: 45834 | C39: 2914 | D39: Glosa : TDC CLP/USD FRANCISCO MIRANDA | E39: FRANCISCO MIRANDA RIADI | G39: 4322 | H39: -1532752
A40: adig/1259 | B40: 45834 | C40: 2915 | D40: Glosa : TDC CLP/USD JORGE MORIS | E40: JORGE MORIS JORDÁN | G40: 39636 | H40: -1572388
A41: adig/1260 | B41: 45834 | C41: 2916 | D41: Glosa : TDC CLP/USD KATHERINE ALARCON | E41: KATHERINNE SILVANA ALARCON ESCOBAR | G41: 2020460 | H41: -3592848
A42: adig/1261 | B42: 45834 | C42: 2917 | D42: Glosa : TDC CLP/USD MARCELO PENNA | E42: MARCELO PENNA SANTOS | G42: 87617 | H42: -3680465
A43: adig/1310 | B43: 45845 | C43: 3037 | D43: Glosa : Payment: multiple items Reembolsos Caroline Zorzi | E43: carolina zorzi | F43: 120730 | H43: -3559735
A44: adig/1311 | B44: 45845 | C44: 3041 | D44: Glosa : Payment: ER - Carol Contreras 25.7 - Reimbursable Expense - compra cervezas happ... | 25.7 - Reimbursable Expense - compra cervezas happ... | E44: CAROL TATIANA CONTRERAS MUÑOZ | F44: 33059 | H44: -3526676
A45: adig/1312 | B45: 45848 | C45: 3049 | D45: Glosa : Bank Transfer to CC Carol Contreras. | E45: CAROL TATIANA CONTRERAS MUÑOZ | F45: 981428 | H45: -2545248
A46: adig/1313 | B46: 45848 | C46: 3050 | D46: Glosa : Bank Transfer to CC Katherinne Alarcon. | E46: KATHERINNE SILVANA ALARCON ESCOBAR | F46: 2020460 | H46: -524788
A47: adig/1314 | B47: 45848 | C47: 3051 | D47: Glosa : Bank Transfer to CC Francisco Miranda. | E47: FRANCISCO MIRANDA RIADI | F47: 20216 | H47: -504572
A48: adig/1315 | B48: 45848 | C48: 3052 | D48: Glosa : Bank Transfer to CC Marcelo Penna. | E48: MARCELO PENNA SANTOS | F48: 87617 | H48: -416955
A49: adig/1333 | B49: 45867 | C49: 3092 | D49: Glosa : TDC CLP/USD CAROl CONTRERAS | E49: CAROL TATIANA CONTRERAS MUÑOZ | G49: 1861875 | H49: -2278830
A50: adig/1334 | B50: 45867 | C50: 3093 | D50: Glosa : TDC CLP/USD KATHERINE ALARCON | E50: KATHERINNE SILVANA ALARCON ESCOBAR | G50: 1476513 | H50: -3755343
A51: adig/1335 | B51: 45867 | C51: 3094 | D51: Glosa : TDC CLP JUAN sebastian CARVALLO | E51: JUAN CARVALLO JIMÉNEZ | G51: 293855 | H51: -4049198
A52: adig/1604 | B52: 45867 | C52: 3576 | D52: Glosa : TDC CLP/USD CESAR MACHADO | E52: CESAR FELIPE MACHADO RIBEIRO LOPES | F52: 2013763 | H52: -2035435
A53: adig/1604 | B53: 45867 | C53: 3576 | D53: Glosa : TDC CLP/USD CESAR MACHADO | E53: CESAR FELIPE MACHADO RIBEIRO LOPES | G53: 2831745 | H53: -4867180
A54: adig/1382 | B54: 45869 | C54: 3271 | D54: Glosa : RECLASIFICA GASTOS RENDICION Carol contreras | E54: CAROL TATIANA CONTRERAS MUÑOZ | G54: 1913232 | H54: -6780412
A55: adig/1383 | B55: 45869 | C55: 3272 | D55: Glosa : RECLASIFICA GASTOS RENDICION Carol contreras feb | E55: CAROL TATIANA CONTRERAS MUÑOZ | G55: 2328147 | H55: -9108559
A56: adig/1384 | B56: 45869 | C56: 3273 | D56: Glosa : RECLASIFICA GASTOS RENDICION Carol contreras mar | E56: CAROL TATIANA CONTRERAS MUÑOZ | G56: 1497172 | H56: -10605731
A57: adig/1386 | B57: 45869 | C57: 3275 | D57: Glosa : reclasifica tdc enero | E57: CAITLIN JOY WHEAT | G57: 260913 | H57: -10866644
A58: adig/1387 | B58: 45869 | C58: 3276 | D58: Glosa : RECLASIFICA TDC K. ALARCON ENERO | E58: KATHERINNE SILVANA ALARCON ESCOBAR | G58: 3388645 | H58: -14255289
A59: adig/1395 | B59: 45869 | C59: 3284 | D59: Glosa : apertura TDC F. MIRANDA ENERO | E59: FRANCISCO MIRANDA RIADI | G59: 181839 | H59: -14437128
A60: adig/1397 | B60: 45869 | C60: 3286 | D60: Glosa : APERTURA TDC J. SEBASTIAN C. ENERO | E60: JUAN CARVALLO JIMÉNEZ | G60: 650343 | H60: -15087471
A61: adig/1398 | B61: 45869 | C61: 3287 | D61: Glosa : APERTURA TDC M. PENNA ENERO | E61: MARCELO PENNA SANTOS | G61: 3652188 | H61: -18739659
A62: adig/1410 | B62: 45869 | C62: 3299 | D62: Glosa : APERTURA TDC C. W FEB | E62: CAITLIN JOY WHEAT | G62: 3872 | H62: -18743531
A63: adig/1411 | B63: 45869 | C63: 3300 | D63: Glosa : APERTURA TDC F. MIRANDA FEB | E63: FRANCISCO MIRANDA RIADI | G63: 819483 | H63: -19563014
A64: adig/1412 | B64: 45869 | C64: 3301 | D64: Glosa : APERTURA TDC K. ALARCON FEB | E64: KATHERINNE SILVANA ALARCON ESCOBAR | G64: 1326542 | H64: -20889556
... A85: adig/1537 | B85: 45869 | C85: 3465 | D85: Glosa : FONDO POR RENDIR VISA Francisco Miranda | E85: FRANCISCO MIRANDA RIADI | G85: 100602 | H85: -27352524
A86: Totales: | F86: 13666145 | G86: 41018669
A87: Saldo Final Al 31/07/2025: | H87: -27352524

Sheet 07102025
A1: Comprobante | B1: Fec. Doc. | C1: Voucher | E1: Titular | F1: T.Doc/Nro | G1: Debe | H1: Haber | I1: Acumulado
A2: adig/991 | B2: 45693 | C2: 2278 | D2: Glosa : Pago Tarjeta de Credito | E2: KATHERINNE SILVANA ALARCON ESCOBAR | G2: 1611355 | I2: 1611355
A3: adig/993 | B3: 45693 | C3: 2280 | D3: Glosa : Pago Tarjeta de Credito | E3: MARCELO PENNA SANTOS | G3: 3652188 | I3: 5263543
A4: adig/994 | B4: 45701 | C4: 2281 | D4: Glosa : Pago Tarjeta de Credito | E4: CAITLIN JOY WHEAT | G4: 260913 | I4: 5524456
A5: adig/995 | B5: 45701 | C5: 2282 | D5: Glosa : Pago Tarjeta de Credito | E5: JUAN CARVALLO JIMÉNEZ | G5: 650343 | I5: 6174799
A6: adig/996 | B6: 45701 | C6: 2283 | D6: Glosa : Pago Tarjeta de Credito | E6: FRANCISCO MIRANDA RIADI | G6: 181839 | I6: 6356638
A7: adig/997 | B7: 45701 | C7: 2284 | D7: Glosa : Pago Tarjeta de Credito | E7: KATHERINNE SILVANA ALARCON ESCOBAR | G7: 1777290 | I7: 8133928
A8: adig/1053 | B8: 45729 | C8: 2342 | D8: Glosa : Pago tarjeta de Credito | E8: CAITLIN JOY WHEAT | G8: 3872 | I8: 8137800
A9: adig/1054 | B9: 45729 | C9: 2343 | D9: Glosa : Pago tarjeta de Credito | E9: JUAN CARVALLO JIMÉNEZ | G9: 20962 | I9: 8158762
A10: adig/1055 | B10: 45729 | C10: 2344 | D10: Glosa : Pago tarjeta de Credito | E10: FRANCISCO MIRANDA RIADI | G10: 819483 | I10: 8978245
A11: plib/8 | B11: 45750 | C11: 2493 | D11: Glosa : reembolso Marcelo Penna | E11: MARCELO PENNA SANTOS | G11: 121678 | I11: 9099923
A12: plib/22 | B12: 45762 | C12: 2508 | D12: Glosa : Pago tarjeta de credio Francisco Miranda | E12: FRANCISCO MIRANDA RIADI | G12: 221541 | I12: 9321464
A13: plib/23 | B13: 45762 | C13: 2509 | D13: Glosa : Pago tarjeta de credito Katherinne Alarcon | E13: KATHERINNE SILVANA ALARCON ESCOBAR | G13: 46444 | I13: 9367908
... A16: plib/26 | B16: 45762 | C16: 2512 | D16: Glosa : Pago Tarjeta de credito Marcelo Penna | E16: MARCELO PENNA SANTOS | G16: 2623654 | I16: 13794176
A17: adig/1114 | B17: 45772 | C17: 2553 | D17: Glosa : TDC CLP_USD C.Contreras | E17: CAROL TATIANA CONTRERAS MUÑOZ | H17: 3070443 | I17: 10723733
A18: adig/1115 | B18: 45772 | C18: 2554 | D18: Glosa : TDC CLP Marcelo PENNA | E18: MARCELO PENNA SANTOS | H18: 1901018 | I18: 8822715
A19: adig/1116 | B19: 45772 | C19: 2555 | D19: Glosa : TDC CLP JUAN CARVALLO | E19: JUAN CARVALLO JIMÉNEZ | H19: 122074 | I19: 8700641
A20: adig/1117 | B20: 45772 | C20: 2556 | D20: Glosa : TDC CLP-USD CAITLIN WHEAT | E20: CAITLIN JOY WHEAT | H20: 100022 | I20: 8600619
A21: adig/1122 | B21: 45772 | C21: 2561 | D21: Glosa : TDC CLP-USD CAtherine alaracon | E21: KATHERINNE SILVANA ALARCON ESCOBAR | H21: 806870 | I21: 7793749
A22: adig/1283 | B22: 45772 | C22: 2939 | D22: Glosa : TDC CLP/USD FRANCISCO MIRANDA | E22: FRANCISCO MIRANDA RIADI | H22: 5014 | I22: 7788735
A23: adig/1161 | B23: 45785 | C23: 2721 | D23: Glosa : Payment: ER - Marcelo Penna25.4 - Reimbursable Expense - Apr 2025 - Reimbursa... | E23: MARCELO PENNA SANTOS | G23: 22780 | I23: 7811515
A24: adig/1163 | B24: 45785 | C24: 2723 | D24: Glosa : Payment: ER - Katherinne Alarcon25.3 - Reimbursable Expense - Viaje Lima | 25.3 - Reimbursable Expense - Viaje Lima | E24: KATHERINNE SILVANA ALARCON ESCOBAR | G24: 15336 | I24: 7826851
A25: adig/1170 | B25: 45792 | C25: 2742 | D25: Glosa : Bank Transfer to CC Caitlin Wheat. | E25: CAITLIN JOY WHEAT | G25: 100022 | I25: 7926873
A26: adig/1171 | B26: 45792 | C26: 2743 | D26: Glosa : Bank Transfer to CC Carol Contreras. | E26: CAROL TATIANA CONTRERAS MUÑOZ | G26: 3070443 | I26: 10997316
A27: adig/1172 | B27: 45792 | C27: 2744 | D27: Glosa : Bank Transfer to CC Katherinne Alarcon. | E27: KATHERINNE SILVANA ALARCON ESCOBAR | G27: 806870 | I27: 11804186
A28: adig/1173 | B28: 45792 | C28: 2745 | D28: Glosa : Bank Transfer to CC Francisco Miranda. | E28: FRANCISCO MIRANDA RIADI | G28: 5014 | I28: 11809200
A29: adig/1174 | B29: 45792 | C29: 2746 | D29: Glosa : Bank Transfer to CC Sebastián Carvallo. | E29: JUAN CARVALLO JIMÉNEZ | G29: 72314 | I29: 11881514
A30: adig/1175 | B30: 45792 | C30: 2749 | D30: Glosa : Bank Transfer to CC Marcelo Penna. | E30: MARCELO PENNA SANTOS | G30: 1901018 | I30: 13782532
A31: adig/1250 | B31: 45805 | C31: 2906 | D31: Glosa : TDC CLP-USD CAITLIN WHEAT | E31: CAITLIN JOY WHEAT | H31: 450611 | I31: 13331921
A32: adig/1251 | B32: 45805 | C32: 2907 | D32: Glosa : TDC CLP_USD C.Contreras | E32: CAROL TATIANA CONTRERAS MUÑOZ | H32: 1231423 | I32: 12100498
A33: adig/1252 | B33: 45805 | C33: 2908 | D33: Glosa : Tarjeta de Credito F.Miranda | E33: FRANCISCO MIRANDA RIADI | H33: 71087 | I33: 12029411
A34: adig/1253 | B34: 45805 | C34: 2909 | D34: Glosa : TDC pesos USD Katherine Alarcon | E34: KATHERINNE SILVANA ALARCON ESCOBAR | H34: 100449 | I34: 11928962
A35: adig/1254 | B35: 45805 | C35: 2910 | D35: Glosa : TDC CLP/USD Marcelo PENNA | E35: MARCELO PENNA SANTOS | H35: 79021 | I35: 11849941
A36: adig/1255 | B36: 45805 | C36: 2911 | D36: Glosa : TDC CLP JUAN sebastian CARVALLO | E36: JUAN CARVALLO JIMÉNEZ | H36: 161109 | I36: 11688832
A37: adig/1284 | B37: 45805 | C37: 2940 | D37: Glosa : TDC CLP/USD CESAR MACHADO | E37: CESAR FELIPE MACHADO RIBEIRO LOPES | H37: 51519 | I37: 11637313
A38: adig/1553 | B38: 45805 | C38: 3504 | D38: Glosa : TDC CLP JUAN sebastian CARVALLO | E38: JUAN CARVALLO JIMÉNEZ | H38: 229285 | I38: 11408028
A39: adig/1187 | B39: 45813 | C39: 2810 | D39: Glosa : Payment: multiple itemsReembolsos Caroline Zorzi | E39: DESWIK CHILE SPA | G39: 36610 | I39: 11444638
A40: adig/1189 | B40: 45813 | C40: 2812 | D40: Glosa : Payment: ER - Jorge Moris25.4 - Reimbursable Expense - Vacuna Influenza | 25.4 - Reimbursable Expense - Vacuna Influenza | E40: JORGE MORIS JORDÁN | G40: 19500 | I40: 11464138
A41: adig/1190 | B41: 45813 | C41: 2813 | D41: Glosa : Payment: ER - Caitlin Wheat25.5 - Reimbursable Expense - Reimbursement May 20... | 25.5 - Reimbursable Expense - Reimbursement May 20... | E41: CAITLIN JOY WHEAT | G41: 2300 | I41: 11466438
A42: adig/1191 | B42: 45813 | C42: 2814 | D42: Glosa : Payment: ER - Sebastián Carvallo25.5 - Reimbursable Expense - Lundin Mining - Cand... | 25.5 - Reimbursable Expense - Lundin Mining - Cand... | E42: JUAN CARVALLO JIMÉNEZ | G42: 43000 | I42: 11509438
A43: adig/1192 | B43: 45813 | C43: 2815 | D43: Glosa : Payment: ER - Marcelo Penna25.5 - Reimbursable Expense - Candelaria Site Visi... | 25.5 - Reimbursable Expense - Candelaria Site Visi... | E43: MARCELO PENNA SANTOS | G43: 20000 | I43: 11529438
A44: adig/1202 | B44: 45820 | C44: 2858 | D44: Glosa : Bank Transfer to CC Caitlin Wheat. | E44: CAITLIN JOY WHEAT | G44: 450611 | I44: 11980049
A45: adig/1203 | B45: 45820 | C45: 2859 | D45: Glosa : Bank Transfer to CC Katherinne Alarcon. | E45: KATHERINNE SILVANA ALARCON ESCOBAR | G45: 100449 | I45: 12080498
A46: adig/1204 | B46: 45820 | C46: 2860 | D46: Glosa : Bank Transfer to CC Francisco Miranda. | E46: FRANCISCO MIRANDA RIADI | G46: 71087 | I46: 12151585
A47: adig/1205 | B47: 45820 | C47: 2861 | D47: Glosa : Bank Transfer to CC Marcelo Penna. | E47: MARCELO PENNA SANTOS | G47: 79021 | I47: 12230606
A48: adig/1206 | B48: 45820 | C48: 2862 | D48: Glosa : Bank Transfer to CC Sebastián Carvallo. | E48: JUAN CARVALLO JIMÉNEZ | G48: 210396 | I48: 12441002
A49: adig/1207 | B49: 45820 | C49: 2863 | D49: Glosa : Bank Transfer to CC Carol Contreras. | E49: CAROL TATIANA CONTRERAS MUÑOZ | G49: 1231423 | I49: 13672425
A50: adig/1194 | B50: 45834 | C50: 2817 | D50: Glosa : Payment: ER - Jorge Moris25.6 - Reimbursable Expense - Estacionamiento Mine... | E50: JORGE MORIS JORDÁN | G50: 9000 | I50: 13681425
A51: adig/1256 | B51: 45834 | C51: 2912 | D51: Glosa : TDC CLP/USD CARLO CONTRERAS | E51: CAROL TATIANA CONTRERAS MUÑOZ | H51: 981428 | I51: 12699997
A52: adig/1257 | B52: 45834 | C52: 2913 | D52: Glosa : TDC CLP/USD CESAR MACHADO | E52: CESAR FELIPE MACHADO RIBEIRO LOPES | H52: 1962244 | I52: 10737753
A53: adig/1258 | B53: 45834 | C53: 2914 | D53: Glosa : TDC CLP/USD FRANCISCO MIRANDA | E53: FRANCISCO MIRANDA RIADI | H53: 4322 | I53: 10733431
A54: adig/1259 | B54: 45834 | C54: 2915 | D54: Glosa : TDC CLP/USD JORGE MORIS | E54: JORGE MORIS JORDÁN | H54: 39636 | I54: 10693795
A55: adig/1260 | B55: 45834 | C55: 2916 | D55: Glosa : TDC CLP/USD KATHERINE ALARCON | E55: KATHERINNE SILVANA ALARCON ESCOBAR | H55: 2020460 | I55: 8673335
A56: adig/1261 | B56: 45834 | C56: 2917 | D56: Glosa : TDC CLP/USD MARCELO PENNA | E56: MARCELO PENNA SANTOS | H56: 87617 | I56: 8585718
A57: adig/1310 | B57: 45845 | C57: 3037 | D57: Glosa : Payment: multiple items Reembolsos Caroline Zorzi | E57: DESWIK CHILE SPA | G57: 120730 | I57: 8706448
A58: adig/1311 | B58: 45845 | C58: 3041 | D58: Glosa : Payment: ER - Carol Contreras 25.7 - Reimbursable Expense - compra cervezas happ... | 25.7 - Reimbursable Expense - compra cervezas happ... | E58: CAROL TATIANA CONTRERAS MUÑOZ | G58: 33059 | I58: 8739507
A59: adig/1312 | B59: 45848 | C59: 3049 | D59: Glosa : Bank Transfer to CC Carol Contreras. | E59: CAROL TATIANA CONTRERAS MUÑOZ | G59: 981428 | I59: 9720935
A60: adig/1313 | B60: 45848 | C60: 3050 | D60: Glosa : Bank Transfer to CC Katherinne Alarcon. | E60: KATHERINNE SILVANA ALARCON ESCOBAR | G60: 2020460 | I60: 11741395
A61: adig/1314 | B61: 45848 | C61: 3051 | D61: Glosa : Bank Transfer to CC Francisco Miranda. | E61: FRANCISCO MIRANDA RIADI | G61: 20216 | I61: 11761611
A62: adig/1315 | B62: 45848 | C62: 3052 | D62: Glosa : Bank Transfer to CC Marcelo Penna. | E62: MARCELO PENNA SANTOS | G62: 87617 | I62: 11849228
A63: adig/1333 | B63: 45867 | C63: 3092 | D63: Glosa : TDC CLP/USD CAROl CONTRERAS | E63: CAROL TATIANA CONTRERAS MUÑOZ | H63: 1861875 | I63: 9987353
A64: adig/1334 | B64: 45867 | C64: 3093 | D64: Glosa : TDC CLP/USD KATHERINE ALARCON | E64: KATHERINNE SILVANA ALARCON ESCOBAR | H64: 1476513 | I64: 8510840
A65: adig/1335 | B65: 45867 | C65: 3094 | D65: Glosa : TDC CLP JUAN sebastian CARVALLO | E65: JUAN CARVALLO JIMÉNEZ | H65: 293855 | I65: 8216985
A66: adig/1604 | B66: 45867 | C66: 3576 | D66: Glosa : TDC CLP/USD CESAR MACHADO | E66: CESAR FELIPE MACHADO RIBEIRO LOPES | G66: 2013763 | I66: 10230748
A67: adig/1604 | B67: 45867 | C67: 3576 | D67: Glosa : TDC CLP/USD CESAR MACHADO | E67: CESAR FELIPE MACHADO RIBEIRO LOPES | H67: 2831745 | I67: 7399003
A68: adig/1382 | B68: 45869 | C68: 3271 | D68: Glosa : RECLASIFICA GASTOS RENDICION Carol contreras | E68: CAROL TATIANA CONTRERAS MUÑOZ | H68: 1913232 | I68: 5485771
A69: adig/1383 | B69: 45869 | C69: 3272 | D69: Glosa : RECLASIFICA GASTOS RENDICION Carol contreras feb | E69: CAROL TATIANA CONTRERAS MUÑOZ | H69: 2328147 | I69: 3157624
A70: adig/1384 | B70: 45869 | C70: 3273 | D70: Glosa : RECLASIFICA GASTOS RENDICION Carol contreras mar | E70: CAROL TATIANA CONTRERAS MUÑOZ | H70: 1497172 | I70: 1660452
A71: adig/1386 | B71: 45869 | C71: 3275 | D71: Glosa : reclasifica tdc enero | E71: CAITLIN JOY WHEAT | H71: 260913 | I71: 1399539
A72: adig/1387 | B72: 45869 | C72: 3276 | D72: Glosa : RECLASIFICA TDC K. ALARCON ENERO | E72: KATHERINNE SILVANA ALARCON ESCOBAR | H72: 3388645 | I72: -1989106
A73: adig/1395 | B73: 45869 | C73: 3284 | D73: Glosa : apertura TDC F. MIRANDA ENERO | E73: FRANCISCO MIRANDA RIADI | H73: 181839 | I73: -2170945
A74: adig/1397 | B74: 45869 | C74: 3286 | D74: Glosa : APERTURA TDC J. SEBASTIAN C. ENERO | E74: JUAN CARVALLO JIMÉNEZ | H74: 650343 | I74: -2821288
A75: adig/1398 | B75: 45869 | C75: 3287 | D75: Glosa : APERTURA TDC M. PENNA ENERO | E75: MARCELO PENNA SANTOS | H75: 3652188 | I75: -6473476
A76: adig/1410 | B76: 45869 | C76: 3299 | D76: Glosa : APERTURA TDC C. W FEB | E76: CAITLIN JOY WHEAT | H76: 3872 | I76: -6477348
A77: adig/1411 | B77: 45869 | C77: 3300 | D77: Glosa : APERTURA TDC F. MIRANDA FEB | E77: FRANCISCO MIRANDA RIADI | H77: 819483 | I77: -7296831
A78: adig/1412 | B78: 45869 | C78: 3301 | D78: Glosa : APERTURA TDC K. ALARCON FEB | E78: KATHERINNE SILVANA ALARCON ESCOBAR | H78: 1326542 | I78: -8623373
... A99: adig/1537 | B99: 45869 | C99: 3465 | D99: Glosa : FONDO POR RENDIR VISA Francisco Miranda | E99: FRANCISCO MIRANDA RIADI | H99: 100602 | I99: -15088640
A100: adig/1602 | B100: 45869 | C100: 3574 | D100: Glosa : compensa prov | E100: CAROL TATIANA CONTRERAS MUÑOZ | G100: 5414035 | I100: -9674605
A101: adig/1602 | B101: 45869 | C101: 3574 | D101: Glosa : compensa prov | E101: CAITLIN JOY WHEAT | G101: 233279 | I101: -9441326
A102: adig/1602 | B102: 45869 | C102: 3574 | D102: Glosa : compensa prov | E102: FRANCISCO MIRANDA RIADI | G102: 84808 | I102: -9356518
A103: adig/1602 | B103: 45869 | C103: 3574 | D103: Glosa : compensa prov | E103: JUAN CARVALLO JIMÉNEZ | G103: 594864 | I103: -8761654
A104: adig/1602 | B104: 45869 | C104: 3574 | D104: Glosa : compensa prov | E104: KATHERINNE SILVANA ALARCON ESCOBAR | G104: 1326542 | I104: -7435112
A105: adig/1602 | B105: 45869 | C105: 3574 | D105: Glosa : compensa prov | E105: JORGE MORIS JORDÁN | H105: 5112 | I105: -7440224
A106: adig/1602 | B106: 45869 | C106: 3574 | D106: Glosa : compensa prov | E106: MARCELO PENNA SANTOS | G106: 1078540 | I106: -6361684
A107: adig/1602 | B107: 45869 | C107: 3574 | D107: Glosa : compensa prov caroline zorzi | E107: DESWIK CHILE SPA | H107: 157340 | I107: -6519024

Sheet a sep
A1: Comprobante | B1: Fec. Doc. | C1: Voucher | E1: Titular | F1: T.Doc/Nro | G1: Debe | H1: Haber | I1: Acumulado
A2: adig/1372 | B2: 45876 | C2: 3256 | D2: Glosa : Reembolsos Sebastian Carvallo | E2: JUAN SEBASTIAN CARVALLO JIMÉNEZ | G2: 87720 | I2: -6429422
A3: adig/1373 | B3: 45882 | C3: 3257 | D3: Glosa : MP´s credit card payment | E3: MARCELO PENNA SANTOS | G3: 8406 | I3: -6421016
A4: adig/1374 | B4: 45882 | C4: 3258 | D4: Glosa : Carol's cc payment | E4: CAROL TATIANA CONTRERAS MUÑOZ | G4: 1861875 | I4: -4559141
A5: adig/1375 | B5: 45882 | C5: 3259 | D5: Glosa : Sebastian´s cc payment | E5: JUAN SEBASTIAN CARVALLO JIMÉNEZ | G5: 293855 | I5: -4265286
A6: adig/1376 | B6: 45882 | C6: 3260 | D6: Glosa : KA´s credit card payment | E6: KATHERINNE SILVANA ALARCON ESCOBAR | G6: 1476513 | I6: -2788773
A7: adig/1377 | B7: 45891 | C7: 3264 | D7: Glosa : CM´s credit card payment | E7: CESAR FELIPE MACHADO RIBEIRO LOPES | G7: 2831745 | I7: 42972
A8: adig/1378 | B8: 45891 | C8: 3265 | D8: Glosa : JM´s credit card payment | E8: JORGE MORIS JORDÁN | G8: 44748 | I8: 87720
A9: adig/1551 | B9: 45896 | C9: 3484 | D9: Glosa : TDC CLP/USD CAROl CONTRERAS | E9: CAROL TATIANA CONTRERAS MUÑOZ | H9: 607271 | I9: -519551
A10: adig/1552 | B10: 45896 | C10: 3496 | D10: Glosa : TDC CLP/USD CESAR MACHADO | E10: CESAR FELIPE MACHADO RIBEIRO LOPES | H10: 39966 | I10: -559517
A11: adig/1554 | B11: 45896 | C11: 3506 | D11: Glosa : TDC CLP/USD KATHERINE ALARCON | E11: KATHERINNE SILVANA ALARCON ESCOBAR | H11: 408970 | I11: -968487
A12: adig/1555 | B12: 45896 | C12: 3507 | D12: Glosa : TDC CLP/USD JORGE MORIS | E12: JORGE MORIS JORDÁN | H12: 4257 | I12: -972744
A13: adig/1553 | B13: 45897 | C13: 3504 | D13: Glosa : TDC CLP JUAN sebastian CARVALLO | E13: JUAN SEBASTIAN CARVALLO JIMÉNEZ | H13: 37917 | I13: -1010661
A14: adig/1550 | B14: 45900 | C14: 3483 | D14: Glosa : TDC CLP-USD CAITLIN WHEAT | E14: CAITLIN JOY WHEAT | H14: 965161 | I14: -1975822
A15: adig/1565 | B15: 45904 | C15: 3529 | D15: Glosa : 25.8 - Reimbursable Expense - Reimbursements Augus... | 25.8 - Reimbursable Expense - Reimbursements Augus... | E15: CAITLIN JOY WHEAT | G15: 78080 | I15: -1897742
A16: adig/1597 | B16: 45905 | C16: 3569 | D16: Glosa : 25.8 - Reimbursable Expense - Viaje BHP Assistenci... | E16: DESWIK CHILE SPA | G16: 248681 | I16: -1649061
A17: adig/1566 | B17: 45911 | C17: 3530 | D17: Glosa : 25.9 - Reimbursable Expense - Reimbursement - Empa... | 25.9 - Reimbursable Expense - Reimbursement - Empa... | E17: CAITLIN JOY WHEAT | G17: 67000 | I17: -1582061
A18: adig/1567 | B18: 45911 | C18: 3531 | D18: Glosa : Carol's cc payment | E18: CAROL TATIANA CONTRERAS MUÑOZ | G18: 607270 | I18: -974791
A19: adig/1568 | B19: 45911 | C19: 3532 | D19: Glosa : JM´s credit card payment | E19: JORGE MORIS JORDÁN | G19: 4267 | I19: -970524
A20: adig/1569 | B20: 45911 | C20: 3533 | D20: Glosa : 25.9 - Reimbursable Expense - Reimbursement - Empa... | 25.9 - Reimbursable Expense - Reimbursement - Empa... | E20: CAITLIN JOY WHEAT | G20: 965161 | I20: -5363
A21: adig/1570 | B21: 45911 | C21: 3534 | D21: Glosa : SEBASTIAN CARVALLO | E21: JUAN SEBASTIAN CARVALLO JIMÉNEZ | G21: 37919 | I21: 32556
A22: adig/1571 | B22: 45911 | C22: 3535 | D22: Glosa : Katherinnes credit card payment | E22: KATHERINNE SILVANA ALARCON ESCOBAR | G22: 408970 | I22: 441526
A23: adig/1572 | B23: 45911 | C23: 3536 | D23: Glosa : CM´s credit card payment | E23: CESAR FELIPE MACHADO RIBEIRO LOPES | G23: 36966 | I23: 478492
A24: adig/1599 | B24: 45917 | C24: 3571 | D24: Glosa : Reserva seminario COL | E24: DESWIK CHILE SPA | G24: 1453361 | I24: 1931853
A25: adig/1574 | B25: 45925 | C25: 3538 | D25: Glosa : 25.8 - Reimbursable Expense - Taxi de hotel Atacam... | 25.8 - Reimbursable Expense - Taxi de hotel Atacam... | E25: ANTONIETA GONZALEZ OLIVEROS | G25: 44839 | I25: 1976692
A26: adig/1576 | B26: 45925 | C26: 3540 | D26: Glosa : 25.8 - Reimbursable Expense - Agosto - Implementac... | 25.8 - Reimbursable Expense - Agosto - Implementac... | E26: DESWIK CHILE SPA | G26: 39430 | I26: 2016122
A27: adig/1607 | B27: 45926 | C27: 3579 | D27: Glosa : TDC CLP JUAN sebastian CARVALLO | E27: JUAN SEBASTIAN CARVALLO JIMÉNEZ | H27: 50192 | I27: 1965930
A28: adig/1608 | B28: 45926 | C28: 3580 | D28: Glosa : TDC CLP/USD KATHERINE ALARCON | E28: KATHERINNE SILVANA ALARCON ESCOBAR | H28: 925857 | I28: 1040073
A29: adig/1609 | B29: 45926 | C29: 3581 | D29: Glosa : TDC CLP-USD CAITLIN WHEAT | E29: CAITLIN JOY WHEAT | H29: 943249 | I29: 96824
A30: adig/1610 | B30: 45926 | C30: 3582 | D30: Glosa : TDC CLP/USD CESAR MACHADO | E30: CESAR FELIPE MACHADO RIBEIRO LOPES | H30: 491676 | I30: -394852
D31: Totales:
A32: Totales: | D32: Saldo Final Al 30/09/2025: | G32: 10596806 | H32: 4474516
A33: Saldo Final Al 30/09/2025: | D33: Cuenta: 2114 TARJETAS DE CREDITO USD | I33: -394852
A34: Cuenta: 2114 TARJETAS DE CREDITO USD | D34: Moneda de la Cta: Dólares Americanos
A35: Moneda de la Cta: Dólares Americanos | D35: Comprobante
A36: Comprobante | B36: Fec. Doc. | C36: Voucher | D36: 0 | E36: Titular | F36: T.Doc/Nro | G36: Debe | H36: Haber | I36: Acumulado
A37: adig/1552 | B37: 45896 | C37: 3496 | D37: Glosa : TDC CLP/USD CESAR MACHADO | E37: CESAR FELIPE MACHADO RIBEIRO LOPES | H37: 479.8 | I37: -479.8
A38: adig/1554 | B38: 45896 | C38: 3506 | D38: Glosa : TDC CLP/USD KATHERINE ALARCON | E38: KATHERINNE SILVANA ALARCON ESCOBAR | H38: 487.61 | I38: -967.41
A39: adig/1553 | B39: 45897 | C39: 3504 | D39: Glosa : TDC CLP JUAN sebastian CARVALLO | E39: JUAN SEBASTIAN CARVALLO JIMÉNEZ | H39: 203.9 | I39: -1171.31
A40: adig/1607 | B40: 45926 | C40: 3579 | D40: Glosa : TDC CLP JUAN sebastian CARVALLO | E40: JUAN SEBASTIAN CARVALLO JIMÉNEZ | H40: 239.08 | I40: -1410.39
A41: adig/1607 | B41: 45926 | C41: 3579 | D41: Glosa : TDC CLP JUAN sebastian CARVALLO | E41: JUAN SEBASTIAN CARVALLO JIMÉNEZ | G41: 39.94 | I41: -1370.45
A42: adig/1608 | B42: 45926 | C42: 3580 | D42: Glosa : TDC CLP/USD KATHERINE ALARCON | E42: KATHERINNE SILVANA ALARCON ESCOBAR | G42: 487.61 | I42: -882.84
A43: adig/1608 | B43: 45926 | C43: 3580 | D43: Glosa : TDC CLP/USD KATHERINE ALARCON | E43: KATHERINNE SILVANA ALARCON ESCOBAR | H43: 137.11 | I43: -1019.95
A44: adig/1610 | B44: 45926 | C44: 3582 | D44: Glosa : TDC CLP/USD CESAR MACHADO | E44: CESAR FELIPE MACHADO RIBEIRO LOPES | G44: 479.8 | I44: -540.15
A45: adig/1610 | B45: 45926 | C45: 3582 | D45: Glosa : TDC CLP/USD CESAR MACHADO | E45: CESAR FELIPE MACHADO RIBEIRO LOPES | H45: 79.35 | I45: -619.5
A46: Totales: | G46: 1007.35 | H46: 1626.85
A47: Saldo Final Al 30/09/2025: | I47: -619.5
A49: MGMayorContableOF_CtaRel

Sheet 9
A1: Comprobante | B1: Fec. Doc. | C1: Voucher | E1: Titular | F1: T.Doc/Nro | G1: Debe | H1: Haber | I1: Acumulado
A2: adig/1122 | B2: 45772 | C2: 2561 | D2: Glosa : TDC CLP-USD CAtherine alaracon | E2: KATHERINNE SILVANA ALARCON ESCOBAR | H2: 806870 | I2: =-H2 -> -806870
A3: adig/1172 | B3: 45792 | C3: 2744 | D3: Glosa : Bank Transfer to CC Katherinne Alarcon. | E3: KATHERINNE SILVANA ALARCON ESCOBAR | G3: 806870 | I3: =+I2+G3 -> 0
A4: adig/1122 | B4: 45772 | C4: 2561 | D4: Glosa : TDC CLP-USD CAtherine alaracon | E4: KATHERINNE SILVANA ALARCON ESCOBAR | H4: 706.36 | I4: =-H4 -> -706.36
A5: adig/1122 | B5: 45772 | C5: 2561 | D5: Glosa : TDC CLP-USD CAtherine alaracon | E5: KATHERINNE SILVANA ALARCON ESCOBAR | G5: 706.36 | I5: =+I4-G5 -> -1412.72
A6: adig/1253 | B6: 45805 | C6: 2909 | D6: Glosa : TDC pesos USD Katherine Alarcon | E6: KATHERINNE SILVANA ALARCON ESCOBAR | H6: 100449 | I6: =-H6 -> -100449
A7: adig/1253 | B7: 45805 | C7: 2909 | D7: Glosa : TDC pesos USD Katherine Alarcon | E7: KATHERINNE SILVANA ALARCON ESCOBAR | H7: 1710.39 | I7: =-H7 -> -1710.39
A8: adig/1203 | B8: 45820 | C8: 2859 | D8: Glosa : Bank Transfer to CC Katherinne Alarcon. | E8: KATHERINNE SILVANA ALARCON ESCOBAR | G8: 100449 | I8: =I6+G8 -> 0
A9: adig/1260 | B9: 45834 | C9: 2916 | D9: Glosa : TDC CLP/USD KATHERINE ALARCON | E9: KATHERINNE SILVANA ALARCON ESCOBAR | G9: 1710.39 | I9: =I7+G9 -> 0
A10: adig/1260 | B10: 45834 | C10: 2916 | D10: Glosa : TDC CLP/USD KATHERINE ALARCON | E10: KATHERINNE SILVANA ALARCON ESCOBAR | H10: 2020460 | I10: =-H10 -> -2020460
A11: adig/1313 | B11: 45848 | C11: 3050 | D11: Glosa : Bank Transfer to CC Katherinne Alarcon. | E11: KATHERINNE SILVANA ALARCON ESCOBAR | G11: 2020460 | I11: =+I10+G11 -> 0
A12: adig/1334 | B12: 45867 | C12: 3093 | D12: Glosa : TDC CLP/USD KATHERINE ALARCON | E12: KATHERINNE SILVANA ALARCON ESCOBAR | H12: 1476513 | I12: =-H12 -> -1476513
A13: adig/1387 | B13: 45869 | C13: 3276 | D13: Glosa : RECLASIFICA TDC K. ALARCON ENERO | E13: KATHERINNE SILVANA ALARCON ESCOBAR | H13: 3388645 | I13: =I12+G13-H13 -> -4865158
A14: adig/1412 | B14: 45869 | C14: 3301 | D14: Glosa : APERTURA TDC K. ALARCON FEB | E14: KATHERINNE SILVANA ALARCON ESCOBAR | H14: 1326542 | I14: =I13+G14-H14 -> -6191700
A15: adig/1417 | B15: 45869 | C15: 3306 | D15: Glosa : APERTURA TDC K. ALARCON MARZO | E15: KATHERINNE SILVANA ALARCON ESCOBAR | H15: 46444 | I15: =I14+G15-H15 -> -6238144
A16: adig/1260 | B16: 45834 | C16: 2916 | D16: Glosa : TDC CLP/USD KATHERINE ALARCON | E16: KATHERINNE SILVANA ALARCON ESCOBAR | H16: 664.62 | I16: =I7+G16-H16 -> -2375.01 | J16: =H16*936.29 -> 622277.06
A17: adig/1334 | B17: 45867 | C17: 3093 | D17: Glosa : TDC CLP/USD KATHERINE ALARCON | E17: KATHERINNE SILVANA ALARCON ESCOBAR | G17: 664.62 | I17: =I9+G17-H17 -> 664.62
G18: =SUM(G2:G17) -> 2930860.4 | H18: =SUM(H2:H17) -> 9169004.4 | I18: =H18-G18 -> 6238144
D21: 2114-09 - CC Katherinne Alarcon | F21: 1476513
B23: Fec. Doc. | C23: Voucher | E23: Titular | G23: Debe | H23: Haber | I23: Acumulado
B24: 45772 | C24: 2561 | D24: Glosa : TDC CLP-USD CAtherine alaracon | E24: KATHERINNE SILVANA ALARCON ESCOBAR | H24: 806870 | I24: -4472434
B25: 45785 | C25: 2723 | D25: Glosa : Payment: ER - Katherinne Alarcon25.3 - Reimbursable Expense - Viaje Lima | 25.3 - Reimbursable Expense - Viaje Lima | E25: KATHERINNE SILVANA ALARCON ESCOBAR | G25: 15336 | I25: -4439332
B26: 45792 | C26: 2744 | D26: Glosa : Bank Transfer to CC Katherinne Alarcon. | E26: KATHERINNE SILVANA ALARCON ESCOBAR | G26: 806870 | I26: -461997
B27: 45805 | C27: 2909 | D27: Glosa : TDC pesos USD Katherine Alarcon | E27: KATHERINNE SILVANA ALARCON ESCOBAR | H27: 100449 | I27: -337221
B28: 45820 | C28: 2859 | D28: Glosa : Bank Transfer to CC Katherinne Alarcon. | E28: KATHERINNE SILVANA ALARCON ESCOBAR | G28: 100449 | I28: -185685
B29: 45834 | C29: 2916 | D29: Glosa : TDC CLP/USD KATHERINE ALARCON | E29: KATHERINNE SILVANA ALARCON ESCOBAR | H29: 2020460 | I29: -3592848
B30: 45848 | C30: 3050 | D30: Glosa : Bank Transfer to CC Katherinne Alarcon. | E30: KATHERINNE SILVANA ALARCON ESCOBAR | G30: 2020460 | I30: -524788
B31: 45867 | C31: 3093 | D31: Glosa : TDC CLP/USD KATHERINE ALARCON | E31: KATHERINNE SILVANA ALARCON ESCOBAR | H31: 1476513 | I31: -3755343
B32: 45869 | C32: 3276 | D32: Glosa : RECLASIFICA TDC K. ALARCON ENERO | E32: KATHERINNE SILVANA ALARCON ESCOBAR | H32: 3388645 | I32: -14255289
B33: 45869 | C33: 3301 | D33: Glosa : APERTURA TDC K. ALARCON FEB | E33: KATHERINNE SILVANA ALARCON ESCOBAR | H33: 1326542 | I33: -20889556 | J33: 2011
B34: 45869 | C34: 3306 | D34: Glosa : APERTURA TDC K. ALARCON MARZO | E34: KATHERINNE SILVANA ALARCON ESCOBAR | H34: 46444 | I34: -22199356
B35: 45869 | C35: 3451 | D35: Glosa : reclasifica CC Expense | E35: KATHERINNE SILVANA ALARCON ESCOBAR | H35: 15336 | I35: -24836047
B37: Fec. Doc. | C37: Voucher | E37: Titular | F37: T.Doc/Nro | G37: Debe | H37: Haber | I37: Acumulado
B38: 45772 | C38: 2561 | D38: Glosa : TDC CLP-USD CAtherine alaracon | E38: KATHERINNE SILVANA ALARCON ESCOBAR | H38: 806870 | I38: =-H38 -> -806870
B39: 45785 | C39: 2723 | D39: Glosa : Payment: ER - Katherinne Alarcon25.3 - Reimbursable Expense - Viaje Lima | 25.3 - Reimbursable Expense - Viaje Lima | E39: KATHERINNE SILVANA ALARCON ESCOBAR | G39: 15336 | I39: =I38+G39-H39 -> -791534
B40: 45792 | C40: 2744 | D40: Glosa : Bank Transfer to CC Katherinne Alarcon. | E40: KATHERINNE SILVANA ALARCON ESCOBAR | G40: 806870 | I40: =I39+G40-H40 -> 15336
B41: 45805 | C41: 2909 | D41: Glosa : TDC pesos USD Katherine Alarcon | E41: KATHERINNE SILVANA ALARCON ESCOBAR | H41: 100449 | I41: =I40+G41-H41 -> -85113
B42: 45820 | C42: 2859 | D42: Glosa : Bank Transfer to CC Katherinne Alarcon. | E42: KATHERINNE SILVANA ALARCON ESCOBAR | G42: 100449 | I42: =I41+G42-H42 -> 15336
B43: 45834 | C43: 2916 | D43: Glosa : TDC CLP/USD KATHERINE ALARCON | E43: KATHERINNE SILVANA ALARCON ESCOBAR | H43: 2020460 | I43: =I42+G43-H43 -> -2005124
B44: 45848 | C44: 3050 | D44: Glosa : Bank Transfer to CC Katherinne Alarcon. | E44: KATHERINNE SILVANA ALARCON ESCOBAR | G44: 2020460 | I44: =I43+G44-H44 -> 15336
B45: 45867 | C45: 3093 | D45: Glosa : TDC CLP/USD KATHERINE ALARCON | E45: KATHERINNE SILVANA ALARCON ESCOBAR | H45: 1476513 | I45: =I44+G45-H45 -> -1461177
B46: 45869 | C46: 3276 | D46: Glosa : RECLASIFICA TDC K. ALARCON ENERO | E46: KATHERINNE SILVANA ALARCON ESCOBAR | H46: 3388645 | I46: =I45+G46-H46 -> -4849822
B47: 45869 | C47: 3301 | D47: Glosa : APERTURA TDC K. ALARCON FEB | E47: KATHERINNE SILVANA ALARCON ESCOBAR | H47: 1326542 | I47: =I46+G47-H47 -> -6176364
B48: 45869 | C48: 3306 | D48: Glosa : APERTURA TDC K. ALARCON MARZO | E48: KATHERINNE SILVANA ALARCON ESCOBAR | H48: 46444 | I48: =I47+G48-H48 -> -6222808
B49: 45869 | C49: 3451 | D49: Glosa : reclasifica CC Expense | E49: KATHERINNE SILVANA ALARCON ESCOBAR | H49: 15336 | I49: =I48+G49-H49 -> -6238144
B50: 45869 | C50: 3574 | D50: Glosa : compensa prov | E50: KATHERINNE SILVANA ALARCON ESCOBAR | G50: 1326542 | I50: =I49+G50-H50 -> -4911602
B51: 45693 | C51: 2278 | D51: Glosa : Pago Tarjeta de Credito | E51: KATHERINNE SILVANA ALARCON ESCOBAR | G51: 1611355 | I51: =I50+G51-H51 -> -3300247
B52: 45701 | C52: 2284 | D52: Glosa : Pago Tarjeta de Credito | E52: KATHERINNE SILVANA ALARCON ESCOBAR | G52: 1777290 | I52: =I51+G52-H52 -> -1522957
B53: 45762 | C53: 2509 | D53: Glosa : Pago tarjeta de credito Katherinne Alarcon | E53: KATHERINNE SILVANA ALARCON ESCOBAR | G53: 46444 | I53: =I52+G53-H53 -> -1476513
B54: 45882 | C54: 3260 | D54: Glosa : KA´s credit card payment | E54: KATHERINNE SILVANA ALARCON ESCOBAR | G54: 1476513 | I54: =I53+G54-H54 -> 0
B55: 45896 | C55: 3506 | D55: Glosa : TDC CLP/USD KATHERINE ALARCON | E55: KATHERINNE SILVANA ALARCON ESCOBAR | H55: 408970 | I55: =I54+G55-H55 -> -408970
D56: Provision Expenses CC - Provision CC KA Viaje Peru | H56: =28000+137718 -> 165718 | I56: =I55+G56-H56 -> -574688
B57: 45911 | C57: 3535 | D57: Glosa : Katherinnes credit card payment | E57: KATHERINNE SILVANA ALARCON ESCOBAR | G57: 408970 | I57: =I56+G57-H57 -> -165718
B58: 45926 | C58: 3580 | D58: Glosa : TDC CLP/USD KATHERINE ALARCON | E58: KATHERINNE SILVANA ALARCON ESCOBAR | H58: 925857 | I58: =I57+G58-H58 -> -1091575
A59: adig/1684 | B59: 45944 | C59: 3748 | D59: KATHERINNE SILVANA ALARCON ESCOBAR | G59: 925857 | I59: =I58+G59-H59 -> -165718
A60: adig/1699 | B60: 45958 | C60: 3802 | D60: KATHERINNE SILVANA ALARCON ESCOBAR | H60: 2007310 | I60: =I59+G60-H60 -> -2173028
A61: adig/1739 | B61: 45974 | C61: 3906 | E61: KATHERINNE SILVANA ALARCON ESCOBAR | G61: 2007310 | I61: =I60+G61-H61 -> -165718
A62: adig/1766 | B62: 45987 | C62: 3954 | D62: =+A62 -> adig/1766 | E62: KATHERINNE SILVANA ALARCON ESCOBAR | H62: 1908028 | I62: =I61+G62-H62 -> -2073746
A63: adig/1809 | B63: 46006 | C63: 4058 | D63: Glosa : Katherinnes credit card payment | E63: KATHERINNE SILVANA ALARCON ESCOBAR | G63: 1908028 | I63: =I62+G63-H63 -> -165718
A64: adig/1836 | B64: 46017 | C64: 4130 | D64: Glosa : TDC K. ALARCON | E64: KATHERINNE SILVANA ALARCON ESCOBAR | H64: 596065 | I64: =I63+G64-H64 -> -761783
B67: 45896 | C67: 3506 | D67: Glosa : TDC CLP/USD KATHERINE ALARCON | E67: KATHERINNE SILVANA ALARCON ESCOBAR | H67: 487.61 | I67: =-H67 -> -487.61
B68: 45926 | C68: 3580 | D68: Glosa : TDC CLP/USD KATHERINE ALARCON | E68: KATHERINNE SILVANA ALARCON ESCOBAR | G68: 487.61 | I68: =I67+G68-H68 -> 0
B69: 45926 | C69: 3580 | D69: Glosa : TDC CLP/USD KATHERINE ALARCON | E69: KATHERINNE SILVANA ALARCON ESCOBAR | H69: 137.11 | I69: =I68+G69-H69 -> -137.11
B70: 45958 | C70: 3802 | E70: KATHERINNE SILVANA ALARCON ESCOBAR | G70: 137.11 | I70: =I69+G70-H70 -> 0 | K70: -2041897
B71: 45958 | C71: 3802 | E71: KATHERINNE SILVANA ALARCON ESCOBAR | H71: 1139.58 | I71: =I70+G71-H71 -> -1139.58 | J71: =-H73*928.16 -> -119519.16 | K71: =+J71+I62 -> -2193265.2 | L71: =K71-K70 -> -151368.16
A72: adig/1766 | B72: 45987 | C72: 3954 | D72: =+A72 -> adig/1766 | E72: KATHERINNE SILVANA ALARCON ESCOBAR | G72: 1139.58 | I72: =I71+G72-H72 -> 0
A73: adig/1766 | B73: 45987 | C73: 3954 | D73: adig/1766 | E73: KATHERINNE SILVANA ALARCON ESCOBAR | H73: 128.77 | I73: =I72+G73-H73 -> -128.77
A74: adig/1836 | B74: 46017 | C74: 4130 | D74: Glosa : TDC K. ALARCON | E74: KATHERINNE SILVANA ALARCON ESCOBAR | G74: 128.77 | I74: =I73+G74-H74 -> 0
A75: adig/1836 | B75: 46017 | C75: 4130 | D75: Glosa : TDC K. ALARCON | E75: KATHERINNE SILVANA ALARCON ESCOBAR | H75: 667.63 | I75: =I74+G75-H75 -> -667.63 | J75: =-H75*907.13 -> -605627.2 | K75: =+J75+I64 -> -1367410.2

Sheet 9_x
A1: Account Code | B1: Account | C1: Date | D1: Source | E1: Description | F1: Reference | G1: Debit | H1: Credit
A2: 2114-09 | B2: CC Katherinne Alarcon | C2: 45667 | D2: Spend Money | E2: CC Expense | F2: Dinner and drinks | G2: 0 | H2: 350570 | I2: =+G2-H2 -> -350570
A3: 2114-09 | B3: CC Katherinne Alarcon | C3: 45667 | D3: Spend Money | E3: CC Expense | F3: Dinner and drinks | G3: 0 | H3: 51920 | I3: =I2+G3-H3 -> -402490
A4: 2114-09 | B4: CC Katherinne Alarcon | C4: 45670 | D4: Bank Transfer | E4: Bank Transfer from Citibank - CLP to CC Katherinne Alarcon | F4: CC Automatic Payment | G4: 2919571 | H4: 0 | I4: =I3+G4-H4 -> 2517081
A5: 2114-09 | B5: CC Katherinne Alarcon | C5: 45670 | D5: Spend Money | E5: Banco De Chile | G5: 0 | H5: 697 | I5: =I4+G5-H5 -> 2516384
A6: 2114-09 | B6: CC Katherinne Alarcon | C6: 45673 | D6: Payable Payment | E6: Payment: LATAM | F6: F/6268133 | G6: 0 | H6: 110880 | I6: =I5+G6-H6 -> 2405504
A7: 2114-09 | B7: CC Katherinne Alarcon | C7: 45675 | D7: Spend Money | E7: CC Expense | F7: Taxi aeropuerto domicilio | G7: 0 | H7: 26000 | I7: =I6+G7-H7 -> 2379504
A8: 2114-09 | B8: CC Katherinne Alarcon | C8: 45675 | D8: Spend Money | E8: CC Expense | F8: Snack Aeropuerto | G8: 0 | H8: 5681.58 | I8: =I7+G8-H8 -> 2373822.4
A9: 2114-09 | B9: CC Katherinne Alarcon | C9: 45675 | D9: Spend Money | E9: CC Expense | F9: Cafe aeropuerto | G9: 0 | H9: 6877.18 | I9: =I8+G9-H9 -> 2366945.2
A10: 2114-09 | B10: CC Katherinne Alarcon | C10: 45677 | D10: Spend Money | E10: Banco De Chile | G10: 0 | H10: 889 | I10: =I9+G10-H10 -> 2366056.2
A11: 2114-09 | B11: CC Katherinne Alarcon | C11: 45677 | D11: Spend Money | E11: Banco De Chile | G11: 0 | H11: 141 | I11: =I10+G11-H11 -> 2365915.2
A12: 2114-09 | B12: CC Katherinne Alarcon | C12: 45677 | D12: Spend Money | E12: Banco De Chile | G12: 0 | H12: 172 | I12: =I11+G12-H12 -> 2365743.2
A13: 2114-09 | B13: CC Katherinne Alarcon | C13: 45681 | D13: Adjustment | E13: Reconciliation adjustment | G13: 0 | H13: 0.01 | I13: =I12+G13-H13 -> 2365743.2
A14: 2114-09 | B14: CC Katherinne Alarcon | C14: 45681 | D14: Payable Payment | E14: Payment: LATAM | F14: F/6281525 | G14: 0 | H14: 814728 | I14: =I13+G14-H14 -> 1551015.2
A15: 2114-09 | B15: CC Katherinne Alarcon | C15: 45681 | D15: Payable Payment | E15: Payment: LATAM | F15: F/6282508 | G15: 0 | H15: 96556 | I15: =I14+G15-H15 -> 1454459.2
A16: 2114-09 | B16: CC Katherinne Alarcon | C16: 45686 | D16: Spend Money | E16: Banco De Chile | G16: 0 | H16: 3839 | I16: =I15+G16-H16 -> 1450620.2
A17: 2114-09 | B17: CC Katherinne Alarcon | C17: 45687 | D17: Spend Money | E17: CC Expense | F17: Taxi aeropuerto Hotel | G17: 0 | H17: 27311.08 | I17: =I16+G17-H17 -> 1423309.1
A18: 2114-09 | B18: CC Katherinne Alarcon | C18: 45687 | D18: Spend Money | E18: CC Expense | F18: Cenas | G18: 0 | H18: 34870.05 | I18: =I17+G18-H18 -> 1388439.1
A19: 2114-09 | B19: CC Katherinne Alarcon | C19: 45688 | D19: Spend Money | E19: CC Expense | F19: Patente comercial | G19: 0 | H19: 1520151 | I19: =I18+G19-H19 -> -131711.9
A20: 2114-09 | B20: CC Katherinne Alarcon | C20: 45688 | D20: Spend Money | E20: CC Expense | F20: Pasaje Sebastian | G20: 0 | H20: 399065 | I20: =I19+G20-H20 -> -530776.9
A21: 2114-09 | B21: CC Katherinne Alarcon | C21: 45690 | D21: Spend Money | E21: CC Expense | F21: Dif pasjae Katherinne BH | G21: 0 | H21: 13036.99 | I21: =I20+G21-H21 -> -543813.89
A22: 2114-09 | B22: CC Katherinne Alarcon | C22: 45692 | D22: Spend Money | E22: CC Expense | F22: Almuerzo con el equipo | G22: 0 | H22: 667150 | I22: =I21+G22-H22 -> -1210963.9
A23: 2114-09 | B23: CC Katherinne Alarcon | C23: 45693 | D23: Bank Transfer | E23: Bank Transfer from Citibank - CLP to CC Katherinne Alarcon | F23: KA CC payment | G23: 1611355 | H23: 0 | I23: =I22+G23-H23 -> 400391.11
A24: 2114-09 | B24: CC Katherinne Alarcon | C24: 45693 | D24: Spend Money | E24: CC Expense | F24: Cena con Equipo | G24: 0 | H24: 355520 | I24: =I23+G24-H24 -> 44871.11
A25: 2114-09 | B25: CC Katherinne Alarcon | C25: 45693 | D25: Spend Money | E25: CC Expense | F25: Almuerzo | G25: 0 | H25: 64779 | I25: =I24+G25-H25 -> -19907.89
A26: 2114-09 | B26: CC Katherinne Alarcon | C26: 45694 | D26: Spend Money | E26: CC Expense | F26: Almuerzo | G26: 0 | H26: 11950 | I26: =I25+G26-H26 -> -31857.89
A27: 2114-09 | B27: CC Katherinne Alarcon | C27: 45694 | D27: Spend Money | E27: CC Expense | F27: almuerzo | G27: 0 | H27: 53207 | I27: =I26+G27-H27 -> -85064.89
A28: 2114-09 | B28: CC Katherinne Alarcon | C28: 45701 | D28: Bank Transfer | E28: Bank Transfer from Citibank - CLP to CC Katherinne Alarcon | F28: CC payment Katherinne | G28: 1777290 | H28: 0 | I28: =I27+G28-H28 -> 1692225.1
A29: 2114-09 | B29: CC Katherinne Alarcon | C29: 45713 | D29: Payable Payment | E29: Payment: PROD - RED DE TRANSPORTES COMERCIALES LTDA | F29: F/62420 | G29: 0 | H29: 71240 | I29: =I28+G29-H29 -> 1620985.1
A30: 2114-09 | B30: CC Katherinne Alarcon | C30: 45714 | D30: Spend Money | E30: Banco De Chile | G30: 0 | H30: 49 | I30: =I29+G30-H30 -> 1620936.1
A31: 2114-09 | B31: CC Katherinne Alarcon | C31: 45714 | D31: Spend Money | E31: Banco De Chile | G31: 0 | H31: 3862 | I31: =I30+G31-H31 -> 1617074.1
A32: 2114-09 | B32: CC Katherinne Alarcon | C32: 45714 | D32: Spend Money | E32: Banco De Chile | G32: 0 | H32: 1835 | I32: =I31+G32-H32 -> 1615239.1
A33: 2114-09 | B33: CC Katherinne Alarcon | C33: 45715 | D33: Spend Money | E33: CC Expense | F33: Fruta semana 24 feb | G33: 0 | H33: 23352 | I33: =I32+G33-H33 -> 1591887.1
A34: 2114-09 | B34: CC Katherinne Alarcon | C34: 45716 | D34: Receive Money | E34: Banco De Chile | G34: 1141.89 | H34: 0 | I34: =I33+G34-H34 -> 1593029
A35: 2114-09 | B35: CC Katherinne Alarcon | C35: 45723 | D35: Bank Transfer | E35: Bank Transfer from Citibank - CLP to CC Katherinne Alarcon | F35: Katherinne A CC payment | G35: 1326542 | H35: 0 | I35: =I34+G35-H35 -> 2919571
A36: 2114-09 | B36: CC Katherinne Alarcon | C36: 45732 | D36: Spend Money | E36: Provision Expenses CC | G36: 0 | H36: 22214 | I36: =I35+G36-H36 -> 2897357
A37: 2114-09 | B37: CC Katherinne Alarcon | C37: 45733 | D37: Spend Money | E37: Provision Expenses CC | G37: 0 | H37: 8354 | I37: =I36+G37-H37 -> 2889003
A38: 2114-09 | B38: CC Katherinne Alarcon | C38: 45733 | D38: Spend Money | E38: Provision Expenses CC | G38: 0 | H38: 110552 | I38: =I37+G38-H38 -> 2778451
A39: 2114-09 | B39: CC Katherinne Alarcon | C39: 45734 | D39: Spend Money | E39: Banco De Chile | G39: 0 | H39: 553 | I39: =I38+G39-H39 -> 2777898
A40: 2114-09 | B40: CC Katherinne Alarcon | C40: 45734 | D40: Spend Money | E40: Banco De Chile | G40: 0 | H40: 206 | I40: =I39+G40-H40 -> 2777692
A41: 2114-09 | B41: CC Katherinne Alarcon | C41: 45734 | D41: Spend Money | E41: Banco De Chile | G41: 0 | H41: 2735 | I41: =I40+G41-H41 -> 2774957
A42: 2114-09 | B42: CC Katherinne Alarcon | C42: 45734 | D42: Spend Money | E42: Provision Expenses CC | G42: 0 | H42: 454715 | I42: =I41+G42-H42 -> 2320242
A43: 2114-09 | B43: CC Katherinne Alarcon | C43: 45735 | D43: Spend Money | E43: Banco De Chile | G43: 0 | H43: 11263 | I43: =I42+G43-H43 -> 2308979
A44: 2114-09 | B44: CC Katherinne Alarcon | C44: 45735 | D44: Spend Money | E44: Provision Expenses CC | G44: 0 | H44: 15015 | I44: =I43+G44-H44 -> 2293964
A45: 2114-09 | B45: CC Katherinne Alarcon | C45: 45736 | D45: Spend Money | E45: Banco De Chile | G45: 0 | H45: 375 | I45: =I44+G45-H45 -> 2293589
A46: 2114-09 | B46: CC Katherinne Alarcon | C46: 45736 | D46: Spend Money | E46: Provision Expenses CC | G46: 0 | H46: 2782 | I46: =I45+G46-H46 -> 2290807
A47: 2114-09 | B47: CC Katherinne Alarcon | C47: 45737 | D47: Spend Money | E47: Banco De Chile | G47: 0 | H47: 66 | I47: =I46+G47-H47 -> 2290741
... A53: 2114-09 | B53: CC Katherinne Alarcon | C53: 45743 | D53: Spend Money | E53: Banco De Chile | G53: 0 | H53: 3887 | I53: =I52+G53-H53 -> 2204838
A54: 2114-09 | B54: CC Katherinne Alarcon | C54: 45748 | D54: Spend Money | E54: CC Expense | F54: Agua | G54: 0 | H54: 8354 | I54: =I53+G54-H54 -> 2196484
A55: 2114-09 | B55: CC Katherinne Alarcon | C55: 45748 | D55: Spend Money | E55: CC Expense | F55: Cafe con el equipo | G55: 0 | H55: 20247 | I55: =I54+G55-H55 -> 2176237
A56: 2114-09 | B56: CC Katherinne Alarcon | C56: 45748 | D56: Spend Money | E56: CC Expense | F56: Llegada Lima | G56: 0 | H56: 22214 | I56: =I55+G56-H56 -> 2154023
A57: 2114-09 | B57: CC Katherinne Alarcon | C57: 45748 | D57: Spend Money | E57: CC Expense | F57: Cena Equipo Fzas mas Mateus | G57: 0 | H57: 110552 | I57: =I56+G57-H57 -> 2043471
A58: 2114-09 | B58: CC Katherinne Alarcon | C58: 45748 | D58: Spend Money | E58: CC Expense | F58: Cena Equipo | G58: 0 | H58: 15015 | I58: =I57+G58-H58 -> 2028456
A59: 2114-09 | B59: CC Katherinne Alarcon | C59: 45748 | D59: Spend Money | E59: CC Expense | F59: Cena Equipo | G59: 0 | H59: 34410 | I59: =I58+G59-H59 -> 1994046
A60: 2114-09 | B60: CC Katherinne Alarcon | C60: 45748 | D60: Spend Money | E60: CC Expense | F60: Taxi regreso Stgo | G60: 0 | H60: 26000 | I60: =I59+G60-H60 -> 1968046
A61: 2114-09 | B61: CC Katherinne Alarcon | C61: 45748 | D61: Spend Money | E61: CC Expense | F61: Cena con Equipo en Lima | G61: 0 | H61: 454715 | I61: =I60+G61-H61 -> 1513331
A62: 2114-09 | B62: CC Katherinne Alarcon | C62: 45748 | D62: Receive Money | E62: Provision Expenses CC | G62: 26000 | H62: 0 | I62: =I61+G62-H62 -> 1539331
A63: 2114-09 | B63: CC Katherinne Alarcon | C63: 45748 | D63: Receive Money | E63: Provision Expenses CC | G63: 34410 | H63: 0 | I63: =I62+G63-H63 -> 1573741
A64: 2114-09 | B64: CC Katherinne Alarcon | C64: 45748 | D64: Receive Money | E64: Provision Expenses CC | G64: 22214 | H64: 0 | I64: =I63+G64-H64 -> 1595955
A65: 2114-09 | B65: CC Katherinne Alarcon | C65: 45748 | D65: Receive Money | E65: Provision Expenses CC | G65: 15015 | H65: 0 | I65: =I64+G65-H65 -> 1610970
A66: 2114-09 | B66: CC Katherinne Alarcon | C66: 45748 | D66: Receive Money | E66: Provision Expenses CC | G66: 110552 | H66: 0 | I66: =I65+G66-H66 -> 1721522
A67: 2114-09 | B67: CC Katherinne Alarcon | C67: 45748 | D67: Receive Money | E67: Provision Expenses CC | G67: 20247 | H67: 0 | I67: =I66+G67-H67 -> 1741769
A68: 2114-09 | B68: CC Katherinne Alarcon | C68: 45748 | D68: Receive Money | E68: Provision Expenses CC | G68: 8354 | H68: 0 | I68: =I67+G68-H68 -> 1750123
A69: 2114-09 | B69: CC Katherinne Alarcon | C69: 45748 | D69: Receive Money | E69: Provision Expenses CC | G69: 454715 | H69: 0 | I69: =I68+G69-H69 -> 2204838
A70: 2114-09 | B70: CC Katherinne Alarcon | C70: 45762 | D70: Bank Transfer | E70: Bank Transfer from Citibank - CLP to CC Katherinne Alarcon | F70: KA´s credit card payment | G70: 46444 | H70: 0 | I70: =I69+G70-H70 -> 2251282
A71: 2114-09 | B71: CC Katherinne Alarcon | C71: 45762 | D71: Spend Money | E71: Banco De Chile | G71: 0 | H71: 462 | I71: =I70+G71-H71 -> 2250820
A72: 2114-09 | B72: CC Katherinne Alarcon | C72: 45770 | D72: Spend Money | E72: Provision Expenses CC | G72: 0 | H72: 84444 | I72: =I71+G72-H72 -> 2166376
A73: 2114-09 | B73: CC Katherinne Alarcon | C73: 45772 | D73: Spend Money | E73: Banco De Chile | G73: 0 | H73: 3904 | I73: =I72+G73-H73 -> 2162472
A74: 2114-09 | B74: CC Katherinne Alarcon | C74: 45772 | D74: Spend Money | E74: Banco De Chile | G74: 0 | H74: 18764 | I74: =I73+G74-H74 -> 2143708
A75: 2114-09 | B75: CC Katherinne Alarcon | C75: 45772 | D75: Spend Money | E75: Banco De Chile | G75: 0 | H75: 22734.58 | I75: =I74+G75-H75 -> 2120973.4
A76: 2114-09 | B76: CC Katherinne Alarcon | C76: 45774 | D76: Spend Money | E76: Provision Expenses CC | G76: 0 | H76: 8272.42 | I76: =I75+G76-H76 -> 2112701
A77: 2114-09 | B77: CC Katherinne Alarcon | C77: 45778 | D77: Spend Money | E77: Banco De Chile | G77: 0 | H77: 211 | I77: =I76+G77-H77 -> 2112490
A78: 2114-09 | B78: CC Katherinne Alarcon | C78: 45778 | D78: Spend Money | E78: CC Expense | F78: Aguas snacks | G78: 0 | H78: 8202 | I78: =I77+G78-H78 -> 2104288
A79: 2114-09 | B79: CC Katherinne Alarcon | C79: 45778 | D79: Adjustment | E79: Reconciliation adjustment | G79: 0.01 | H79: 0 | I79: =I78+G79-H79 -> 2104288
A80: 2114-09 | B80: CC Katherinne Alarcon | C80: 45779 | D80: Spend Money | E80: CC Expense | F80: Comida Katty y Caro | G80: 0 | H80: 7386 | I80: =I79+G80-H80 -> 2096902
A81: 2114-09 | B81: CC Katherinne Alarcon | C81: 45779 | D81: Adjustment | E81: Reconciliation adjustment | G81: 0 | H81: 0.48 | I81: =I80+G81-H81 -> 2096901.5
A82: 2114-09 | B82: CC Katherinne Alarcon | C82: 45780 | D82: Spend Money | E82: CC Expense | F82: Cena Katty | G82: 0 | H82: 8380 | I82: =I81+G82-H82 -> 2088521.5
A83: 2114-09 | B83: CC Katherinne Alarcon | C83: 45780 | D83: Adjustment | E83: Reconciliation adjustment | G83: 0 | H83: 0.09 | I83: =I82+G83-H83 -> 2088521.4
A84: 2114-09 | B84: CC Katherinne Alarcon | C84: 45781 | D84: Spend Money | E84: CC Expense | F84: Aguas y Snack Caro y Katty | G84: 0 | H84: 9271 | I84: =I83+G84-H84 -> 2079250.4
A85: 2114-09 | B85: CC Katherinne Alarcon | C85: 45781 | D85: Adjustment | E85: Reconciliation adjustment | G85: 0.41 | H85: 0 | I85: =I84+G85-H85 -> 2079250.8
A86: 2114-09 | B86: CC Katherinne Alarcon | C86: 45782 | D86: Spend Money | E86: Banco De Chile | G86: 0 | H86: 211 | I86: =I85+G86-H86 -> 2079039.8
A87: 2114-09 | B87: CC Katherinne Alarcon | C87: 45782 | D87: Spend Money | E87: Banco De Chile | G87: 0 | H87: 191 | I87: =I86+G87-H87 -> 2078848.8
A88: 2114-09 | B88: CC Katherinne Alarcon | C88: 45782 | D88: Spend Money | E88: Banco De Chile | G88: 0 | H88: 239 | I88: =I87+G88-H88 -> 2078609.8
A89: 2114-09 | B89: CC Katherinne Alarcon | C89: 45783 | D89: Spend Money | E89: CC Expense | F89: Cena Caro y Katty | G89: 0 | H89: 36511 | I89: =I88+G89-H89 -> 2042098.8
A90: 2114-09 | B90: CC Katherinne Alarcon | C90: 45783 | D90: Adjustment | E90: Reconciliation adjustment | G90: 0.44 | H90: 0 | I90: =I89+G90-H90 -> 2042099.3
A91: 2114-09 | B91: CC Katherinne Alarcon | C91: 45784 | D91: Spend Money | E91: Banco De Chile | G91: 0 | H91: 928 | I91: =I90+G91-H91 -> 2041171.3
A92: 2114-09 | B92: CC Katherinne Alarcon | C92: 45784 | D92: Spend Money | E92: CC Expense | F92: Taxi aeropuerto domicilio | G92: 0 | H92: 26000 | I92: =I91+G92-H92 -> 2015171.3
A93: 2114-09 | B93: CC Katherinne Alarcon | C93: 45784 | D93: Spend Money | E93: CC Expense | F93: Almuerzo aeropuerto Sao Paulo | G93: 0 | H93: 13367 | I93: =I92+G93-H93 -> 2001804.3
A94: 2114-09 | B94: CC Katherinne Alarcon | C94: 45784 | D94: Spend Money | E94: CC Expense | F94: Comidas Katty y Caro en el hotel | G94: 0 | H94: 120490 | I94: =I93+G94-H94 -> 1881314.3
A95: 2114-09 | B95: CC Katherinne Alarcon | C95: 45784 | D95: Adjustment | E95: Reconciliation adjustment | G95: 0.1 | H95: 0 | I95: =I94+G95-H95 -> 1881314.4
A96: 2114-09 | B96: CC Katherinne Alarcon | C96: 45784 | D96: Adjustment | E96: Reconciliation adjustment | G96: 0.46 | H96: 0 | I96: =I95+G96-H96 -> 1881314.8
A97: 2114-09 | B97: CC Katherinne Alarcon | C97: 45785 | D97: Spend Money | E97: Banco De Chile | G97: 0 | H97: 345 | I97: =I96+G97-H97 -> 1880969.8
A98: 2114-09 | B98: CC Katherinne Alarcon | C98: 45785 | D98: Spend Money | E98: Banco De Chile | G98: 0 | H98: 3072 | I98: =I97+G98-H98 -> 1877897.8
A99: 2114-09 | B99: CC Katherinne Alarcon | C99: 45791 | D99: Spend Money | E99: Banco De Chile | G99: 0 | H99: 335 | I99: =I98+G99-H99 -> 1877562.8
A100: 2114-09 | B100: CC Katherinne Alarcon | C100: 45791 | D100: Spend Money | E100: CC Expense | G100: 0 | H100: 12945.08 | I100: =I99+G100-H100 -> 1864617.8
A101: 2114-09 | B101: CC Katherinne Alarcon | C101: 45792 | D101: Bank Transfer | E101: Bank Transfer from Citibank - CLP to CC Katherinne Alarcon | F101: KA´s credit card payment | G101: 806870 | H101: 0 | I101: =I100+G101-H101 -> 2671487.8
A102: 2114-09 | B102: CC Katherinne Alarcon | C102: 45792 | D102: Spend Money | E102: CC Expense | F102: Agua aeropuerto Stgo | G102: 0 | H102: 3600 | I102: =I101+G102-H102 -> 2667887.8
A103: 2114-09 | B103: CC Katherinne Alarcon | C103: 45794 | D103: Spend Money | E103: CC Expense | F103: Agua Aeropuerto NZ | G103: 0 | H103: 3318 | I103: =I102+G103-H103 -> 2664569.8
A104: 2114-09 | B104: CC Katherinne Alarcon | C104: 45794 | D104: Spend Money | E104: CC Expense | F104: Agua y Bebida Aeropuerto Brisbane | G104: 0 | H104: 5680 | I104: =I103+G104-H104 -> 2658889.8
A105: 2114-09 | B105: CC Katherinne Alarcon | C105: 45794 | D105: Spend Money | E105: CC Expense | F105: Taxi aeropuerto Hotel Brisbane | G105: 0 | H105: 43400 | I105: =I104+G105-H105 -> 2615489.8
...

Sheet 10
A1: Comprobante | B1: Fec. Doc. | C1: Voucher | E1: Titular | F1: T.Doc/Nro | G1: Debe | H1: Haber | I1: Acumulado
A2: adig/1114 | B2: 45772 | C2: 2553 | D2: Glosa : TDC CLP_USD C.Contreras | E2: CAROL TATIANA CONTRERAS MUÑOZ | H2: 3070443 | I2: =-H2 -> -3070443
A3: adig/1171 | B3: 45792 | C3: 2743 | D3: Glosa : Bank Transfer to CC Carol Contreras. | E3: CAROL TATIANA CONTRERAS MUÑOZ | G3: 3070443 | I3: =+I2+G3 -> 0
A4: adig/1251 | B4: 45805 | C4: 2907 | D4: Glosa : TDC CLP_USD C.Contreras | E4: CAROL TATIANA CONTRERAS MUÑOZ | H4: 1231423 | I4: =-H4 -> -1231423
A5: adig/1207 | B5: 45820 | C5: 2863 | D5: Glosa : Bank Transfer to CC Carol Contreras. | E5: CAROL TATIANA CONTRERAS MUÑOZ | G5: 1231423 | I5: =+I4+G5 -> 0
A6: adig/1256 | B6: 45834 | C6: 2912 | D6: Glosa : TDC CLP/USD CARLO CONTRERAS | E6: CAROL TATIANA CONTRERAS MUÑOZ | H6: 981428 | I6: =-H6 -> -981428
A7: adig/1312 | B7: 45848 | C7: 3049 | D7: Glosa : Bank Transfer to CC Carol Contreras. | E7: CAROL TATIANA CONTRERAS MUÑOZ | G7: 981428 | I7: =+I6+G7 -> 0
A8: adig/1311 | B8: 45845 | C8: 3041 | D8: Glosa : Payment: ER - Carol Contreras 25.7 - Reimbursable Expense - compra cervezas happ... | 25.7 - Reimbursable Expense - compra cervezas happ... | E8: CAROL TATIANA CONTRERAS MUÑOZ | G8: 33059 | I8: =+G8 -> 33059
A9: adig/1333 | B9: 45867 | C9: 3092 | D9: Glosa : TDC CLP/USD CAROl CONTRERAS | E9: CAROL TATIANA CONTRERAS MUÑOZ | H9: 1861875 | I9: =-H9 -> -1861875
A10: adig/1382 | B10: 45869 | C10: 3271 | D10: Glosa : RECLASIFICA GASTOS RENDICION Carol contreras | E10: CAROL TATIANA CONTRERAS MUÑOZ | H10: 1913232 | I10: =-H10 -> -1913232
A11: adig/1383 | B11: 45869 | C11: 3272 | D11: Glosa : RECLASIFICA GASTOS RENDICION Carol contreras feb | E11: CAROL TATIANA CONTRERAS MUÑOZ | H11: 2328147 | I11: =-H11 -> -2328147
A12: adig/1384 | B12: 45869 | C12: 3273 | D12: Glosa : RECLASIFICA GASTOS RENDICION Carol contreras mar | E12: CAROL TATIANA CONTRERAS MUÑOZ | H12: 1497172 | I12: =-H12 -> -1497172
A15: adig/1114 | B15: 45772 | C15: 2553 | D15: Glosa : TDC CLP_USD C.Contreras | E15: CONTRERAS | G15: 975.05 | I15: 975.05
A16: adig/1114 | B16: 45772 | C16: 2553 | D16: Glosa : TDC CLP_USD C.Contreras | E16: CONTRERAS | H16: 975.05 | I16: 0
D19: 2114-10 - CC Carol Contreras | F19: 1861875
B22: Fec. Doc. | C22: Voucher | E22: Titular | G22: Debe | H22: Haber | I22: Acumulado
B23: 45772 | C23: 2553 | D23: Glosa : TDC CLP_USD C.Contreras | E23: CAROL TATIANA CONTRERAS MUÑOZ | H23: 3070443 | I23: -2948765
B24: 45792 | C24: 2743 | D24: Glosa : Bank Transfer to CC Carol Contreras. | E24: CAROL TATIANA CONTRERAS MUÑOZ | G24: 3070443 | I24: -1268867
B25: 45805 | C25: 2907 | D25: Glosa : TDC CLP_USD C.Contreras | E25: CAROL TATIANA CONTRERAS MUÑOZ | H25: 1231423 | I25: -165685
B26: 45820 | C26: 2863 | D26: Glosa : Bank Transfer to CC Carol Contreras. | E26: CAROL TATIANA CONTRERAS MUÑOZ | G26: 1231423 | I26: 1406242
B27: 45834 | C27: 2912 | D27: Glosa : TDC CLP/USD CARLO CONTRERAS | E27: CAROL TATIANA CONTRERAS MUÑOZ | H27: 981428 | I27: 433814
B28: 45845 | C28: 3041 | D28: Glosa : Payment: ER - Carol Contreras 25.7 - Reimbursable Expense - compra cervezas happ... | 25.7 - Reimbursable Expense - compra cervezas happ... | E28: CAROL TATIANA CONTRERAS MUÑOZ | G28: 33059 | I28: -3526676
B29: 45848 | C29: 3049 | D29: Glosa : Bank Transfer to CC Carol Contreras. | E29: CAROL TATIANA CONTRERAS MUÑOZ | G29: 981428 | I29: -2545248
B30: 45867 | C30: 3092 | D30: Glosa : TDC CLP/USD CAROl CONTRERAS | E30: CAROL TATIANA CONTRERAS MUÑOZ | H30: 1861875 | I30: -2278830
B31: 45869 | C31: 3271 | D31: Glosa : RECLASIFICA GASTOS RENDICION Carol contreras | E31: CAROL TATIANA CONTRERAS MUÑOZ | H31: 1913232 | I31: -6780412 | J31: 2011
B32: 45869 | C32: 3272 | D32: Glosa : RECLASIFICA GASTOS RENDICION Carol contreras feb | E32: CAROL TATIANA CONTRERAS MUÑOZ | H32: 2328147 | I32: -9108559 | J32: 2011
B33: 45869 | C33: 3273 | D33: Glosa : RECLASIFICA GASTOS RENDICION Carol contreras mar | E33: CAROL TATIANA CONTRERAS MUÑOZ | H33: 1497172 | I33: -10605731
B34: 45869 | C34: 3458 | D34: Glosa : Spend Money CC Expense ABRIL-MAYO-JUNIO-JULIO | E34: CAROL TATIANA CONTRERAS MUÑOZ | H34: 460158 | I34: -25653462 | J34: ?
B35: 45869 | C35: 3458 | D35: Glosa : Spend Money CC Expense ABRIL-MAYO-JUNIO-JULIO | E35: CAROL TATIANA CONTRERAS MUÑOZ | H35: 100167 | I35: -25753629 | J35: ?
B36: 45869 | C36: 3458 | D36: Glosa : Spend Money CC Expense ABRIL-MAYO-JUNIO-JULIO | E36: CAROL TATIANA CONTRERAS MUÑOZ | H36: 289020 | I36: -26042649 | J36: ?
B37: 45869 | C37: 3458 | D37: Glosa : Spend Money CC Expense ABRIL-MAYO-JUNIO-JULIO | E37: CAROL TATIANA CONTRERAS MUÑOZ | H37: 356370 | I37: -26399019 | J37: ?
B40: Fec. Doc. | C40: Voucher | E40: Titular | F40: T.Doc/Nro | G40: Debe | H40: Haber | I40: Acumulado
B41: 45772 | C41: 2553 | D41: Glosa : TDC CLP_USD C.Contreras | E41: CAROL TATIANA CONTRERAS MUÑOZ | H41: 3070443 | I41: =-H41 -> -3070443
B42: 45792 | C42: 2743 | D42: Glosa : Bank Transfer to CC Carol Contreras. | E42: CAROL TATIANA CONTRERAS MUÑOZ | G42: 3070443 | I42: =I41+G42-H42 -> 0
B43: 45805 | C43: 2907 | D43: Glosa : TDC CLP_USD C.Contreras | E43: CAROL TATIANA CONTRERAS MUÑOZ | H43: 1231423 | I43: =I42+G43-H43 -> -1231423
B44: 45820 | C44: 2863 | D44: Glosa : Bank Transfer to CC Carol Contreras. | E44: CAROL TATIANA CONTRERAS MUÑOZ | G44: 1231423 | I44: =I43+G44-H44 -> 0
B45: 45834 | C45: 2912 | D45: Glosa : TDC CLP/USD CARLO CONTRERAS | E45: CAROL TATIANA CONTRERAS MUÑOZ | H45: 981428 | I45: =I44+G45-H45 -> -981428
B46: 45845 | C46: 3041 | D46: Glosa : Payment: ER - Carol Contreras 25.7 - Reimbursable Expense - compra cervezas happ... | 25.7 - Reimbursable Expense - compra cervezas happ... | E46: CAROL TATIANA CONTRERAS MUÑOZ | G46: 33059 | I46: =I45+G46-H46 -> -948369
B47: 45848 | C47: 3049 | D47: Glosa : Bank Transfer to CC Carol Contreras. | E47: CAROL TATIANA CONTRERAS MUÑOZ | G47: 981428 | I47: =I46+G47-H47 -> 33059
B48: 45867 | C48: 3092 | D48: Glosa : TDC CLP/USD CAROl CONTRERAS | E48: CAROL TATIANA CONTRERAS MUÑOZ | H48: 1861875 | I48: =I47+G48-H48 -> -1828816
B49: 45869 | C49: 3271 | D49: Glosa : RECLASIFICA GASTOS RENDICION Carol contreras | E49: CAROL TATIANA CONTRERAS MUÑOZ | H49: 1913232 | I49: =I48+G49-H49 -> -3742048
B50: 45869 | C50: 3272 | D50: Glosa : RECLASIFICA GASTOS RENDICION Carol contreras feb | E50: CAROL TATIANA CONTRERAS MUÑOZ | H50: 2328147 | I50: =I49+G50-H50 -> -6070195
B51: 45869 | C51: 3273 | D51: Glosa : RECLASIFICA GASTOS RENDICION Carol contreras mar | E51: CAROL TATIANA CONTRERAS MUÑOZ | H51: 1497172 | I51: =I50+G51-H51 -> -7567367
B52: 45869 | C52: 3458 | D52: Glosa : Spend Money CC Expense ABRIL-MAYO-JUNIO-JULIO | E52: CAROL TATIANA CONTRERAS MUÑOZ | H52: 460158 | I52: =I51+G52-H52 -> -8027525
B53: 45869 | C53: 3458 | D53: Glosa : Spend Money CC Expense ABRIL-MAYO-JUNIO-JULIO | E53: CAROL TATIANA CONTRERAS MUÑOZ | H53: 100167 | I53: =I52+G53-H53 -> -8127692
B54: 45869 | C54: 3458 | D54: Glosa : Spend Money CC Expense ABRIL-MAYO-JUNIO-JULIO | E54: CAROL TATIANA CONTRERAS MUÑOZ | H54: 289020 | I54: =I53+G54-H54 -> -8416712
B55: 45869 | C55: 3458 | D55: Glosa : Spend Money CC Expense ABRIL-MAYO-JUNIO-JULIO | E55: CAROL TATIANA CONTRERAS MUÑOZ | H55: 356370 | I55: =I54+G55-H55 -> -8773082
B56: 45869 | C56: 3574 | D56: Glosa : compensa prov | E56: CAROL TATIANA CONTRERAS MUÑOZ | G56: 5414035 | I56: =I55+G56-H56 -> -3359047
B57: 45762 | C57: 2510 | D57: Glosa : Pago tarjeta de credito Carol Contreras | E57: CAROL TATIANA CONTRERAS MUÑOZ | G57: 1497172 | I57: =I56+G57-H57 -> -1861875
B58: 45882 | C58: 3258 | D58: Glosa : Carol's cc payment | E58: CAROL TATIANA CONTRERAS MUÑOZ | G58: 1861875 | I58: =I57+G58-H58 -> 0
B59: 45896 | C59: 3484 | D59: Glosa : TDC CLP/USD CAROl CONTRERAS | E59: CAROL TATIANA CONTRERAS MUÑOZ | H59: 607271 | I59: =I58+G59-H59 -> -607271
B60: 45911 | C60: 3531 | D60: Glosa : Carol's cc payment | E60: CAROL TATIANA CONTRERAS MUÑOZ | G60: 607270 | I60: =I59+G60-H60 -> -1
I61: 0

Sheet 10_X
A1: Account Code | B1: Account | C1: Date | D1: Source | E1: Description | F1: Reference | G1: Debit | H1: Credit
A2: 2114-10 | B2: CC Carol Contreras | C2: 45659 | D2: Payable Payment | E2: Payment: PROD - RED DE TRANSPORTES COMERCIALES LTDA | F2: F/60232 | G2: 0 | H2: 156090 | I2: =+G2-H2 -> -156090
A3: 2114-10 | B3: CC Carol Contreras | C3: 45663 | D3: Payable Payment | E3: Payment: Telefonica Chile S.A (Movistar) | F3: F/52229965 | G3: 0 | H3: 294887 | I3: =I2+G3-H3 -> -450977
A4: 2114-10 | B4: CC Carol Contreras | C4: 45663 | D4: Payable Payment | E4: Payment: Telefonica Chile S.A (Movistar) | F4: F/50708669 | G4: 0 | H4: 24003 | I4: =I3+G4-H4 -> -474980
A5: 2114-10 | B5: CC Carol Contreras | C5: 45664 | D5: Spend Money | E5: CC Expense | F5: tortas cumpleaos la danesa | G5: 0 | H5: 83390 | I5: =I4+G5-H5 -> -558370
A6: 2114-10 | B6: CC Carol Contreras | C6: 45664 | D6: Payable Payment | E6: Payment: BECKER PADRUNO GRATTINI Y COMPANIA LTDA | F6: 1044458 | G6: 0 | H6: 208720 | I6: =I5+G6-H6 -> -767090
A7: 2114-10 | B7: CC Carol Contreras | C7: 45666 | D7: Spend Money | E7: CC Expense | F7: almuerzo oficina Black Chiken | G7: 0 | H7: 162830 | I7: =I6+G7-H7 -> -929920
A8: 2114-10 | B8: CC Carol Contreras | C8: 45666 | D8: Spend Money | E8: CC Expense | F8: black Chiken happy hour cesar | G8: 0 | H8: 15980 | I8: =I7+G8-H8 -> -945900
A9: 2114-10 | B9: CC Carol Contreras | C9: 45666 | D9: Spend Money | E9: CC Expense | F9: OXXO happy Hour cesar | G9: 0 | H9: 4380 | I9: =I8+G9-H9 -> -950280
A10: 2114-10 | B10: CC Carol Contreras | C10: 45667 | D10: Spend Money | E10: CC Expense | F10: uber happy hour cesar marcelo | G10: 0 | H10: 22008 | I10: =I9+G10-H10 -> -972288
A11: 2114-10 | B11: CC Carol Contreras | C11: 45667 | D11: Spend Money | E11: CC Expense | F11: choripanes cesar unimarc | G11: 0 | H11: 53148 | I11: =I10+G11-H11 -> -1025436
A12: 2114-10 | B12: CC Carol Contreras | C12: 45670 | D12: Bank Transfer | E12: Bank Transfer from Citibank - CLP to CC Carol Contreras | F12: CC Automatic Payment | G12: 949710 | H12: 0 | I12: =I11+G12-H12 -> -75726
A13: 2114-10 | B13: CC Carol Contreras | C13: 45670 | D13: Spend Money | E13: CC Expense | F13: torta cumpleaos carol | G13: 0 | H13: 29000 | I13: =I12+G13-H13 -> -104726
A14: 2114-10 | B14: CC Carol Contreras | C14: 45670 | D14: Spend Money | E14: CC Expense | F14: uber dennisse cena Cesar y andrew | G14: 0 | H14: 11889 | I14: =I13+G14-H14 -> -116615
... A19: 2114-10 | B19: CC Carol Contreras | C19: 45678 | D19: Spend Money | E19: CC Expense | F19: fruta oficina | G19: 0 | H19: 24120 | I19: =I18+G19-H19 -> -901954
A20: 2114-10 | B20: CC Carol Contreras | C20: 45678 | D20: Spend Money | E20: uber | G20: 1206 | H20: 0 | I20: =I19+G20-H20 -> -900748
A21: 2114-10 | B21: CC Carol Contreras | C21: 45678 | D21: Spend Money | E21: uber | G21: 0 | H21: 1206 | I21: =I20+G21-H21 -> -901954
A22: 2114-10 | B22: CC Carol Contreras | C22: 45684 | D22: Spend Money | E22: CC Expense | F22: fruta oficina | G22: 0 | H22: 21759 | I22: =I21+G22-H22 -> -923713
A23: 2114-10 | B23: CC Carol Contreras | C23: 45684 | D23: Spend Money | E23: CC Expense | F23: audifonos carol | G23: 0 | H23: 9990 | I23: =I22+G23-H23 -> -933703
A24: 2114-10 | B24: CC Carol Contreras | C24: 45684 | D24: Spend Money | E24: uber | G24: 0 | H24: 1036 | I24: =I23+G24-H24 -> -934739
A25: 2114-10 | B25: CC Carol Contreras | C25: 45684 | D25: Spend Money | E25: uber | G25: 1036 | H25: 0 | I25: =I24+G25-H25 -> -933703
A26: 2114-10 | B26: CC Carol Contreras | C26: 45686 | D26: Spend Money | E26: Banco De Chile | G26: 0 | H26: 3839 | I26: =I25+G26-H26 -> -937542
A27: 2114-10 | B27: CC Carol Contreras | C27: 45687 | D27: Payable Payment | E27: Payment: CVH STORE SPA | F27: F/1604 | G27: 0 | H27: 53980 | I27: =I26+G27-H27 -> -991522
A28: 2114-10 | B28: CC Carol Contreras | C28: 45689 | D28: Spend Money | E28: CC Expense | F28: uber despedida Marcelo Siro | G28: 0 | H28: 7420 | I28: =I27+G28-H28 -> -998942
A29: 2114-10 | B29: CC Carol Contreras | C29: 45689 | D29: Spend Money | E29: CC Expense | F29: uber denisse despedida Marcelo siro | G29: 0 | H29: 12546 | I29: =I28+G29-H29 -> -1011488
A30: 2114-10 | B30: CC Carol Contreras | C30: 45689 | D30: Spend Money | E30: CC Expense | F30: uber carol despedida marcelo siro | G30: 0 | H30: 10361 | I30: =I29+G30-H30 -> -1021849
A31: 2114-10 | B31: CC Carol Contreras | C31: 45689 | D31: Adjustment | E31: Reconciliation adjustment | G31: 20 | H31: 0 | I31: =I30+G31-H31 -> -1021829
A32: 2114-10 | B32: CC Carol Contreras | C32: 45691 | D32: Spend Money | E32: CC Expense | F32: almuerzo staff Brazil | G32: 0 | H32: 109395 | I32: =I31+G32-H32 -> -1131224
A33: 2114-10 | B33: CC Carol Contreras | C33: 45691 | D33: Spend Money | E33: CC Expense | F33: uber fruta oficina | G33: 0 | H33: 23607 | I33: =I32+G33-H33 -> -1154831
A34: 2114-10 | B34: CC Carol Contreras | C34: 45691 | D34: Spend Money | E34: CC Expense | F34: Cambio de pasaje francisco Balmaceda | G34: 0 | H34: 6600 | I34: =I33+G34-H34 -> -1161431
A35: 2114-10 | B35: CC Carol Contreras | C35: 45691 | D35: Spend Money | E35: CC Expense | F35: uber tramites bancarios | G35: 0 | H35: 4333 | I35: =I34+G35-H35 -> -1165764
A36: 2114-10 | B36: CC Carol Contreras | C36: 45691 | D36: Spend Money | E36: CC Expense | F36: uber tramites Bancarios | G36: 0 | H36: 3911 | I36: =I35+G36-H36 -> -1169675
A37: 2114-10 | B37: CC Carol Contreras | C37: 45691 | D37: Payable Payment | E37: Payment: PROD - RED DE TRANSPORTES COMERCIALES LTDA | F37: F/61615 | G37: 0 | H37: 113249 | I37: =I36+G37-H37 -> -1282924
A38: 2114-10 | B38: CC Carol Contreras | C38: 45691 | D38: Payable Payment | E38: Payment: PRODUCOTS TECNOLOGICOS B&V SPA | F38: F/6379 | G38: 0 | H38: 22990 | I38: =I37+G38-H38 -> -1305914
A39: 2114-10 | B39: CC Carol Contreras | C39: 45691 | D39: Adjustment | E39: Reconciliation adjustment | G39: 0 | H39: 1 | I39: =I38+G39-H39 -> -1305915
A40: 2114-10 | B40: CC Carol Contreras | C40: 45692 | D40: Spend Money | E40: CC Expense | F40: franui oficina | G40: 0 | H40: 27730 | I40: =I39+G40-H40 -> -1333645
A41: 2114-10 | B41: CC Carol Contreras | C41: 45693 | D41: Bank Transfer | E41: Bank Transfer from Citibank - CLP to CC Carol Contreras | F41: Carol CC payment | G41: 1994192 | H41: 0 | I41: =I40+G41-H41 -> 660547
A42: 2114-10 | B42: CC Carol Contreras | C42: 45693 | D42: Payable Payment | E42: Payment: INVERSIONES Y ASESORIAS RA SPA | F42: F/325 | G42: 0 | H42: 26980 | I42: =I41+G42-H42 -> 633567
A43: 2114-10 | B43: CC Carol Contreras | C43: 45694 | D43: Payable Payment | E43: Payment: Telefonica Chile S.A (Movistar) | F43: F/52597895 | G43: 0 | H43: 294600 | I43: =I42+G43-H43 -> 338967
A44: 2114-10 | B44: CC Carol Contreras | C44: 45694 | D44: Payable Payment | E44: Payment: LATAM AIRLINES GROUP SA | F44: F/6302257 | G44: 0 | H44: 152842 | I44: =I43+G44-H44 -> 186125
A45: 2114-10 | B45: CC Carol Contreras | C45: 45695 | D45: Spend Money | E45: CC Expense | F45: medias lunas staff brasil | G45: 0 | H45: 17990 | I45: =I44+G45-H45 -> 168135
A46: 2114-10 | B46: CC Carol Contreras | C46: 45695 | D46: Spend Money | E46: CC Expense | F46: almuerzo staff Brazil | G46: 0 | H46: 98120 | I46: =I45+G46-H46 -> 70015
A47: 2114-10 | B47: CC Carol Contreras | C47: 45695 | D47: Spend Money | E47: CC Expense | F47: uber happy hour staff brasil | G47: 0 | H47: 3052 | I47: =I46+G47-H47 -> 66963
A48: 2114-10 | B48: CC Carol Contreras | C48: 45695 | D48: Spend Money | E48: CC Expense | F48: happy hour staff brasil Malva loca | G48: 0 | H48: 312290 | I48: =I47+G48-H48 -> -245327
A49: 2114-10 | B49: CC Carol Contreras | C49: 45695 | D49: Spend Money | E49: CC Expense | F49: uber happy hour carol | G49: 0 | H49: 19471 | I49: =I48+G49-H49 -> -264798
A50: 2114-10 | B50: CC Carol Contreras | C50: 45695 | D50: Payable Payment | E50: Payment: Telefonica Chile S.A (Movistar) | F50: F/50708669 | G50: 0 | H50: 24003 | I50: =I49+G50-H50 -> -288801
A51: 2114-10 | B51: CC Carol Contreras | C51: 45699 | D51: Spend Money | E51: CC Expense | F51: uber fruta oficina martes 12 | G51: 0 | H51: 30031 | I51: =I50+G51-H51 -> -318832
... A54: 2114-10 | B54: CC Carol Contreras | C54: 45712 | D54: Spend Money | E54: CC Expense | F54: parlante oficina | G54: 0 | H54: 163980 | I54: =I53+G54-H54 -> -1348595
A55: 2114-10 | B55: CC Carol Contreras | C55: 45714 | D55: Spend Money | E55: Banco De Chile | G55: 0 | H55: 3862 | I55: =I54+G55-H55 -> -1352457
A56: 2114-10 | B56: CC Carol Contreras | C56: 45721 | D56: Payable Payment | E56: Payment: BECKER PADRUNO GRATTINI Y COMPANIA LTDA | F56: F1045340 | G56: 0 | H56: 102350 | I56: =I55+G56-H56 -> -1454807
A57: 2114-10 | B57: CC Carol Contreras | C57: 45721 | D57: Spend Money | E57: CC Expense | F57: traslado documentos bancarios | G57: 0 | H57: 6023 | I57: =I56+G57-H57 -> -1460830
A58: 2114-10 | B58: CC Carol Contreras | C58: 45721 | D58: Spend Money | E58: CC Expense | F58: traslado documentos Bancarios | G58: 0 | H58: 5299 | I58: =I57+G58-H58 -> -1466129
A59: 2114-10 | B59: CC Carol Contreras | C59: 45722 | D59: Spend Money | E59: CC Expense | F59: celebracion dia de la mujer | G59: 0 | H59: 110550 | I59: =I58+G59-H59 -> -1576679
A60: 2114-10 | B60: CC Carol Contreras | C60: 45722 | D60: Spend Money | E60: CC Expense | F60: celebracion dia de la mujer | G60: 0 | H60: 312510 | I60: =I59+G60-H60 -> -1889189
A61: 2114-10 | B61: CC Carol Contreras | C61: 45723 | D61: Bank Transfer | E61: Bank Transfer from Citibank - CLP to CC Carol Contreras | F61: Carol CC Payment | G61: 2436520 | H61: 0 | I61: =I60+G61-H61 -> 547331
A62: 2114-10 | B62: CC Carol Contreras | C62: 45726 | D62: Spend Money | E62: CC Expense | F62: cafe de grano | G62: 0 | H62: 101700 | I62: =I61+G62-H62 -> 445631
A63: 2114-10 | B63: CC Carol Contreras | C63: 45726 | D63: Spend Money | E63: CC Expense | F63: tramites bancarios | G63: 0 | H63: 5963 | I63: =I62+G63-H63 -> 439668
A64: 2114-10 | B64: CC Carol Contreras | C64: 45726 | D64: Spend Money | E64: CC Expense | F64: Tramites Bancarios | G64: 0 | H64: 6233 | I64: =I63+G64-H64 -> 433435
A65: 2114-10 | B65: CC Carol Contreras | C65: 45726 | D65: Payable Payment | E65: Payment: Comercializadora Sur del Mundo Limitada | F65: 18847 | G65: 0 | H65: 62980 | I65: =I64+G65-H65 -> 370455
A66: 2114-10 | B66: CC Carol Contreras | C66: 45726 | D66: Payable Payment | E66: Payment: Telefonica Chile S.A (Movistar) | F66: F/52606207 | G66: 0 | H66: 296759 | I66: =I65+G66-H66 -> 73696
A67: 2114-10 | B67: CC Carol Contreras | C67: 45726 | D67: Payable Payment | E67: Payment: Telefonica Chile S.A (Movistar) | F67: F/50708669 | G67: 0 | H67: 24003 | I67: =I66+G67-H67 -> 49693
... A71: 2114-10 | B71: CC Carol Contreras | C71: 45729 | D71: Payable Payment | E71: Payment: PROD - RED DE TRANSPORTES COMERCIALES LTDA | F71: 0000063157 | G71: 0 | H71: 96830 | I71: =I70+G71-H71 -> -381844
A72: 2114-10 | B72: CC Carol Contreras | C72: 45729 | D72: Spend Money | E72: CC Expense | G72: 0 | H72: 13970 | I72: =I71+G72-H72 -> -395814
A73: 2114-10 | B73: CC Carol Contreras | C73: 45732 | D73: Spend Money | E73: CC Expense | F73: adaptadores de vuelos para peru | G73: 0 | H73: 6400 | I73: =I72+G73-H73 -> -402214
A74: 2114-10 | B74: CC Carol Contreras | C74: 45732 | D74: Spend Money | E74: CC Expense | F74: snack oficina peru regalos | G74: 0 | H74: 5980 | I74: =I73+G74-H74 -> -408194
A75: 2114-10 | B75: CC Carol Contreras | C75: 45732 | D75: Spend Money | E75: CC Expense | F75: snack katherinne y Carol Aeropuerto | G75: 0 | H75: 10400 | I75: =I74+G75-H75 -> -418594
A76: 2114-10 | B76: CC Carol Contreras | C76: 45732 | D76: Spend Money | E76: CC Expense | F76: Cinta doble Contacto y no mas clavo | G76: 0 | H76: 28480 | I76: =I75+G76-H76 -> -447074
A77: 2114-10 | B77: CC Carol Contreras | C77: 45733 | D77: Spend Money | E77: CC Expense | F77: almuerzo carolina,katherinne y carol (pen168.30) | G77: 0 | H77: 43984 | I77: =I76+G77-H77 -> -491058
A78: 2114-10 | B78: CC Carol Contreras | C78: 45733 | D78: Spend Money | E78: CC Expense | F78: cena aeropuerto en efectivo con dinero girado desde el cajero (200.00 pen) | G78: 0 | H78: 62490 | I78: =I77+G78-H78 -> -553548
A79: 2114-10 | B79: CC Carol Contreras | C79: 45734 | D79: Spend Money | E79: Banco De Chile | G79: 0 | H79: 1087 | I79: =I78+G79-H79 -> -554635
A80: 2114-10 | B80: CC Carol Contreras | C80: 45734 | D80: Spend Money | E80: CC Expense | F80: Almuerzo admin mas raul Abogado lima (287.00 pen) | G80: 0 | H80: 75650 | I80: =I79+G80-H80 -> -630285
A81: 2114-10 | B81: CC Carol Contreras | C81: 45734 | D81: Spend Money | E81: CC Expense | F81: Salida staff peru (181.00 Pen) | G81: 0 | H81: 47712 | I81: =I80+G81-H81 -> -677997
A82: 2114-10 | B82: CC Carol Contreras | C82: 45735 | D82: Spend Money | E82: Banco De Chile | G82: 0 | H82: 1874 | I82: =I81+G82-H82 -> -679871
A83: 2114-10 | B83: CC Carol Contreras | C83: 45735 | D83: Spend Money | E83: Banco De Chile | G83: 0 | H83: 3889 | I83: =I82+G83-H83 -> -683760
A84: 2114-10 | B84: CC Carol Contreras | C84: 45735 | D84: Spend Money | E84: CC Expense | F84: snack regalo oficina chile (46.20 pen) | G84: 0 | H84: 12867 | I84: =I83+G84-H84 -> -696627
A85: 2114-10 | B85: CC Carol Contreras | C85: 45735 | D85: Spend Money | E85: CC Expense | F85: Bebestible Carol (7.10 pen) | G85: 0 | H85: 1883 | I85: =I84+G85-H85 -> -698510
A86: 2114-10 | B86: CC Carol Contreras | C86: 45735 | D86: Spend Money | E86: CC Expense | F86: almuerzo staff admin (176.00 pen) | G86: 0 | H86: 49008 | I86: =I85+G86-H86 -> -747518
A87: 2114-10 | B87: CC Carol Contreras | C87: 45735 | D87: Spend Money | E87: CC Expense | F87: salida staff admin y staff peru (370.00 pen) | G87: 0 | H87: 97713 | I87: =I86+G87-H87 -> -845231
A88: 2114-10 | B88: CC Carol Contreras | C88: 45736 | D88: Spend Money | E88: Banco De Chile | G88: 0 | H88: 1181 | I88: =I87+G88-H88 -> -846412
A89: 2114-10 | B89: CC Carol Contreras | C89: 45736 | D89: Spend Money | E89: Banco De Chile | G89: 0 | H89: 1218 | I89: =I88+G89-H89 -> -847630
A90: 2114-10 | B90: CC Carol Contreras | C90: 45736 | D90: Spend Money | E90: Banco De Chile | G90: 0 | H90: 319 | I90: =I89+G90-H90 -> -847949
A91: 2114-10 | B91: CC Carol Contreras | C91: 45736 | D91: Spend Money | E91: Banco De Chile | G91: 0 | H91: 47 | I91: =I90+G91-H91 -> -847996
A92: 2114-10 | B92: CC Carol Contreras | C92: 45736 | D92: Spend Money | E92: Banco De Chile | G92: 0 | H92: 2417 | I92: =I91+G92-H92 -> -850413
A93: 2114-10 | B93: CC Carol Contreras | C93: 45736 | D93: Spend Money | E93: CC Expense | F93: cabify vuelta visitas hoteles (24.02 pen) | G93: 0 | H93: 5459 | I93: =I92+G93-H93 -> -855872
A94: 2114-10 | B94: CC Carol Contreras | C94: 45736 | D94: Spend Money | E94: CC Expense | F94: cena equipo peru (1111.55 pen) | G94: 0 | H94: 293821 | I94: =I93+G94-H94 -> -1149693
A95: 2114-10 | B95: CC Carol Contreras | C95: 45736 | D95: Spend Money | E95: CC Expense | F95: almuerzo equipo peru (512.00 | G95: 0 | H95: 142899 | I95: =I94+G95-H95 -> -1292592
A96: 2114-10 | B96: CC Carol Contreras | C96: 45736 | D96: Spend Money | E96: CC Expense | F96: postres oficina peru (54.50 pen) | G96: 0 | H96: 14409 | I96: =I95+G96-H96 -> -1307001
A97: 2114-10 | B97: CC Carol Contreras | C97: 45736 | D97: Spend Money | E97: CC Expense | F97: cabify visita hoteles miraflores (20.65 pen) | G97: 0 | H97: 6169 | I97: =I96+G97-H97 -> -1313170
A98: 2114-10 | B98: CC Carol Contreras | C98: 45736 | D98: Spend Money | E98: CC Expense | F98: cabify salida a cenar (23.34 pen) | G98: 0 | H98: 6348 | I98: =I97+G98-H98 -> -1319518
A99: 2114-10 | B99: CC Carol Contreras | C99: 45737 | D99: Spend Money | E99: Banco De Chile | G99: 0 | H99: 3542 | I99: =I98+G99-H99 -> -1323060
A100: 2114-10 | B100: CC Carol Contreras | C100: 45737 | D100: Spend Money | E100: Banco De Chile | G100: 0 | H100: 131 | I100: =I99+G100-H100 -> -1323191
A101: 2114-10 | B101: CC Carol Contreras | C101: 45737 | D101: Spend Money | E101: Banco De Chile | G101: 0 | H101: 159 | I101: =I100+G101-H101 -> -1323350
A102: 2114-10 | B102: CC Carol Contreras | C102: 45737 | D102: Spend Money | E102: Banco De Chile | G102: 0 | H102: 150 | I102: =I101+G102-H102 -> -1323500
A103: 2114-10 | B103: CC Carol Contreras | C103: 45737 | D103: Spend Money | E103: Banco De Chile | G103: 0 | H103: 7271 | I103: =I102+G103-H103 -> -1330771
A104: 2114-10 | B104: CC Carol Contreras | C104: 45737 | D104: Spend Money | E104: Banco De Chile | G104: 0 | H104: 356 | I104: =I103+G104-H104 -> -1331127
A105: 2114-10 | B105: CC Carol Contreras | C105: 45737 | D105: Spend Money | E105: CC Expense | F105: almuerzo staff admin (207.00 pen) | G105: 0 | H105: 54789 | I105: =I104+G105-H105 -> -1385916
A106: 2114-10 | B106: CC Carol Contreras | C106: 45738 | D106: Spend Money | E106: CC Expense | F106: taxi aeropuerto casa Carol | G106: 0 | H106: 32000 | I106: =I105+G106-H106 -> -1417916
A107: 2114-10 | B107: CC Carol Contreras | C107: 45740 | D107: Spend Money | E107: Banco De Chile | G107: 0 | H107: 178 | I107: =I106+G107-H107 -> -1418094
A108: 2114-10 | B108: CC Carol Contreras | C108: 45740 | D108: Spend Money | E108: Banco De Chile | G108: 0 | H108: 1359 | I108: =I107+G108-H108 -> -1419453
A109: 2114-10 | B109: CC Carol Contreras | C109: 45742 | D109: Spend Money | E109: CC Expense | F109: cabify Jorge tramite bancario ida | G109: 0 | H109: 6353 | I109: =I108+G109-H109 -> -1425806
...

Sheet 11
A1: Comprobante | B1: Fec. Doc. | C1: Voucher | E1: Titular | F1: T.Doc/Nro | G1: Debe | H1: Haber | I1: Acumulado
A2: adig/1116 | B2: 45772 | C2: 2555 | D2: Glosa : TDC CLP JUAN CARVALLO | E2: JUAN CARVALLO JIMÉNEZ | H2: 122074 | I2: -3687220
A3: adig/1174 | B3: 45792 | C3: 2746 | D3: Glosa : Bank Transfer to CC Sebastián Carvallo. | E3: JUAN CARVALLO JIMÉNEZ | G3: 72314 | I3: -544463
A4: adig/1255 | B4: 45805 | C4: 2911 | D4: Glosa : TDC CLP JUAN sebastian CARVALLO | E4: JUAN CARVALLO JIMÉNEZ | H4: 161109 | I4: -498439
A5: adig/1553 | B5: 45805 | C5: 3504 | D5: Glosa : TDC CLP JUAN sebastian CARVALLO | E5: JUAN CARVALLO JIMÉNEZ | H5: 229285 | I5: -779243
A6: adig/1206 | B6: 45820 | C6: 2862 | D6: Glosa : Bank Transfer to CC Sebastián Carvallo. | E6: JUAN CARVALLO JIMÉNEZ | G6: 210396 | I6: 107093
A7: adig/1335 | B7: 45867 | C7: 3094 | D7: Glosa : TDC CLP JUAN sebastian CARVALLO | E7: JUAN CARVALLO JIMÉNEZ | H7: 293855 | I7: -3600643
A8: adig/1397 | B8: 45869 | C8: 3286 | D8: Glosa : APERTURA TDC J. SEBASTIAN C. ENERO | E8: JUAN CARVALLO JIMÉNEZ | H8: 650343 | I8: -13820934
A9: adig/1414 | B9: 45869 | C9: 3303 | D9: Glosa : APERTURA TDC JS. CARVALLO FEB | E9: JUAN CARVALLO JIMÉNEZ | H9: 20962 | I9: -20359392
D12: 2114-11 - CC Sebastián Carvallo | G12: 293855
B14: Fec. Doc. | C14: Voucher | E14: Titular | G14: Debe | H14: Haber | I14: Acumulado
B15: 45772 | C15: 2555 | D15: Glosa : TDC CLP JUAN CARVALLO | E15: JUAN CARVALLO JIMÉNEZ | H15: 122074 | I15: =-H15 -> -122074
B16: 45792 | C16: 2746 | D16: Glosa : Bank Transfer to CC Sebastián Carvallo. | E16: JUAN CARVALLO JIMÉNEZ | G16: 72314 | I16: =I15+G16-H16 -> -49760
B17: 45805 | C17: 2911 | D17: Glosa : TDC CLP JUAN sebastian CARVALLO | E17: JUAN CARVALLO JIMÉNEZ | H17: 161109 | I17: =I16+G17-H17 -> -210869
B18: 45805 | C18: 3504 | D18: Glosa : TDC CLP JUAN sebastian CARVALLO | E18: JUAN CARVALLO JIMÉNEZ | H18: 229285 | I18: =I17+G18-H18 -> -440154
B19: 45813 | C19: 2814 | D19: Glosa : Payment: ER - Sebastián Carvallo25.5 - Reimbursable Expense - Lundin Mining - Cand... | 25.5 - Reimbursable Expense - Lundin Mining - Cand... | E19: JUAN CARVALLO JIMÉNEZ | G19: 43000 | I19: =I18+G19-H19 -> -397154
B20: 45820 | C20: 2862 | D20: Glosa : Bank Transfer to CC Sebastián Carvallo. | E20: JUAN CARVALLO JIMÉNEZ | G20: 210396 | I20: =I19+G20-H20 -> -186758
B21: 45867 | C21: 3094 | D21: Glosa : TDC CLP JUAN sebastian CARVALLO | E21: JUAN CARVALLO JIMÉNEZ | H21: 293855 | I21: -4049198
B22: 45869 | C22: 3286 | D22: Glosa : APERTURA TDC J. SEBASTIAN C. ENERO | E22: JUAN CARVALLO JIMÉNEZ | H22: 650343 | I22: -15087471
B23: 45869 | C23: 3303 | D23: Glosa : APERTURA TDC JS. CARVALLO FEB | E23: JUAN CARVALLO JIMÉNEZ | H23: 20962 | I23: -21625929
B24: 45869 | C24: 3459 | D24: Glosa : Spend Money CC Expense ABRIL-JULIO 2114-11 | E24: JUAN CARVALLO JIMÉNEZ | H24: 118170 | I24: -26517189 | J24: ?
B25: 45869 | C25: 3459 | D25: Glosa : Spend Money CC Expense ABRIL-JULIO 2114-11 | E25: JUAN CARVALLO JIMÉNEZ | H25: 289936 | I25: -26807125 | J25: ?
B28: Fec. Doc. | C28: Voucher | E28: Titular | F28: T.Doc/Nro | G28: Debe | H28: Haber | I28: Acumulado
B29: 45701 | C29: 2282 | D29: Glosa : Pago Tarjeta de Credito | E29: JUAN CARVALLO JIMÉNEZ | G29: 650343 | I29: =+G29 -> 650343
B30: 45772 | C30: 2555 | D30: Glosa : TDC CLP JUAN CARVALLO | E30: JUAN CARVALLO JIMÉNEZ | H30: 122074 | I30: =I29+G30-H30 -> 528269
B31: 45792 | C31: 2746 | D31: Glosa : Bank Transfer to CC Sebastián Carvallo. | E31: JUAN CARVALLO JIMÉNEZ | G31: 72314 | I31: =I30+G31-H31 -> 600583
B32: 45805 | C32: 2911 | D32: Glosa : TDC CLP JUAN sebastian CARVALLO | E32: JUAN CARVALLO JIMÉNEZ | H32: 161109 | I32: =I31+G32-H32 -> 439474
B33: 45805 | C33: 3504 | D33: Glosa : TDC CLP JUAN sebastian CARVALLO | E33: JUAN CARVALLO JIMÉNEZ | H33: 229285 | I33: =I32+G33-H33 -> 210189
B34: 45813 | C34: 2814 | D34: Glosa : Payment: ER - Sebastián Carvallo25.5 - Reimbursable Expense - Lundin Mining - Cand... | 25.5 - Reimbursable Expense - Lundin Mining - Cand... | E34: JUAN CARVALLO JIMÉNEZ | G34: 43000 | I34: =I33+G34-H34 -> 253189
B35: 45820 | C35: 2862 | D35: Glosa : Bank Transfer to CC Sebastián Carvallo. | E35: JUAN CARVALLO JIMÉNEZ | G35: 210396 | I35: =I34+G35-H35 -> 463585
B36: 45867 | C36: 3094 | D36: Glosa : TDC CLP JUAN sebastian CARVALLO | E36: JUAN CARVALLO JIMÉNEZ | H36: 293855 | I36: =I35+G36-H36 -> 169730
B37: 45869 | C37: 3286 | D37: Glosa : APERTURA TDC J. SEBASTIAN C. ENERO | E37: JUAN CARVALLO JIMÉNEZ | H37: 650343 | I37: =I36+G37-H37 -> -480613
B38: 45869 | C38: 3303 | D38: Glosa : APERTURA TDC JS. CARVALLO FEB | E38: JUAN CARVALLO JIMÉNEZ | H38: 20962 | I38: =I37+G38-H38 -> -501575
B39: 45869 | C39: 3459 | D39: Glosa : Spend Money CC Expense ABRIL-JULIO 2114-11 | E39: JUAN CARVALLO JIMÉNEZ | H39: 118170 | I39: =I38+G39-H39 -> -619745
B40: 45869 | C40: 3459 | D40: Glosa : Spend Money CC Expense ABRIL-JULIO 2114-11 | E40: JUAN CARVALLO JIMÉNEZ | H40: 289936 | I40: =I39+G40-H40 -> -909681
B41: 45869 | C41: 3574 | D41: Glosa : compensa prov | E41: JUAN CARVALLO JIMÉNEZ | G41: 594864 | I41: =I40+G41-H41 -> -314817
B42: 45729 | C42: 2343 | D42: Glosa : Pago tarjeta de Credito | E42: JUAN CARVALLO JIMÉNEZ | G42: 20962 | I42: =I41+G42-H42 -> -293855
B43: 45882 | C43: 3259 | D43: Glosa : Sebastian´s cc payment | E43: JUAN SEBASTIAN CARVALLO JIMÉNEZ | G43: 293855 | I43: =I42+G43-H43 -> 0
B44: 45897 | C44: 3504 | D44: Glosa : TDC CLP JUAN sebastian CARVALLO | E44: JUAN SEBASTIAN CARVALLO JIMÉNEZ | H44: 37917 | I44: =I43+G44-H44 -> -37917
B45: 45897 | D45: provision | G45: 37919 | H45: 71641 | I45: =I44+G45-H45 -> -71639
B46: 45911 | C46: 3534 | D46: Glosa : SEBASTIAN CARVALLO | E46: JUAN SEBASTIAN CARVALLO JIMÉNEZ | G46: 37917 | I46: =I45+G46-H46 -> -33722
B47: 45926 | C47: 3579 | D47: Glosa : TDC CLP JUAN sebastian CARVALLO | E47: JUAN SEBASTIAN CARVALLO JIMÉNEZ | H47: 50192 | I47: =I46+G47-H47 -> -83914
A48: adig/1683 | B48: 45944 | C48: 3747 | D48: JUAN SEBASTIAN CARVALLO JIMÉNEZ | G48: 50192 | I48: =I47+G48-H48 -> -33722
A49: adig/1698 | B49: 45958 | C49: 3801 | D49: JUAN SEBASTIAN CARVALLO JIMÉNEZ | H49: 246372 | I49: =I48+G49-H49 -> -280094
A50: adig/1740 | B50: 45974 | C50: 3907 | D50: =+A50 -> adig/1740 | E50: JUAN SEBASTIAN CARVALLO JIMÉNEZ | G50: 246372 | I50: =I49+G50-H50 -> -33722
A51: adig/1827 | B51: 46009 | C51: 4119 | D51: Glosa : Visa Arg Sebastian Carvallo | E51: JUAN SEBASTIAN CARVALLO JIMÉNEZ | I51: =I50+G51-H51 -> -33722
A52: adig/1838 | B52: 46017 | C52: 4132 | D52: Glosa : TDC JS CARVALLO | E52: JUAN SEBASTIAN CARVALLO JIMÉNEZ | H52: 6314 | I52: =I51+G52-H52 -> -40036
B55: 45897 | C55: 3504 | D55: Glosa : TDC CLP JUAN sebastian CARVALLO | E55: JUAN SEBASTIAN CARVALLO JIMÉNEZ | H55: 39.94 | I55: =-H55 -> -39.94 | J55: =H55*965.28 -> 38553.283
B56: 45926 | C56: 3579 | D56: Glosa : TDC CLP JUAN sebastian CARVALLO | E56: JUAN SEBASTIAN CARVALLO JIMÉNEZ | H56: 239.08 | I56: =I55+G56-H56 -> -279.02 | J56: =H56*962.39 -> 230088.2
B57: 45926 | C57: 3579 | D57: Glosa : TDC CLP JUAN sebastian CARVALLO | E57: JUAN SEBASTIAN CARVALLO JIMÉNEZ | G57: 39.94 | I57: =I56+G57-H57 -> -239.08 | J57: =I57*962.39 -> -230088.2
B58: 45958 | C58: 3801 | E58: JUAN SEBASTIAN CARVALLO JIMÉNEZ | G58: 239.08 | I58: =I57+G58-H58 -> 2.8421709e-14 | J58: 224302
B59: 46017 | C59: 4132 | D59: Glosa : TDC JS CARVALLO | E59: JUAN SEBASTIAN CARVALLO JIMÉNEZ | H59: 101.42 | I59: =I58+G59-H59 -> -101.42 | J59: =-H59*907.13 -> -92001.125 | K59: =+J59+I52 -> -132037.12
A60: adig/1838

Sheet 11_X
A1: Account Code | B1: Account | C1: Date | D1: Source | E1: Description | F1: Reference | G1: Debit | H1: Credit
A2: 2114-11 | B2: CC Sebastián Carvallo | C2: 45677 | D2: Payable Payment | E2: Payment: INMOBILIARIA COLIPI SPA | F2: F/86375 | G2: 0 | H2: 243096 | I2: =+G2-H2 -> -243096
A3: 2114-11 | B3: CC Sebastián Carvallo | C3: 45677 | D3: Spend Money | E3: CC Expense | F3: Cena 20-Enero | G3: 0 | H3: 26840 | I3: =I2+G3-H3 -> -269936
A4: 2114-11 | B4: CC Sebastián Carvallo | C4: 45678 | D4: Spend Money | E4: CC Expense | F4: Cena 21-Enero | G4: 0 | H4: 26840 | I4: =I3+G4-H4 -> -296776
A5: 2114-11 | B5: CC Sebastián Carvallo | C5: 45684 | D5: Payable Payment | E5: Payment: INMOBILIARIA COLIPI SPA | F5: F/87375 | G5: 0 | H5: 303858 | I5: =I4+G5-H5 -> -600634
A6: 2114-11 | B6: CC Sebastián Carvallo | C6: 45684 | D6: Spend Money | E6: CC Expense | F6: Cena 27-Enero | G6: 0 | H6: 19960 | I6: =I5+G6-H6 -> -620594
A7: 2114-11 | B7: CC Sebastián Carvallo | C7: 45684 | D7: Adjustment | E7: Reconciliation adjustment | G7: 270 | H7: 0 | I7: =I6+G7-H7 -> -620324
A8: 2114-11 | B8: CC Sebastián Carvallo | C8: 45685 | D8: Spend Money | E8: CC Expense | F8: Cena 28-Enero | G8: 0 | H8: 26180 | I8: =I7+G8-H8 -> -646504
A9: 2114-11 | B9: CC Sebastián Carvallo | C9: 45686 | D9: Spend Money | E9: Banco De Chile | G9: 0 | H9: 3839 | I9: =I8+G9-H9 -> -650343
A10: 2114-11 | B10: CC Sebastián Carvallo | C10: 45686 | D10: Spend Money | E10: CC Expense | F10: Cena 29-Enero | G10: 0 | H10: 17100 | I10: =I9+G10-H10 -> -667443
A11: 2114-11 | B11: CC Sebastián Carvallo | C11: 45701 | D11: Bank Transfer | E11: Bank Transfer from Citibank - CLP to CC Sebastián Carvallo | F11: CC payment Sebas | G11: 650343 | H11: 0 | I11: =I10+G11-H11 -> -17100
A12: 2114-11 | B12: CC Sebastián Carvallo | C12: 45714 | D12: Spend Money | E12: Banco De Chile | G12: 0 | H12: 3862 | I12: =I11+G12-H12 -> -20962
A13: 2114-11 | B13: CC Sebastián Carvallo | C13: 45729 | D13: Bank Transfer | E13: Bank Transfer from Citibank - CLP to CC Sebastián Carvallo | F13: SC´s credit card payment | G13: 20962 | H13: 0 | I13: =I12+G13-H13 -> 0
A14: 2114-11 | B14: CC Sebastián Carvallo | C14: 45769 | D14: Spend Money | E14: CC Expense | F14: Almuerzo K. Bollmann - A. Gonzalez - S. Carvallo | G14: 0 | H14: 19500 | I14: =I13+G14-H14 -> -19500
A15: 2114-11 | B15: CC Sebastián Carvallo | C15: 45771 | D15: Spend Money | E15: CC Expense | F15: Almuerzo K. Bollmann - A. Gonzalez - S. Carvallo | G15: 0 | H15: 98670 | I15: =I14+G15-H15 -> -118170
A16: 2114-11 | B16: CC Sebastián Carvallo | C16: 45772 | D16: Spend Money | E16: Banco De Chile | G16: 0 | H16: 3904 | I16: =I15+G16-H16 -> -122074
A17: 2114-11 | B17: CC Sebastián Carvallo | C17: 45782 | D17: Spend Money | E17: CC Expense | F17: Taxi aeropuerto a Hotel Chagall | G17: 0 | H17: 10000 | I17: =I16+G17-H17 -> -132074
A18: 2114-11 | B18: CC Sebastián Carvallo | C18: 45785 | D18: Payable Payment | E18: Payment: Hotelera Domus Ltda | F18: Pago restante | G18: 0 | H18: 49287 | I18: =I17+G18-H18 -> -181361
A19: 2114-11 | B19: CC Sebastián Carvallo | C19: 45789 | D19: Spend Money | E19: CC Expense | F19: Taxi Aeropuerto a Hotel | G19: 0 | H19: 10000 | I19: =I18+G19-H19 -> -191361
A20: 2114-11 | B20: CC Sebastián Carvallo | C20: 45789 | D20: Spend Money | E20: CC Expense | F20: Almuerzo da 1 | G20: 0 | H20: 21065 | I20: =I19+G20-H20 -> -212426
A21: 2114-11 | B21: CC Sebastián Carvallo | C21: 45791 | D21: Spend Money | E21: CC Expense | F21: Cena da 3 | G21: 0 | H21: 16115 | I21: =I20+G21-H21 -> -228541
A22: 2114-11 | B22: CC Sebastián Carvallo | C22: 45792 | D22: Bank Transfer | E22: Bank Transfer from Citibank - CLP to CC Sebastián Carvallo | F22: SCs credit card payment | G22: 72314 | H22: 0 | I22: =I21+G22-H22 -> -156227
A23: 2114-11 | B23: CC Sebastián Carvallo | C23: 45792 | D23: Spend Money | E23: CC Expense | F23: Cenas das 1 y 2 | G23: 0 | H23: 50251 | I23: =I22+G23-H23 -> -206478
A24: 2114-11 | B24: CC Sebastián Carvallo | C24: 45805 | D24: Spend Money | E24: Banco De Chile | G24: 0 | H24: 3918 | I24: =I23+G24-H24 -> -210396
A25: 2114-11 | B25: CC Sebastián Carvallo | C25: 45820 | D25: Bank Transfer | E25: Bank Transfer from Citibank - CLP to CC Sebastián Carvallo | F25: Sebastian Carvallo´s credit card | G25: 210396 | H25: 0 | I25: =I24+G25-H25 -> 0
A26: 2114-11 | B26: CC Sebastián Carvallo | C26: 45845 | D26: Spend Money | E26: CC Expense | F26: Desayuno da 7-Jul | G26: 0 | H26: 12320 | I26: =I25+G26-H26 -> -12320
A27: 2114-11 | B27: CC Sebastián Carvallo | C27: 45845 | D27: Spend Money | E27: CC Expense | F27: Almuerzo da 7-Jul | G27: 0 | H27: 8500 | I27: =I26+G27-H27 -> -20820
A28: 2114-11 | B28: CC Sebastián Carvallo | C28: 45848 | D28: Spend Money | E28: CC Expense | F28: Cenas das 7,8,9-Jul | G28: 0 | H28: 58498 | I28: =I27+G28-H28 -> -79318
A29: 2114-11 | B29: CC Sebastián Carvallo | C29: 45859 | D29: Spend Money | E29: CC Expense | F29: Desayuno 21-Jul | G29: 0 | H29: 7000 | I29: =I28+G29-H29 -> -86318
A30: 2114-11 | B30: CC Sebastián Carvallo | C30: 45859 | D30: Spend Money | E30: CC Expense | F30: Taxi desde aeropuerto a mina Candelaria | G30: 0 | H30: 60000 | I30: =I29+G30-H30 -> -146318
A31: 2114-11 | B31: CC Sebastián Carvallo | C31: 45862 | D31: Spend Money | E31: CC Expense | F31: Cenas 21,22,23-Jul | G31: 0 | H31: 77018 | I31: =I30+G31-H31 -> -223336
A32: 2114-11 | B32: CC Sebastián Carvallo | C32: 45862 | D32: Spend Money | E32: CC Expense | F32: Taxi desde mina Candelaria a aeropuerto | G32: 0 | H32: 60000 | I32: =I31+G32-H32 -> -283336
A33: 2114-11 | B33: CC Sebastián Carvallo | C33: 45863 | D33: Spend Money | E33: CC Expense | F33: Estacionamiento mutual de seguridad | G33: 0 | H33: 6600 | I33: =I32+G33-H33 -> -289936
A34: 2114-11 | B34: CC Sebastián Carvallo | C34: 45867 | D34: Spend Money | E34: Banco De Chile | G34: 0 | H34: 3919 | I34: =I33+G34-H34 -> -293855
A35: 2114-11 | B35: CC Sebastián Carvallo | C35: 45882 | D35: Bank Transfer | E35: Bank Transfer from Citibank - CLP to CC Sebastián Carvallo | F35: Sebastian´s cc payment | G35: 293855 | H35: 0 | I35: =I34+G35-H35 -> 0
A36: 2114-11 | B36: CC Sebastián Carvallo | C36: 45894 | D36: Spend Money | E36: Provision Expenses CC | G36: 0 | H36: 33000 | I36: =I35+G36-H36 -> -33000
A37: 2114-11 | B37: CC Sebastián Carvallo | C37: 45894 | D37: Spend Money | E37: Provision Expenses CC | G37: 0 | H37: 16979 | I37: =I36+G37-H37 -> -49979
A38: 2114-11 | B38: CC Sebastián Carvallo | C38: 45895 | D38: Spend Money | E38: Banco De Chile | G38: 0 | H38: 433 | I38: =I37+G38-H38 -> -50412
A39: 2114-11 | B39: CC Sebastián Carvallo | C39: 45895 | D39: Spend Money | E39: Provision Expenses CC | G39: 0 | H39: 21662 | I39: =I38+G39-H39 -> -72074
A40: 2114-11 | B40: CC Sebastián Carvallo | C40: 45896 | D40: Spend Money | E40: Banco De Chile | G40: 0 | H40: 3934 | I40: =I39+G40-H40 -> -76008
A41: 2114-11 | B41: CC Sebastián Carvallo | C41: 45896 | D41: Spend Money | E41: Banco De Chile | G41: 0 | H41: 552 | I41: =I40+G41-H41 -> -76560
A42: 2114-11 | B42: CC Sebastián Carvallo | C42: 45901 | D42: Spend Money | E42: Banco De Chile | G42: 0 | H42: 205 | I42: =I41+G42-H42 -> -76765
A43: 2114-11 | B43: CC Sebastián Carvallo | C43: 45901 | D43: Spend Money | E43: Banco De Chile | G43: 0 | H43: 4037 | I43: =I42+G43-H43 -> -80802
A44: 2114-11 | B44: CC Sebastián Carvallo | C44: 45901 | D44: Spend Money | E44: CC Expense | F44: Snack para turno noche | G44: 0 | H44: 7997 | I44: =I43+G44-H44 -> -88799
A45: 2114-11 | B45: CC Sebastián Carvallo | C45: 45901 | D45: Spend Money | E45: CC Expense | F45: Taxi aeropuerto a hotel | G45: 0 | H45: 21662 | I45: =I44+G45-H45 -> -110461
A46: 2114-11 | B46: CC Sebastián Carvallo | C46: 45901 | D46: Spend Money | E46: CC Expense | F46: Taxi hotel a aeropuerto | G46: 0 | H46: 16979 | I46: =I45+G46-H46 -> -127440
A47: 2114-11 | B47: CC Sebastián Carvallo | C47: 45901 | D47: Spend Money | E47: Provision Expenses CC | G47: 21662 | H47: 0 | I47: =I46+G47-H47 -> -105778
A48: 2114-11 | B48: CC Sebastián Carvallo | C48: 45901 | D48: Spend Money | E48: Provision Expenses CC | G48: 16979 | H48: 0 | I48: =I47+G48-H48 -> -88799
A49: 2114-11 | B49: CC Sebastián Carvallo | C49: 45901 | D49: Spend Money | E49: Provision Expenses CC | G49: 33000 | H49: 0 | I49: =I48+G49-H49 -> -55799
A50: 2114-11 | B50: CC Sebastián Carvallo | C50: 45901 | D50: Spend Money | E50: CC Expense | F50: Hotel y cena | G50: 0 | H50: 159181 | I50: =I49+G50-H50 -> -214980
A51: 2114-11 | B51: CC Sebastián Carvallo | C51: 45901 | D51: Adjustment | E51: Reconciliation adjustment | G51: 0 | H51: 1 | I51: =I50+G51-H51 -> -214981
A52: 2114-11 | B52: CC Sebastián Carvallo | C52: 45901 | D52: Spend Money | E52: CC Expense | F52: Almuerzo da 25 de agosto | G52: 0 | H52: 33000 | I52: =I51+G52-H52 -> -247981
A53: 2114-11 | B53: CC Sebastián Carvallo | C53: 45909 | D53: Spend Money | E53: CC Expense | F53: Snack en aeropuerto | G53: 0 | H53: 8882 | I53: =I52+G53-H53 -> -256863
A54: 2114-11 | B54: CC Sebastián Carvallo | C54: 45909 | D54: Spend Money | E54: CC Expense | F54: Cena en aeropuerto | G54: 0 | H54: 53753 | I54: =I53+G54-H54 -> -310616
A55: 2114-11 | B55: CC Sebastián Carvallo | C55: 45910 | D55: Spend Money | E55: Banco De Chile | G55: 0 | H55: 1365 | I55: =I54+G55-H55 -> -311981
A56: 2114-11 | B56: CC Sebastián Carvallo | C56: 45910 | D56: Spend Money | E56: Banco De Chile | G56: 0 | H56: 224 | I56: =I55+G56-H56 -> -312205
A57: 2114-11 | B57: CC Sebastián Carvallo | C57: 45911 | D57: Bank Transfer | E57: Bank Transfer from Citibank - CLP to CC Sebastián Carvallo | F57: Sebastians credit card payment | G57: 37919 | H57: 0 | I57: =I56+G57-H57 -> -274286
A58: 2114-11 | B58: CC Sebastián Carvallo | C58: 45911 | D58: Spend Money | E58: Banco De Chile | G58: 0 | H58: 620 | I58: =I57+G58-H58 -> -274906
A59: 2114-11 | B59: CC Sebastián Carvallo | C59: 45926 | D59: Spend Money | E59: Banco De Chile | G59: 0 | H59: 26 | I59: =I58+G59-H59 -> -274932
A60: 2114-11 | B60: CC Sebastián Carvallo | C60: 45926 | D60: Spend Money | E60: Banco De Chile | G60: 0 | H60: 3949 | I60: =I59+G60-H60 -> -278881
A61: 2114-11 | B61: CC Sebastián Carvallo | C61: 45926 | D61: Spend Money | E61: Banco De Chile | G61: 0 | H61: 1125 | I61: =I60+G61-H61 -> -280006
A62: 2114-11 | B62: CC Sebastián Carvallo | C62: 45944 | D62: Bank Transfer | E62: Bank Transfer from Citibank - CLP to CC Sebastián Carvallo | F62: SC´s credita card payment | G62: 50192 | H62: 0 | I62: =I61+G62-H62 -> -229814
A63: 2114-11 | B63: CC Sebastián Carvallo | C63: 45944 | D63: Spend Money | E63: Banco De Chile | G63: 0 | H63: 6397 | I63: =I62+G63-H63 -> -236211
A64: 2114-11 | B64: CC Sebastián Carvallo | C64: 45958 | D64: Spend Money | E64: Banco De Chile | G64: 0 | H64: 156 | I64: =I63+G64-H64 -> -236367
A65: 2114-11 | B65: CC Sebastián Carvallo | C65: 45958 | D65: Spend Money | E65: Banco De Chile | G65: 0 | H65: 3958 | I65: =I64+G65-H65 -> -240325
A66: 2114-11 | B66: CC Sebastián Carvallo | C66: 45958 | D66: Spend Money | E66: Banco De Chile | G66: 0 | H66: 6047 | I66: =I65+G66-H66 -> -246372
A67: 2114-11 | B67: CC Sebastián Carvallo | C67: 45974 | D67: Bank Transfer | E67: Bank Transfer from Citibank - CLP to CC Sebastián Carvallo | F67: Credit card payment SC | G67: 246372 | H67: 0 | I67: =I66+G67-H67 -> 0
A68: 2114-11 | B68: CC Sebastián Carvallo | C68: 45992 | D68: Spend Money | E68: CC Expense | F68: Almuerzo | G68: 0 | H68: 9448.62 | I68: =I67+G68-H68 -> -9448.62
A69: 2114-11 | B69: CC Sebastián Carvallo | C69: 45993 | D69: Spend Money | E69: CC Expense | G69: 0 | H69: 241 | I69: =I68+G69-H69 -> -9689.62
A70: 2114-11 | B70: CC Sebastián Carvallo | C70: 45993 | D70: Spend Money | E70: CC Expense | F70: Almuerzo (Anto, Caroline, Denisse, Pancho, Jorge y yo) | G70: 0 | H70: 82340.54 | I70: =I69+G70-H70 -> -92030.16
A71: 2114-11 | B71: CC Sebastián Carvallo | C71: 45994 | D71: Spend Money | E71: CC Expense | G71: 0 | H71: 2102 | I71: =I70+G71-H71 -> -94132.16
A72: 2114-11 | B72: CC Sebastián Carvallo | C72: 46017 | D72: Spend Money | E72: Banco De Chile | G72: 0 | H72: 3971 | I72: =I71+G72-H72 -> -98103.16 | J72: 0 | K72: dif balance xero y mayor xero
G73: =SUM(G2:G72) -> 1654264 | H73: =SUM(H2:H72) -> 1752367.2 | I73: =G73-H73 -> -98103.16
J79: =98103+'11'!K59 -> -33934.125 | K79: diferencia balance xero y magnus

Sheet 12
A1: Comprobante | B1: Fec. Doc. | C1: Voucher | E1: Titular | F1: T.Doc/Nro | G1: Debe | H1: Haber | I1: Acumulado
A2: adig/1283 | B2: 45772 | C2: 2939 | D2: Glosa : TDC CLP/USD FRANCISCO MIRANDA | E2: FRANCISCO MIRANDA RIADI | H2: 5014 | I2: -4599126
A3: adig/1173 | B3: 45792 | C3: 2745 | D3: Glosa : Bank Transfer to CC Francisco Miranda. | E3: FRANCISCO MIRANDA RIADI | G3: 5014 | I3: -616777
A4: adig/1252 | B4: 45805 | C4: 2908 | D4: Glosa : Tarjeta de Credito F.Miranda | E4: FRANCISCO MIRANDA RIADI | H4: 71087 | I4: -157860
A5: adig/1204 | B5: 45820 | C5: 2860 | D5: Glosa : Bank Transfer to CC Francisco Miranda. | E5: FRANCISCO MIRANDA RIADI | G5: 71087 | I5: -182324
A6: adig/1258 | B6: 45834 | C6: 2914 | D6: Glosa : TDC CLP/USD FRANCISCO MIRANDA | E6: FRANCISCO MIRANDA RIADI | H6: 4322 | I6: -1609478
A7: adig/1314 | B7: 45848 | C7: 3051 | D7: Glosa : Bank Transfer to CC Francisco Miranda. | E7: FRANCISCO MIRANDA RIADI | G7: 20216 | I7: -702028
A8: adig/1395 | B8: 45869 | C8: 3284 | D8: Glosa : apertura TDC F. MIRANDA ENERO | E8: FRANCISCO MIRANDA RIADI | H8: 181839 | I8: -13170591
A9: adig/1411 | B9: 45869 | C9: 3300 | D9: Glosa : APERTURA TDC F. MIRANDA FEB | E9: FRANCISCO MIRANDA RIADI | H9: 819483 | I9: -18296477
A10: adig/1416 | B10: 45869 | C10: 3305 | D10: Glosa : APERTURA TDC F. MIRANDA MARZO | E10: FRANCISCO MIRANDA RIADI | H10: 221541 | I10: -20886375
A11: adig/1283 | B11: 45772 | C11: 2939 | D11: Glosa : TDC CLP/USD FRANCISCO MIRANDA | E11: FRANCISCO MIRANDA RIADI | G11: 45.39 | H11: 45.39 | I11: -294.57
A12: adig/1258 | B12: 45834 | C12: 2914 | D12: Glosa : TDC CLP/USD FRANCISCO MIRANDA | E12: FRANCISCO MIRANDA RIADI | G12: 16.73 | H12: 16.73 | I12: -5059
D15: 2114-12 - CC Francisco Miranda | F15: 0
B18: Fec. Doc. | C18: Voucher | E18: Titular | G18: Debe | H18: Haber | I18: Acumulado
B19: 45772 | C19: 2939 | D19: Glosa : TDC CLP/USD FRANCISCO MIRANDA | E19: FRANCISCO MIRANDA RIADI | H19: 5014 | I19: -4477448
B20: 45792 | C20: 2745 | D20: Glosa : Bank Transfer to CC Francisco Miranda. | E20: FRANCISCO MIRANDA RIADI | G20: 5014 | I20: -456983
B21: 45805 | C21: 2908 | D21: Glosa : Tarjeta de Credito F.Miranda | E21: FRANCISCO MIRANDA RIADI | H21: 71087 | I21: -236772
B22: 45820 | C22: 2860 | D22: Glosa : Bank Transfer to CC Francisco Miranda. | E22: FRANCISCO MIRANDA RIADI | G22: 71087 | I22: -114598
B23: 45834 | C23: 2914 | D23: Glosa : TDC CLP/USD FRANCISCO MIRANDA | E23: FRANCISCO MIRANDA RIADI | H23: 4322 | I23: -1532752
B24: 45848 | C24: 3051 | D24: Glosa : Bank Transfer to CC Francisco Miranda. | E24: FRANCISCO MIRANDA RIADI | G24: 20216 | I24: -504572
B25: 45869 | C25: 3284 | D25: Glosa : apertura TDC F. MIRANDA ENERO | E25: FRANCISCO MIRANDA RIADI | H25: 181839 | I25: -14437128
B26: 45869 | C26: 3300 | D26: Glosa : APERTURA TDC F. MIRANDA FEB | E26: FRANCISCO MIRANDA RIADI | H26: 819483 | I26: -19563014
B27: 45869 | C27: 3305 | D27: Glosa : APERTURA TDC F. MIRANDA MARZO | E27: FRANCISCO MIRANDA RIADI | H27: 221541 | I27: -22152912
B28: 45869 | C28: 3465 | D28: Glosa : FONDO POR RENDIR VISA Francisco Miranda | E28: FRANCISCO MIRANDA RIADI | H28: 100602 | I28: -27352524
B30: Fec. Doc. | C30: Voucher | E30: Titular | F30: T.Doc/Nro | G30: Debe | H30: Haber | I30: Acumulado
B31: 45772 | C31: 2939 | D31: Glosa : TDC CLP/USD FRANCISCO MIRANDA | E31: FRANCISCO MIRANDA RIADI | H31: 5014 | I31: =-H31 -> -5014
B32: 45792 | C32: 2745 | D32: Glosa : Bank Transfer to CC Francisco Miranda. | E32: FRANCISCO MIRANDA RIADI | G32: 5014 | I32: =I31+G32-H32 -> 0
B33: 45805 | C33: 2908 | D33: Glosa : Tarjeta de Credito F.Miranda | E33: FRANCISCO MIRANDA RIADI | H33: 71087 | I33: =I32+G33-H33 -> -71087
B34: 45820 | C34: 2860 | D34: Glosa : Bank Transfer to CC Francisco Miranda. | E34: FRANCISCO MIRANDA RIADI | G34: 71087 | I34: =I33+G34-H34 -> 0
B35: 45834 | C35: 2914 | D35: Glosa : TDC CLP/USD FRANCISCO MIRANDA | E35: FRANCISCO MIRANDA RIADI | H35: 4322 | I35: =I34+G35-H35 -> -4322
B36: 45848 | C36: 3051 | D36: Glosa : Bank Transfer to CC Francisco Miranda. | E36: FRANCISCO MIRANDA RIADI | G36: 20216 | I36: =I35+G36-H36 -> 15894
B37: 45869 | C37: 3284 | D37: Glosa : apertura TDC F. MIRANDA ENERO | E37: FRANCISCO MIRANDA RIADI | H37: 181839 | I37: =I36+G37-H37 -> -165945
B38: 45869 | C38: 3300 | D38: Glosa : APERTURA TDC F. MIRANDA FEB | E38: FRANCISCO MIRANDA RIADI | H38: 819483 | I38: =I37+G38-H38 -> -985428
B39: 45869 | C39: 3305 | D39: Glosa : APERTURA TDC F. MIRANDA MARZO | E39: FRANCISCO MIRANDA RIADI | H39: 221541 | I39: =I38+G39-H39 -> -1206969
B40: 45869 | C40: 3465 | D40: Glosa : FONDO POR RENDIR VISA Francisco Miranda | E40: FRANCISCO MIRANDA RIADI | H40: 100602 | I40: =I39+G40-H40 -> -1307571
B41: 45869 | C41: 3574 | D41: Glosa : compensa prov | E41: FRANCISCO MIRANDA RIADI | G41: 84708 | I41: =I40+G41-H41 -> -1222863
B42: 45701 | C42: 2283 | D42: Glosa : Pago Tarjeta de Credito | E42: FRANCISCO MIRANDA RIADI | G42: 181839 | I42: =I41+G42-H42 -> -1041024
B43: 45729 | C43: 2344 | D43: Glosa : Pago tarjeta de Credito | E43: FRANCISCO MIRANDA RIADI | G43: 819483 | I43: =I42+G43-H43 -> -221541
B44: 45762 | C44: 2508 | D44: Glosa : Pago tarjeta de credio Francisco Miranda | E44: FRANCISCO MIRANDA RIADI | G44: 221541 | I44: =I43+G44-H44 -> 0
A45: adig/1768 | B45: 45987 | C45: 3956 | D45: =+A45 -> adig/1768 | E45: FRANCISCO MIRANDA RIADI | H45: 447848 | I45: =I44+G45-H45 -> -447848
A46: adig/1808 | B46: 46006 | C46: 4057 | D46: Glosa : Bank Transfer to CC Francisco Miranda. | E46: FRANCISCO MIRANDA RIADI | G46: 447848 | I46: =I45+G46-H46 -> 0
A47: adig/1835 | B47: 46017 | C47: 4129 | D47: Glosa : TDC CLP/USD FRANCISCO MIRANDA | E47: FRANCISCO MIRANDA RIADI | H47: 7314 | I47: =I46+G47-H47 -> -7314
A49: adig/1835 | B49: 46017 | C49: 4129 | D49: Glosa : TDC CLP/USD FRANCISCO MIRANDA | E49: FRANCISCO MIRANDA RIADI | H49: 144.43 | I49: =-H49 -> -144.43 | J49: =-H49*907.13 -> -131016.79 | K49: =+J49+I47 -> -138330.79

Sheet 12_x
A1: Account Code | B1: Account | C1: Date | D1: Source | E1: Description | F1: Reference | G1: Debit | H1: Credit
A2: 2114-12 | B2: CC Francisco Miranda | C2: 45678 | D2: Payable Payment | E2: Payment: Procedimientos Clinicos Alto Tabancura SA | F2: Medical | G2: 0 | H2: 108000 | I2: =+G2-H2 -> -108000
A3: 2114-12 | B3: CC Francisco Miranda | C3: 45686 | D3: Spend Money | E3: Banco De Chile | G3: 0 | H3: 3839 | I3: =I2+G3-H3 -> -111839
A4: 2114-12 | B4: CC Francisco Miranda | C4: 45687 | D4: Payable Payment | E4: Payment: LATAM | F4: F/6291929 | G4: 0 | H4: 651180 | I4: =I3+G4-H4 -> -763019
A5: 2114-12 | B5: CC Francisco Miranda | C5: 45691 | D5: Spend Money | E5: STARBUCKS COFFEE CHILE S.A. | G5: 0 | H5: 8600 | I5: =I4+G5-H5 -> -771619
A6: 2114-12 | B6: CC Francisco Miranda | C6: 45692 | D6: Spend Money | E6: Banco De Chile | G6: 0 | H6: 384 | I6: =I5+G6-H6 -> -772003
A7: 2114-12 | B7: CC Francisco Miranda | C7: 45700 | D7: Spend Money | E7: Saba Aeropuerto Chile SpA | G7: 0 | H7: 129000 | I7: =I6+G7-H7 -> -901003
A8: 2114-12 | B8: CC Francisco Miranda | C8: 45700 | D8: Spend Money | E8: Gastronomia las piedras | G8: 0 | H8: 21417 | I8: =I7+G8-H8 -> -922420
A9: 2114-12 | B9: CC Francisco Miranda | C9: 45701 | D9: Bank Transfer | E9: Bank Transfer from Citibank - CLP to CC Francisco Miranda | F9: CC payment Francisco | G9: 181839 | H9: 0 | I9: =I8+G9-H9 -> -740581
A10: 2114-12 | B10: CC Francisco Miranda | C10: 45701 | D10: Spend Money | E10: Ministerio de Relaciones Exteriores Ecuador | G10: 0 | H10: 199754.1 | I10: =I9+G10-H10 -> -940335.1
A11: 2114-12 | B11: CC Francisco Miranda | C11: 45702 | D11: Spend Money | E11: Banco De Chile | G11: 0 | H11: 5040 | I11: =I10+G11-H11 -> -945375.1
A12: 2114-12 | B12: CC Francisco Miranda | C12: 45714 | D12: Spend Money | E12: Banco De Chile | G12: 0 | H12: 3862 | I12: =I11+G12-H12 -> -949237.1
A13: 2114-12 | B13: CC Francisco Miranda | C13: 45729 | D13: Bank Transfer | E13: Bank Transfer from Citibank - CLP to CC Francisco Miranda | F13: FM´s credit card payment | G13: 819483 | H13: 0 | I13: =I12+G13-H13 -> -129754.1
A14: 2114-12 | B14: CC Francisco Miranda | C14: 45743 | D14: Spend Money | E14: Banco De Chile | G14: 0 | H14: 133 | I14: =I13+G14-H14 -> -129887.1
A15: 2114-12 | B15: CC Francisco Miranda | C15: 45743 | D15: Spend Money | E15: Banco De Chile | G15: 0 | H15: 3887 | I15: =I14+G15-H15 -> -133774.1
A16: 2114-12 | B16: CC Francisco Miranda | C16: 45743 | D16: Spend Money | E16: Banco De Chile | G16: 0 | H16: 5921 | I16: =I15+G16-H16 -> -139695.1
A17: 2114-12 | B17: CC Francisco Miranda | C17: 45744 | D17: Spend Money | E17: CC Expense | F17: Cena VIaje Inicial | G17: 0 | H17: 10000 | I17: =I16+G17-H17 -> -149695.1
A18: 2114-12 | B18: CC Francisco Miranda | C18: 45747 | D18: Spend Money | E18: Banco De Chile | G18: 0 | H18: 1845.9 | I18: =I17+G18-H18 -> -151541
A19: 2114-12 | B19: CC Francisco Miranda | C19: 45748 | D19: Spend Money | E19: CC Expense | F19: CENA | G19: 0 | H19: 36049.42 | I19: =I18+G19-H19 -> -187590.42
A20: 2114-12 | B20: CC Francisco Miranda | C20: 45748 | D20: Spend Money | E20: CC Expense | F20: ALMUERZO | G20: 0 | H20: 6517.78 | I20: =I19+G20-H20 -> -194108.2
A21: 2114-12 | B21: CC Francisco Miranda | C21: 45762 | D21: Bank Transfer | E21: Bank Transfer from Citibank - CLP to CC Francisco Miranda | F21: FM´s Credit Card Payment | G21: 221541 | H21: 0 | I21: =I20+G21-H21 -> 27432.8
A22: 2114-12 | B22: CC Francisco Miranda | C22: 45781 | D22: Spend Money | E22: CC Expense | F22: Almuerzo - Ida en Argentina Perito Moreno | G22: 0 | H22: 15682.2 | I22: =I21+G22-H22 -> 11750.6
A23: 2114-12 | B23: CC Francisco Miranda | C23: 45782 | D23: Spend Money | E23: Banco BICE | G23: 0 | H23: 402 | I23: =I22+G23-H23 -> 11348.6
A24: 2114-12 | B24: CC Francisco Miranda | C24: 45790 | D24: Spend Money | E24: CC Expense | F24: Almuerzo - Regreso en Balmaceda | G24: 0 | H24: 22070 | I24: =I23+G24-H24 -> -10721.4
A25: 2114-12 | B25: CC Francisco Miranda | C25: 45792 | D25: Bank Transfer | E25: Bank Transfer from Citibank - CLP to CC Francisco Miranda | F25: FM´s credit card payment | G25: 5014 | H25: 0 | I25: =I24+G25-H25 -> -5707.4
A26: 2114-12 | B26: CC Francisco Miranda | C26: 45792 | D26: Spend Money | E26: Banco De Chile | G26: 0 | H26: 6020.8 | I26: =I25+G26-H26 -> -11728.2
A27: 2114-12 | B27: CC Francisco Miranda | C27: 45805 | D27: Spend Money | E27: Banco BICE | G27: 0 | H27: 29 | I27: =I26+G27-H27 -> -11757.2
A28: 2114-12 | B28: CC Francisco Miranda | C28: 45805 | D28: Spend Money | E28: Banco BICE | G28: 0 | H28: 3918 | I28: =I27+G28-H28 -> -15675.2
A29: 2114-12 | B29: CC Francisco Miranda | C29: 45805 | D29: Spend Money | E29: Banco De Chile | G29: 0 | H29: 1094 | I29: =I28+G29-H29 -> -16769.2
A30: 2114-12 | B30: CC Francisco Miranda | C30: 45820 | D30: Bank Transfer | E30: Bank Transfer from Citibank - CLP to CC Francisco Miranda | F30: Francisco Miranda´s Credit Card | G30: 71087 | H30: 0 | I30: =I29+G30-H30 -> 54317.8
A31: 2114-12 | B31: CC Francisco Miranda | C31: 45834 | D31: Spend Money | E31: Banco De Chile | G31: 0 | H31: 10 | I31: =I30+G31-H31 -> 54307.8
A32: 2114-12 | B32: CC Francisco Miranda | C32: 45834 | D32: Spend Money | E32: Banco De Chile | G32: 0 | H32: 3926 | I32: =I31+G32-H32 -> 50381.8
A33: 2114-12 | B33: CC Francisco Miranda | C33: 45834 | D33: Spend Money | E33: Banco De Chile | G33: 0 | H33: 386 | I33: =I32+G33-H33 -> 49995.8
A34: 2114-12 | B34: CC Francisco Miranda | C34: 45838 | D34: Spend Money | E34: Banco De Chile | G34: 0 | H34: 211.8 | I34: =I33+G34-H34 -> 49784
A35: 2114-12 | B35: CC Francisco Miranda | C35: 45848 | D35: Bank Transfer | E35: Bank Transfer from Citibank - CLP to CC Francisco Miranda | F35: FMs credit card payment | G35: 20216 | H35: 0 | I35: =I34+G35-H35 -> 70000
A36: 2114-12 | B36: CC Francisco Miranda | C36: 45973 | D36: Payable Payment | E36: Payment: Hotelera Domus Ltda | F36: 56400 | G36: 0 | H36: 373950 | I36: =I35+G36-H36 -> -303950
A37: 2114-12 | B37: CC Francisco Miranda | C37: 45973 | D37: Spend Money | E37: COMERCIAL SERPAN SPA | F37: Arriendo de Auto para viajar Aeropuerto a Candelaria | G37: 0 | H37: 69934 | I37: =I36+G37-H37 -> -373884
A38: 2114-12 | B38: CC Francisco Miranda | C38: 45986 | D38: Spend Money | E38: Banco De Chile | G38: 0 | H38: 3964 | I38: =I37+G38-H38 -> -377848
A39: 2114-12 | B39: CC Francisco Miranda | C39: 45992 | D39: Spend Money | E39: CC Expense | F39: Almuerzos Equipo SAM, Jorge, Denisse, Cari, Anto y Francisco | G39: 0 | H39: 60872.99 | I39: =I38+G39-H39 -> -438720.99
A40: 2114-12 | B40: CC Francisco Miranda | C40: 45993 | D40: Spend Money | E40: Banco De Chile | G40: 0 | H40: 1556 | I40: =I39+G40-H40 -> -440276.99
A41: 2114-12 | B41: CC Francisco Miranda | C41: 45994 | D41: Spend Money | E41: CC Expense | F41: Almuerzos Equipo SAM, Jorge, Denisse, Cari, Anto y Francisco | G41: 0 | H41: 69841.94 | I41: =I40+G41-H41 -> -510118.93
A42: 2114-12 | B42: CC Francisco Miranda | C42: 45995 | D42: Spend Money | E42: Banco De Chile | G42: 0 | H42: 1787 | I42: =I41+G42-H42 -> -511905.93
A43: 2114-12 | B43: CC Francisco Miranda | C43: 46006 | D43: Bank Transfer | E43: Bank Transfer from Citibank - CLP to CC Francisco Miranda | F43: Francisco CC Payment | G43: 447848 | I43: =I42+G43-H43 -> -64057.93
A44: 2114-12 | B44: CC Francisco Miranda | C44: 46017 | D44: Spend Money | E44: Banco De Chile | G44: 0 | H44: 3971 | I44: =I43+G44-H44 -> -68028.93 | J44: =68029-138029 -> -70000 | K44: dif balance xero y mayor xero
G45: =SUM(G2:G44) -> 1767028 | H45: =SUM(H2:H44) -> 1835056.9 | I45: =G45-H45 -> -68028.93
J53: =138029+'12'!K49 -> -301.7859 | K53: diferencia balance xero y magnus

Sheet 13
A1: Comprobante | B1: Fec. Doc. | C1: Voucher | E1: Titular | F1: T.Doc/Nro | G1: Debe | H1: Haber | I1: Acumulado
A2: adig/1117 | B2: 45772 | C2: 2556 | D2: Glosa : TDC CLP-USD CAITLIN WHEAT | E2: CAITLIN JOY WHEAT | H2: 100022 | I2: -3787242
A3: adig/1170 | B3: 45792 | C3: 2742 | D3: Glosa : Bank Transfer to CC Caitlin Wheat. | E3: CAITLIN JOY WHEAT | G3: 100022 | I3: -4499104
A4: adig/1250 | B4: 45805 | C4: 2906 | D4: Glosa : TDC CLP-USD CAITLIN WHEAT | E4: CAITLIN JOY WHEAT | H4: 450611 | I4: 1144650
A5: adig/1202 | B5: 45820 | C5: 2858 | D5: Glosa : Bank Transfer to CC Caitlin Wheat. | E5: CAITLIN JOY WHEAT | G5: 450611 | I5: -353860
A6: adig/1386 | B6: 45869 | C6: 3275 | D6: Glosa : reclasifica tdc enero | E6: CAITLIN JOY WHEAT | H6: 260913 | I6: -9600107
A7: adig/1410 | B7: 45869 | C7: 3299 | D7: Glosa : APERTURA TDC C. W FEB | E7: CAITLIN JOY WHEAT | H7: 3872 | I7: -17476994
A8: adig/1415 | B8: 45869 | C8: 3304 | D8: Glosa : APERTURA TDC C. WEATH MARZO | E8: CAITLIN JOY WHEAT | H8: 305442 | I8: -20664834
A9: adig/1117 | B9: 45772 | C9: 2556 | D9: Glosa : TDC CLP-USD CAITLIN WHEAT | E9: CAITLIN JOY WHEAT | H9: 249.18 | I9: -249.18
A10: adig/1250 | B10: 45805 | C10: 2906 | D10: Glosa : TDC CLP-USD CAITLIN WHEAT | E10: CAITLIN JOY WHEAT | G10: 249.18 | I10: -543.75
D13: 2114-13 - CC Caitlin Wheat | E13: 0
B25: Fec. Doc. | C25: Voucher | E25: Titular | G25: Debe | H25: Haber | I25: Acumulado
B26: 45772 | C26: 2556 | D26: Glosa : TDC CLP-USD CAITLIN WHEAT | E26: CAITLIN JOY WHEAT | H26: 100022 | I26: -3665564
B27: 45792 | C27: 2742 | D27: Glosa : Bank Transfer to CC Caitlin Wheat. | E27: CAITLIN JOY WHEAT | G27: 100022 | I27: -4339310
B28: 45805 | C28: 2906 | D28: Glosa : TDC CLP-USD CAITLIN WHEAT | E28: CAITLIN JOY WHEAT | H28: 450611 | I28: 1065738
B29: 45813 | C29: 2813 | D29: Glosa : Payment: ER - Caitlin Wheat25.5 - Reimbursable Expense - Reimbursement May 20... | 25.5 - Reimbursable Expense - Reimbursement May 20... | E29: CAITLIN JOY WHEAT | G29: 2300 | I29: -799745
B30: 45820 | C30: 2858 | D30: Glosa : Bank Transfer to CC Caitlin Wheat. | E30: CAITLIN JOY WHEAT | G30: 450611 | I30: -286134
B31: 45869 | C31: 3275 | D31: Glosa : reclasifica tdc enero | E31: CAITLIN JOY WHEAT | H31: 260913 | I31: -10866644
B32: 45869 | C32: 3299 | D32: Glosa : APERTURA TDC C. W FEB | E32: CAITLIN JOY WHEAT | H32: 3872 | I32: -18743531
B33: 45869 | C33: 3304 | D33: Glosa : APERTURA TDC C. WEATH MARZO | E33: CAITLIN JOY WHEAT | H33: 305442 | I33: -21931371
B34: 45869 | C34: 3454 | D34: Glosa : FONDO POR RENDIR Antonieta Gonzalez | E34: CAITLIN JOY WHEAT | H34: 235579 | I34: -25193304
B36: Fec. Doc. | C36: Voucher | E36: Titular | F36: T.Doc/Nro | G36: Debe | H36: Haber | I36: Acumulado
B37: 45772 | C37: 2556 | D37: Glosa : TDC CLP-USD CAITLIN WHEAT | E37: CAITLIN JOY WHEAT | H37: 100022 | I37: =-H37 -> -100022
B38: 45792 | C38: 2742 | D38: Glosa : Bank Transfer to CC Caitlin Wheat. | E38: CAITLIN JOY WHEAT | G38: 100022 | I38: =I37+G38-H38 -> 0
B39: 45805 | C39: 2906 | D39: Glosa : TDC CLP-USD CAITLIN WHEAT | E39: CAITLIN JOY WHEAT | H39: 450611 | I39: =I38+G39-H39 -> -450611
B40: 45813 | C40: 2813 | D40: Glosa : Payment: ER - Caitlin Wheat25.5 - Reimbursable Expense - Reimbursement May 20... | 25.5 - Reimbursable Expense - Reimbursement May 20... | E40: CAITLIN JOY WHEAT | G40: 2300 | I40: =I39+G40-H40 -> -448311
B41: 45820 | C41: 2858 | D41: Glosa : Bank Transfer to CC Caitlin Wheat. | E41: CAITLIN JOY WHEAT | G41: 450611 | I41: =I40+G41-H41 -> 2300
B42: 45869 | C42: 3275 | D42: Glosa : reclasifica tdc enero | E42: CAITLIN JOY WHEAT | H42: 260913 | I42: =I41+G42-H42 -> -258613
B43: 45869 | C43: 3299 | D43: Glosa : APERTURA TDC C. W FEB | E43: CAITLIN JOY WHEAT | H43: 3872 | I43: =I42+G43-H43 -> -262485
B44: 45869 | C44: 3304 | D44: Glosa : APERTURA TDC C. WEATH MARZO | E44: CAITLIN JOY WHEAT | H44: 305442 | I44: =I43+G44-H44 -> -567927
B45: 45869 | C45: 3454 | D45: Glosa : FONDO POR RENDIR Antonieta Gonzalez | E45: CAITLIN JOY WHEAT | H45: 235579 | I45: =I44+G45-H45 -> -803506
B46: 45869 | C46: 3574 | D46: Glosa : compensa prov | E46: CAITLIN JOY WHEAT | G46: 233279 | I46: =I45+G46-H46 -> -570227
B47: 45762 | C47: 2511 | D47: Glosa : Pago tarjeta de credito Caitlin Wheat | E47: CAITLIN JOY WHEAT | G47: 305442 | I47: =I46+G47-H47 -> -264785
B48: 45701 | C48: 2281 | D48: Glosa : Pago Tarjeta de Credito | E48: CAITLIN JOY WHEAT | G48: 260913 | I48: =I47+G48-H48 -> -3872
B49: 45729 | C49: 2342 | D49: Glosa : Pago tarjeta de Credito | E49: CAITLIN JOY WHEAT | G49: 3872 | I49: =I48+G49-H49 -> 0
B50: 45900 | C50: 3483 | D50: Glosa : TDC CLP-USD CAITLIN WHEAT | E50: CAITLIN JOY WHEAT | H50: 965161 | I50: =I49+G50-H50 -> -965161
H51: 99370 | I51: =I50+G51-H51 -> -1064531
B57: 45904 | C57: 3529 | D57: Glosa : 25.8 - Reimbursable Expense - Reimbursements Augus... | 25.8 - Reimbursable Expense - Reimbursements Augus... | E57: CAITLIN JOY WHEAT | G57: 78080 | I57: =I51+G57-H57 -> -986451
B58: 45911 | C58: 3530 | D58: Glosa : 25.9 - Reimbursable Expense - Reimbursement - Empa... | 25.9 - Reimbursable Expense - Reimbursement - Empa... | E58: CAITLIN JOY WHEAT | G58: 67000 | H58: 67000 | I58: =I57+G58-H58 -> -986451
B59: 45911 | C59: 3533 | D59: Glosa : 25.9 - Reimbursable Expense - Reimbursement - Empa... | 25.9 - Reimbursable Expense - Reimbursement - Empa... | E59: CAITLIN JOY WHEAT | G59: 965161 | I59: =I58+G59-H59 -> -21290
B60: 45926 | C60: 3581 | D60: Glosa : TDC CLP-USD CAITLIN WHEAT | E60: CAITLIN JOY WHEAT | H60: 943249 | I60: =I59+G60-H60 -> -964539
A61: adig/1685 | B61: 45944 | C61: 3749 | D61: CAITLIN JOY WHEAT | G61: 943249 | H61: 158948 | I61: =I60+G61-H61 -> -180238 | J61: -1709221 | K61: xero
A62: adig/1696 | B62: 45958 | C62: 3799 | D62: CAITLIN JOY WHEAT | H62: 1550273 | I62: =I61+G62-H62 -> -1730511 | J62: =J61-I62 -> 21290
A63: adig/1741 | B63: 45974 | C63: 3908 | D63: =+A63 -> adig/1741 | E63: CAITLIN JOY WHEAT | G63: 1550273 | I63: =I62+G63-H63 -> -180238
A64: adig/1765 | B64: 45987 | C64: 3953 | D64: =+A64 -> adig/1765 | E64: CAITLIN JOY WHEAT | H64: 1296486 | I64: =I63+G64-H64 -> -1476724
A65: adig/1771 | B65: 45991 | C65: 3969 | D65: =+A65 -> adig/1771 | E65: CAITLIN JOY WHEAT | H65: 164850 | I65: =I64+G65-H65 -> -1641574
A66: adig/1842 | B66: 45992 | C66: 4136 | D66: Glosa : Travel expenses Brazil - Nov2025 - Latam 6960411 | E66: CAITLIN JOY WHEAT | I66: =I65+G66-H66 -> -1641574
A67: adig/1806 | B67: 45995 | C67: 4055 | D67: Glosa : Credit card payment CW | E67: CAITLIN JOY WHEAT | I67: =I66+G67-H67 -> -1641574
A68: adig/1810 | B68: 46006 | C68: 4059 | D68: Glosa : Credit card payment CW | E68: CAITLIN JOY WHEAT | G68: 1296486 | I68: =I67+G68-H68 -> -345088
A69: adig/1812 | B69: 46017 | C69: 4061 | D69: Glosa : Credit card payment CW | E69: CAITLIN JOY WHEAT | G69: 4059 | I69: =I68+G69-H69 -> -341029
A70: adig/1833 | B70: 46017 | C70: 4127 | D70: Glosa : TDC CAITLYN WEAT | E70: CAITLIN JOY WHEAT | H70: 1202263 | I70: =I69+G70-H70 -> -1543292
A73: adig/1833 | B73: 46017 | C73: 4127 | D73: Glosa : TDC CAITLYN WEAT | E73: CAITLIN JOY WHEAT | H73: 48.56 | I73: =-H73 -> -48.56 | J73: =-H73*907.13 -> -44050.233 | K73: =+J73+I70 -> -1587342.2

Sheet 13_x
A1: Account Code | B1: Account | C1: Date | D1: Source | E1: Description | F1: Reference | G1: Debit | H1: Credit
A2: 2114-13 | B2: CC Caitlin Wheat | C2: 45670 | D2: Bank Transfer | E2: Bank Transfer from Citibank - CLP to CC Caitlin Wheat | F2: CC Automatic Payment | G2: 31740 | H2: 0 | I2: =+G2-H2 -> 31740
A3: 2114-13 | B3: CC Caitlin Wheat | C3: 45670 | D3: Payable Payment | E3: Payment: Soc. Gast Las Vacas Gordas Ltda | F3: B/344113 | G3: 0 | H3: 257074 | I3: =I2+G3-H3 -> -225334
A4: 2114-13 | B4: CC Caitlin Wheat | C4: 45686 | D4: Spend Money | E4: Banco De Chile | G4: 0 | H4: 3839 | I4: =I3+G4-H4 -> -229173
A5: 2114-13 | B5: CC Caitlin Wheat | C5: 45701 | D5: Bank Transfer | E5: Bank Transfer from Citibank - CLP to CC Caitlin Wheat | F5: CC Payment Caitlin | G5: 260913 | H5: 0 | I5: =I4+G5-H5 -> 31740
A6: 2114-13 | B6: CC Caitlin Wheat | C6: 45709 | D6: Spend Money | E6: Banco De Chile | G6: 0 | H6: 10 | I6: =I5+G6-H6 -> 31730
A7: 2114-13 | B7: CC Caitlin Wheat | C7: 45709 | D7: Spend Money | E7: CVFY.APP | G7: 0 | H7: 504.14 | I7: =I6+G7-H7 -> 31225.86
A8: 2114-13 | B8: CC Caitlin Wheat | C8: 45714 | D8: Spend Money | E8: Banco De Chile | G8: 0 | H8: 3862 | I8: =I7+G8-H8 -> 27363.86
A9: 2114-13 | B9: CC Caitlin Wheat | C9: 45716 | D9: Spend Money | E9: CC Expense | F9: International Womens day gift - wallet | G9: 0 | H9: 231942 | I9: =I8+G9-H9 -> -204578.14
A10: 2114-13 | B10: CC Caitlin Wheat | C10: 45716 | D10: Spend Money | E10: CC Expense | F10: International Womens day gift - chocolate | G10: 0 | H10: 73500 | I10: =I9+G10-H10 -> -278078.14
A11: 2114-13 | B11: CC Caitlin Wheat | C11: 45729 | D11: Bank Transfer | E11: Bank Transfer from Citibank - CLP to CC Caitlin Wheat | F11: CW´s credit card payment | G11: 3872 | H11: 0 | I11: =I10+G11-H11 -> -274206.14
A12: 2114-13 | B12: CC Caitlin Wheat | C12: 45743 | D12: Spend Money | E12: Banco De Chile | G12: 0 | H12: 3887 | I12: =I11+G12-H12 -> -278093.14
A13: 2114-13 | B13: CC Caitlin Wheat | C13: 45743 | D13: Spend Money | E13: Banco De Chile | G13: 0 | H13: 185 | I13: =I12+G13-H13 -> -278278.14
A14: 2114-13 | B14: CC Caitlin Wheat | C14: 45747 | D14: Receive Money | E14: Banco De Chile | G14: 165.14 | H14: 0 | I14: =I13+G14-H14 -> -278113
A15: 2114-13 | B15: CC Caitlin Wheat | C15: 45755 | D15: Spend Money | E15: CC Expense | F15: Australia Visa for Antonieta Gonzalez to attend APAC Conference ($197.73AUD/127.67 USD) | G15: 0 | H15: 120550.5 | I15: =I14+G15-H15 -> -398663.5
A16: 2114-13 | B16: CC Caitlin Wheat | C16: 45757 | D16: Spend Money | E16: Banco De Chile | G16: 0 | H16: 2985 | I16: =I15+G16-H16 -> -401648.5
A17: 2114-13 | B17: CC Caitlin Wheat | C17: 45762 | D17: Bank Transfer | E17: Bank Transfer from Citibank - CLP to CC Caitlin Wheat | F17: CW´s credit payment | G17: 309853 | H17: 0 | I17: =I16+G17-H17 -> -91795.5
A18: 2114-13 | B18: CC Caitlin Wheat | C18: 45762 | D18: Spend Money | E18: CC Expense | F18: First aide course | G18: 0 | H18: 90000 | I18: =I17+G18-H18 -> -181795.5
A19: 2114-13 | B19: CC Caitlin Wheat | C19: 45764 | D19: Spend Money | E19: CC Expense | F19: Australia Visa for Katherinne Alarcon ($197.73AUD/127.51USD) | G19: 0 | H19: 115029.25 | I19: =I18+G19-H19 -> -296824.75
A20: 2114-13 | B20: CC Caitlin Wheat | C20: 45768 | D20: Spend Money | E20: Banco De Chile | G20: 0 | H20: 3133 | I20: =I19+G20-H20 -> -299957.75
A21: 2114-13 | B21: CC Caitlin Wheat | C21: 45772 | D21: Spend Money | E21: Banco De Chile | G21: 0 | H21: 3904 | I21: =I20+G21-H21 -> -303861.75
A22: 2114-13 | B22: CC Caitlin Wheat | C22: 45776 | D22: Spend Money | E22: CC Expense | F22: Team lunch - Denisse Castro graduation | G22: 0 | H22: 201890 | I22: =I21+G22-H22 -> -505751.75
A23: 2114-13 | B23: CC Caitlin Wheat | C23: 45778 | D23: Adjustment | E23: Reconciliation adjustment | G23: 0 | H23: 4 | I23: =I22+G23-H23 -> -505755.75
A24: 2114-13 | B24: CC Caitlin Wheat | C24: 45792 | D24: Bank Transfer | E24: Bank Transfer from Citibank - CLP to CC Caitlin Wheat | F24: CW´s credit card payment | G24: 100022 | H24: 0 | I24: =I23+G24-H24 -> -405733.75
A25: 2114-13 | B25: CC Caitlin Wheat | C25: 45792 | D25: Spend Money | E25: Banco De Chile | G25: 0 | H25: 3633.25 | I25: =I24+G25-H25 -> -409367
A26: 2114-13 | B26: CC Caitlin Wheat | C26: 45805 | D26: Spend Money | E26: Banco De Chile | G26: 0 | H26: 158 | I26: =I25+G26-H26 -> -409525
A27: 2114-13 | B27: CC Caitlin Wheat | C27: 45805 | D27: Spend Money | E27: Banco De Chile | G27: 0 | H27: 3918 | I27: =I26+G27-H27 -> -413443
A28: 2114-13 | B28: CC Caitlin Wheat | C28: 45805 | D28: Spend Money | E28: Banco De Chile | G28: 0 | H28: 5935 | I28: =I27+G28-H28 -> -419378
A29: 2114-13 | B29: CC Caitlin Wheat | C29: 45818 | D29: Receive Money | E29: Banco De Chile | G29: 507 | H29: 0 | I29: =I28+G29-H29 -> -418871
A30: 2114-13 | B30: CC Caitlin Wheat | C30: 45820 | D30: Bank Transfer | E30: Bank Transfer from Citibank - CLP to CC Caitlin Wheat | F30: Caitlin wheat´s credit card payemtn | G30: 450611 | H30: 0 | I30: =I29+G30-H30 -> 31740
A31: 2114-13 | B31: CC Caitlin Wheat | C31: 45877 | D31: Spend Money | E31: CC Expense | F31: Unimarc - Choripan - Farewell Carol & Uni lunch | G31: 0 | H31: 88153 | I31: =I30+G31-H31 -> -56413
A32: 2114-13 | B32: CC Caitlin Wheat | C32: 45882 | D32: Spend Money | E32: CC Expense | F32: Chilenazo - Dia de Mineros | G32: 0 | H32: 209873 | I32: =I31+G32-H32 -> -266286
A33: 2114-13 | B33: CC Caitlin Wheat | C33: 45889 | D33: Spend Money | E33: FACTORY NINE SPA | F33: 9237 | G33: 0 | H33: 22990 | I33: =I32+G33-H33 -> -289276
A34: 2114-13 | B34: CC Caitlin Wheat | C34: 45890 | D34: Payable Payment | E34: Payment: LATAM AIRLINES GROUP SA | F34: 6746703 | G34: 0 | H34: 449610 | I34: =I33+G34-H34 -> -738886
A35: 2114-13 | B35: CC Caitlin Wheat | C35: 45896 | D35: Spend Money | E35: Banco De Chile | G35: 0 | H35: 3934 | I35: =I34+G35-H35 -> -742820
A36: 2114-13 | B36: CC Caitlin Wheat | C36: 45896 | D36: Spend Money | E36: CC Expense | F36: Oxxo - Comida para Happy Hour | G36: 0 | H36: 21390 | I36: =I35+G36-H36 -> -764210
A37: 2114-13 | B37: CC Caitlin Wheat | C37: 45897 | D37: Spend Money | E37: CHILE HOTELES LIMITADA | F37: 56199 | G37: 0 | H37: 190601 | I37: =I36+G37-H37 -> -954811
A38: 2114-13 | B38: CC Caitlin Wheat | C38: 45898 | D38: Spend Money | E38: Falabella | F38: Fallabella 5381937 | G38: 0 | H38: 77980 | I38: =I37+G38-H38 -> -1032791
A39: 2114-13 | B39: CC Caitlin Wheat | C39: 45902 | D39: Spend Money | E39: CC Expense | F39: Coca Cola - bebidas y cervezas para la oficina - Extras por fiestas patrias | G39: 0 | H39: 138260 | I39: =I38+G39-H39 -> -1171051
A40: 2114-13 | B40: CC Caitlin Wheat | C40: 45903 | D40: Spend Money | E40: BECKER PADRUNO GRATTINI Y COMPANIA LTDA | F40: F001068227 / Confiteria - snacks oficina | G40: 0 | H40: 76920 | I40: =I39+G40-H40 -> -1247971
A41: 2114-13 | B41: CC Caitlin Wheat | C41: 45903 | D41: Spend Money | E41: Distribucion y Alimentos FF SPA | F41: F1334 / Melbourne Cafe - Cafe oficina | G41: 0 | H41: 135600 | I41: =I40+G41-H41 -> -1383571
A42: 2114-13 | B42: CC Caitlin Wheat | C42: 45903 | D42: Spend Money | E42: CC Expense | F42: Unimarc - office supplies | G42: 0 | H42: 47640 | I42: =I41+G42-H42 -> -1431211
A43: 2114-13 | B43: CC Caitlin Wheat | C43: 45904 | D43: Payable Payment | E43: Payment: Telefonica Chile S.A (Movistar) | F43: 53695238 | G43: 0 | H43: 302372 | I43: =I42+G43-H43 -> -1733583
A44: 2114-13 | B44: CC Caitlin Wheat | C44: 45904 | D44: Payable Payment | E44: Payment: Telefonica Chile S.A (Movistar) | F44: F/50708669 | G44: 0 | H44: 24003 | I44: =I43+G44-H44 -> -1757586
A45: 2114-13 | B45: CC Caitlin Wheat | C45: 45910 | D45: Spend Money | E45: CC Expense | F45: F2213265910 / Unimarc - fiestas patrias extras | G45: 0 | H45: 12971 | I45: =I44+G45-H45 -> -1770557
A46: 2114-13 | B46: CC Caitlin Wheat | C46: 45910 | D46: Spend Money | E46: CC Expense | F46: F2210643599 / Unimarc - Fiestas Patrias | G46: 0 | H46: 102164 | I46: =I45+G46-H46 -> -1872721
A47: 2114-13 | B47: CC Caitlin Wheat | C47: 45911 | D47: Bank Transfer | E47: Bank Transfer from Citibank - CLP to CC Caitlin Wheat | F47: Caitlin´s credit card payemnt | G47: 965161 | H47: 0 | I47: =I46+G47-H47 -> -907560
A48: 2114-13 | B48: CC Caitlin Wheat | C48: 45926 | D48: Spend Money | E48: Banco De Chile | G48: 0 | H48: 3949 | I48: =I47+G48-H48 -> -911509
A49: 2114-13 | B49: CC Caitlin Wheat | C49: 45937 | D49: Spend Money | E49: CC Expense | F49: Coca cola - drinks for the office | G49: 0 | H49: 113390 | I49: =I48+G49-H49 -> -1024899
A50: 2114-13 | B50: CC Caitlin Wheat | C50: 45937 | D50: Payable Payment | E50: Payment: Telefonica Chile S.A (Movistar) | F50: 53704919 | G50: 0 | H50: 303072 | I50: =I49+G50-H50 -> -1327971
A51: 2114-13 | B51: CC Caitlin Wheat | C51: 45937 | D51: Payable Payment | E51: Payment: BECKER PADRUNO GRATTINI Y COMPANIA LTDA | F51: 1068935 | G51: 0 | H51: 101465 | I51: =I50+G51-H51 -> -1429436
A52: 2114-13 | B52: CC Caitlin Wheat | C52: 45937 | D52: Payable Payment | E52: Payment: Telefonica Chile S.A (Movistar) | F52: F/50708669 | G52: 0 | H52: 24003 | I52: =I51+G52-H52 -> -1453439
A53: 2114-13 | B53: CC Caitlin Wheat | C53: 45938 | D53: Spend Money | E53: CC Expense | F53: Unimarc - office supplies | G53: 0 | H53: 36810 | I53: =I52+G53-H53 -> -1490249
A54: 2114-13 | B54: CC Caitlin Wheat | C54: 45938 | D54: Payable Payment | E54: Payment: COMERCIALIZADORA DE INSUMOS | F54: 16341 | G54: 0 | H54: 548226 | I54: =I53+G54-H54 -> -2038475
A55: 2114-13 | B55: CC Caitlin Wheat | C55: 45943 | D55: Payable Payment | E55: Payment: Cafe Diario Encomenderos Spa | F55: 5294 | G55: 0 | H55: 33000 | I55: =I54+G55-H55 -> -2071475
A56: 2114-13 | B56: CC Caitlin Wheat | C56: 45943 | D56: Payable Payment | E56: Payment: Justo Spa | F56: 484349 | G56: 0 | H56: 491 | I56: =I55+G56-H56 -> -2071966
A57: 2114-13 | B57: CC Caitlin Wheat | C57: 45943 | D57: Payable Payment | E57: Payment: SERVICIOS EQUIFAX CHILE LIMITADA | F57: 3981626 | G57: 0 | H57: 27990 | I57: =I56+G57-H57 -> -2099956
A58: 2114-13 | B58: CC Caitlin Wheat | C58: 45943 | D58: Spend Money | E58: Cafe Diario Encomenderos Spa | G58: 0 | H58: 3300 | I58: =I57+G58-H58 -> -2103256
A59: 2114-13 | B59: CC Caitlin Wheat | C59: 45944 | D59: Bank Transfer | E59: Bank Transfer from Citibank - CLP to CC Caitlin Wheat | F59: CW´s credit card payment | G59: 943249 | H59: 0 | I59: =I58+G59-H59 -> -1160007
A60: 2114-13 | B60: CC Caitlin Wheat | C60: 45946 | D60: Payable Payment | E60: Payment: PCS | F60: 52283377 | G60: 0 | H60: 228969 | I60: =I59+G60-H60 -> -1388976
A61: 2114-13 | B61: CC Caitlin Wheat | C61: 45950 | D61: Payable Payment | E61: Payment: Cafe Diario Encomenderos Spa | F61: 5363 | G61: 0 | H61: 48500 | I61: =I60+G61-H61 -> -1437476
A62: 2114-13 | B62: CC Caitlin Wheat | C62: 45950 | D62: Payable Payment | E62: Payment: Justo Spa | F62: 485677 | G62: 0 | H62: 491 | I62: =I61+G62-H62 -> -1437967
A63: 2114-13 | B63: CC Caitlin Wheat | C63: 45950 | D63: Spend Money | E63: Cafe Diario Encomenderos Spa | G63: 0 | H63: 5234 | I63: =I62+G63-H63 -> -1443201
A64: 2114-13 | B64: CC Caitlin Wheat | C64: 45952 | D64: Payable Payment | E64: Payment: Cafe Diario Encomenderos Spa | F64: 5371 | G64: 0 | H64: 65300 | I64: =I63+G64-H64 -> -1508501
A65: 2114-13 | B65: CC Caitlin Wheat | C65: 45952 | D65: Spend Money | E65: Cafe Diario Encomenderos Spa | G65: 0 | H65: 6074 | I65: =I64+G65-H65 -> -1514575
A66: 2114-13 | B66: CC Caitlin Wheat | C66: 45958 | D66: Spend Money | E66: CC Expense | F66: Halloween - candies | G66: 0 | H66: 25060 | I66: =I65+G66-H66 -> -1539635
A67: 2114-13 | B67: CC Caitlin Wheat | C67: 45958 | D67: Spend Money | E67: CC Expense | F67: Mall Chino - Halloween decorations | G67: 0 | H67: 18540 | I67: =I66+G67-H67 -> -1558175
A68: 2114-13 | B68: CC Caitlin Wheat | C68: 45958 | D68: Spend Money | E68: Banco De Chile | G68: 0 | H68: 3958 | I68: =I67+G68-H68 -> -1562133
A69: 2114-13 | B69: CC Caitlin Wheat | C69: 45959 | D69: Spend Money | E69: CC Expense | F69: Office lunch | G69: 0 | H69: 115348 | I69: =I68+G69-H69 -> -1677481
A70: 2114-13 | B70: CC Caitlin Wheat | C70: 45962 | D70: Spend Money | E70: Cafe Diario Encomenderos Spa | G70: 0 | H70: 4809 | I70: =I69+G70-H70 -> -1682290
A71: 2114-13 | B71: CC Caitlin Wheat | C71: 45962 | D71: Spend Money | E71: Cafe Diario Encomenderos Spa | G71: 0 | H71: 4809 | I71: =I70+G71-H71 -> -1687099
A72: 2114-13 | B72: CC Caitlin Wheat | C72: 45964 | D72: Spend Money | E72: CC Expense | F72: Coca cola - drinks for the office | G72: 0 | H72: 115790 | I72: =I71+G72-H72 -> -1802889
A73: 2114-13 | B73: CC Caitlin Wheat | C73: 45964 | D73: Spend Money | E73: CC Expense | F73: Dulceria Praline - Cake for Cristians birthday | G73: 0 | H73: 30350 | I73: =I72+G73-H73 -> -1833239
A74: 2114-13 | B74: CC Caitlin Wheat | C74: 45964 | D74: Spend Money | E74: BECKER PADRUNO GRATTINI Y COMPANIA LTDA | F74: Confiteria Mundial - snacks for the office | G74: 0 | H74: 132650 | I74: =I73+G74-H74 -> -1965889
A75: 2114-13 | B75: CC Caitlin Wheat | C75: 45965 | D75: Payable Payment | E75: Payment: Cafe Diario Encomenderos Spa | F75: 5444 | G75: 0 | H75: 64500 | I75: =I74+G75-H75 -> -2030389
A76: 2114-13 | B76: CC Caitlin Wheat | C76: 45965 | D76: Payable Payment | E76: Payment: Justo Spa | F76: 488235 | G76: 0 | H76: 491 | I76: =I75+G76-H76 -> -2030880
A77: 2114-13 | B77: CC Caitlin Wheat | C77: 45966 | D77: Spend Money | E77: CC Expense | F77: Unimarc - office supplies | G77: 0 | H77: 20310 | I77: =I76+G77-H77 -> -2051190
A78: 2114-13 | B78: CC Caitlin Wheat | C78: 45966 | D78: Spend Money | E78: Distribucion y Alimentos FF SPA | F78: F1387 / Melbourne Cafe - Coffee for the office | G78: 0 | H78: 135600 | I78: =I77+G78-H78 -> -2186790
A79: 2114-13 | B79: CC Caitlin Wheat | C79: 45967 | D79: Spend Money | E79: Cafe Diario Encomenderos Spa | F79: F5504 / Catering - Glencore in the office 11/11 | G79: 0 | H79: 75300 | I79: =I78+G79-H79 -> -2262090
A80: 2114-13 | B80: CC Caitlin Wheat | C80: 45967 | D80: Spend Money | E80: Cafe Diario Encomenderos Spa | F80: F5533 / Catering - Glencore in the office 10/11 | G80: 0 | H80: 70000 | I80: =I79+G80-H80 -> -2332090
A81: 2114-13 | B81: CC Caitlin Wheat | C81: 45971 | D81: Payable Payment | E81: Payment: Cafe Diario Encomenderos Spa | F81: 5490 | G81: 0 | H81: 64500 | I81: =I80+G81-H81 -> -2396590
A82: 2114-13 | B82: CC Caitlin Wheat | C82: 45971 | D82: Payable Payment | E82: Payment: Justo Spa | F82: 489494 | G82: 0 | H82: 491 | I82: =I81+G82-H82 -> -2397081
A83: 2114-13 | B83: CC Caitlin Wheat | C83: 45974 | D83: Bank Transfer | E83: Bank Transfer from Citibank - CLP to CC Caitlin Wheat | F83: Credit card payment CW | G83: 1550273 | H83: 0 | I83: =I82+G83-H83 -> -846808
... A87: 2114-13 | B87: CC Caitlin Wheat | C87: 45980 | D87: Spend Money | E87: Cafe Diario Encomenderos Spa | F87: F5519 / Catering - BHP & Glencore in the office 20/11 | G87: 0 | H87: 56000 | I87: =I86+G87-H87 -> -1260782
A88: 2114-13 | B88: CC Caitlin Wheat | C88: 45987 | D88: Spend Money | E88: Banco De Chile | G88: 0 | H88: 3964 | I88: =I87+G88-H88 -> -1264746
A89: 2114-13 | B89: CC Caitlin Wheat | C89: 45987 | D89: Spend Money | E89: Worldquery Spa | F89: F65434 / Booz - Pisco - Festa fin do ano | G89: 0 | H89: 29450 | I89: =I88+G89-H89 -> -1294196
A90: 2114-13 | B90: CC Caitlin Wheat | C90: 45989 | D90: Spend Money | E90: CC Expense | F90: Drinks and beers order | G90: 0 | H90: 164820 | I90: =I89+G90-H90 -> -1459016
A91: 2114-13 | B91: CC Caitlin Wheat | C91: 45993 | D91: Spend Money | E91: CC Expense | F91: Icecream for team in Belo Hortizonte (BRL135) | G91: 0 | H91: 23178.07 | I91: =I90+G91-H91 -> -1482194.1
A92: 2114-13 | B92: CC Caitlin Wheat | C92: 45994 | D92: Spend Money | E92: Banco De Chile | G92: 0 | H92: 592 | I92: =I91+G92-H92 -> -1482786.1
A93: 2114-13 | B93: CC Caitlin Wheat | C93: 45997 | D93: Spend Money | E93: CC Expense | F93: Uber to End of Year Party - Belo Horizonte (BRL53.97) | G93: 0 | H93: 9303.81 | I93: =I92+G93-H93 -> -1492089.9
A94: 2114-13 | B94: CC Caitlin Wheat | C94: 45997 | D94: Spend Money | E94: CC Expense | F94: Uber from End of Year Party - Belo Horizonte (BRL65.99) | G94: 0 | H94: 11367.3 | I94: =I93+G94-H94 -> -1503457.2
A95: 2114-13 | B95: CC Caitlin Wheat | C95: 46000 | D95: Spend Money | E95: Banco De Chile | G95: 0 | H95: 287 | I95: =I94+G95-H95 -> -1503744.2
A96: 2114-13 | B96: CC Caitlin Wheat | C96: 46000 | D96: Spend Money | E96: Banco De Chile | G96: 0 | H96: 241 | I96: =I95+G96-H96 -> -1503985.2
A97: 2114-13 | B97: CC Caitlin Wheat | C97: 46001 | D97: Spend Money | E97: CC Expense | F97: Amigo secreto gift for Carolina Toro | G97: 0 | H97: 23000 | I97: =I96+G97-H97 -> -1526985.2
A98: 2114-13 | B98: CC Caitlin Wheat | C98: 46001 | D98: Payable Payment | E98: Payment: Telefonica Chile S.A (Movistar) | F98: 53974091 | G98: 0 | H98: 304284 | I98: =I97+G98-H98 -> -1831269.2
A99: 2114-13 | B99: CC Caitlin Wheat | C99: 46001 | D99: Payable Payment | E99: Payment: Telefonica Chile S.A (Movistar) | F99: F/50708669 | G99: 0 | H99: 24003 | I99: =I98+G99-H99 -> -1855272.2
A100: 2114-13 | B100: CC Caitlin Wheat | C100: 46002 | D100: Spend Money | E100: CC Expense | F100: Flowers for Sebastian Carvallo - funeral grandmother | G100: 0 | H100: 64988 | I100: =I99+G100-H100 -> -1920260.2
A101: 2114-13 | B101: CC Caitlin Wheat | C101: 46006 | D101: Bank Transfer | E101: Bank Transfer from Citibank - CLP to CC Caitlin Wheat | F101: CWs credit card payment | G101: 1296486 | I101: =I100+G101-H101 -> -623774.18
A102: 2114-13 | B102: CC Caitlin Wheat | C102: 46007 | D102: Spend Money | E102: CC Expense | F102: Holiday Inn - Accommodation Cesar Machado 15 December | G102: 0 | H102: 263894 | I102: =I101+G102-H102 -> -887668.18
A103: 2114-13 | B103: CC Caitlin Wheat | C103: 46008 | D103: Spend Money | E103: CC Expense | F103: 52643103 / Mobile phone for Carolina Toro | G103: 0 | H103: 209979 | I103: =I102+G103-H103 -> -1097647.2
...

Sheet 14
A1: Comprobante | B1: Fec. Doc. | C1: Voucher | E1: Titular | F1: T.Doc/Nro | G1: Debe | H1: Haber | I1: Acumulado
A2: adig/1284 | B2: 45805 | C2: 2940 | D2: Glosa : TDC CLP/USD CESAR MACHADO | E2: CESAR FELIPE MACHADO RIBEIRO LOPES | H2: 51519 | I2: -549958
A3: adig/1257 | B3: 45834 | C3: 2913 | D3: Glosa : TDC CLP/USD CESAR MACHADO | E3: CESAR FELIPE MACHADO RIBEIRO LOPES | H3: 1962244 | I3: -1605156
A4: adig/1284 | B4: 45805 | C4: 2940 | D4: Glosa : TDC CLP/USD CESAR MACHADO | E4: CESAR FELIPE MACHADO RIBEIRO LOPES | G4: 1989.92 | H4: 1989.92 | I4: -4290.47
A5: adig/1257 | B5: 45834 | C5: 2913 | D5: Glosa : TDC CLP/USD CESAR MACHADO | E5: CESAR FELIPE MACHADO RIBEIRO LOPES | G5: 751.8 | H5: 751.8 | I5: -5042.27 | J5: =H5*950 -> 714210
F9: 2114-14 - CC Cesar Machado | G9: 2831745
B27: Fec. Doc. | C27: Voucher | E27: Titular | G27: Debe | H27: Haber | I27: Acumulado
B28: 45805 | C28: 2940 | D28: Glosa : TDC CLP/USD CESAR MACHADO | E28: CESAR FELIPE MACHADO RIBEIRO LOPES | H28: 51519 | I28: -628870
B29: 45834 | C29: 2913 | D29: Glosa : TDC CLP/USD CESAR MACHADO | E29: CESAR FELIPE MACHADO RIBEIRO LOPES | H29: 1962244 | I29: -1528430
B30: 45867 | C30: 3576 | D30: Glosa : TDC CLP/USD CESAR MACHADO | E30: CESAR FELIPE MACHADO RIBEIRO LOPES | G30: 2013763 | I30: -2035435
B31: 45867 | C31: 3576 | D31: Glosa : TDC CLP/USD CESAR MACHADO | E31: CESAR FELIPE MACHADO RIBEIRO LOPES | H31: 2831745 | I31: -4867180
B34: Fec. Doc. | C34: Voucher | E34: Titular | F34: T.Doc/Nro | G34: Debe | H34: Haber | I34: Acumulado
B35: 45805 | C35: 2940 | D35: Glosa : TDC CLP/USD CESAR MACHADO | E35: CESAR FELIPE MACHADO RIBEIRO LOPES | H35: 51519 | I35: =-H35 -> -51519
B36: 45834 | C36: 2913 | D36: Glosa : TDC CLP/USD CESAR MACHADO | E36: CESAR FELIPE MACHADO RIBEIRO LOPES | H36: 1962244 | I36: =I35+G36-H36 -> -2013763
B37: 45867 | C37: 3576 | D37: Glosa : TDC CLP/USD CESAR MACHADO | E37: CESAR FELIPE MACHADO RIBEIRO LOPES | G37: 2013763 | I37: =I36+G37-H37 -> 0
B38: 45867 | C38: 3576 | D38: Glosa : TDC CLP/USD CESAR MACHADO | E38: CESAR FELIPE MACHADO RIBEIRO LOPES | H38: 2831745 | I38: =I37+G38-H38 -> -2831745
B39: 45891 | C39: 3264 | D39: Glosa : CM´s credit card payment | E39: CESAR FELIPE MACHADO RIBEIRO LOPES | G39: 2831745 | I39: =I38+G39-H39 -> 0
B40: 45896 | C40: 3496 | D40: Glosa : TDC CLP/USD CESAR MACHADO | E40: CESAR FELIPE MACHADO RIBEIRO LOPES | H40: 36966 | I40: =I39+G40-H40 -> -36966
B41: 45911 | C41: 3536 | D41: Glosa : CM´s credit card payment | E41: CESAR FELIPE MACHADO RIBEIRO LOPES | G41: 36966 | I41: =I40+G41-H41 -> 0
B42: 45926 | C42: 3582 | D42: Glosa : TDC CLP/USD CESAR MACHADO | E42: CESAR FELIPE MACHADO RIBEIRO LOPES | H42: 491676 | I42: =I41+G42-H42 -> -491676
A43: adig/1686 | B43: 45944 | C43: 3750 | D43: CESAR FELIPE MACHADO RIBEIRO LOPES | G43: 491676 | I43: =I42+G43-H43 -> 0
A44: adig/1697 | B44: 45958 | C44: 3800 | D44: CESAR FELIPE MACHADO RIBEIRO LOPES | H44: 115845 | I44: =I43+G44-H44 -> -115845
A45: adig/1742 | B45: 45974 | C45: 3909 | D45: =+A45 -> adig/1742 | E45: CESAR FELIPE MACHADO RIBEIRO LOPES | G45: 115845 | I45: =I44+G45-H45 -> 0
A46: adig/1769 | B46: 45987 | C46: 3957 | D46: =+A46 -> adig/1769 | E46: CESAR FELIPE MACHADO RIBEIRO LOPES | H46: 1303416 | I46: =I45+G46-H46 -> -1303416
A47: adig/1811 | B47: 46006 | C47: 4060 | D47: Glosa : Credit Card payment CM | E47: CESAR FELIPE MACHADO RIBEIRO LOPES | G47: 1303416 | I47: =I46+G47-H47 -> 0
A48: adig/1834 | B48: 46017 | C48: 4128 | D48: Glosa : TDC CESAR MACHADO | E48: CESAR FELIPE MACHADO RIBEIRO LOPES | H48: 719990 | I48: =I47+G48-H48 -> -719990
B50: 45896 | C50: 3496 | D50: Glosa : TDC CLP/USD CESAR MACHADO | E50: CESAR FELIPE MACHADO RIBEIRO LOPES | H50: 479.8 | I50: =-H50 -> -479.8
B51: 45926 | C51: 3582 | D51: Glosa : TDC CLP/USD CESAR MACHADO | E51: CESAR FELIPE MACHADO RIBEIRO LOPES | G51: 479.8 | I51: =I50+G51-H51 -> 0
B52: 45926 | C52: 3582 | D52: Glosa : TDC CLP/USD CESAR MACHADO | E52: CESAR FELIPE MACHADO RIBEIRO LOPES | H52: 79.35 | I52: =I51+G52-H52 -> -79.35
B53: 45958 | C53: 3800 | E53: CESAR FELIPE MACHADO RIBEIRO LOPES | G53: 79.35 | I53: =I52+G53-H53 -> 0
B54: 45958 | C54: 3800 | E54: CESAR FELIPE MACHADO RIBEIRO LOPES | H54: 1302.92 | I54: =I53+G54-H54 -> -1302.92
A55: adig/1769 | B55: 45987 | C55: 3957 | D55: adig/1769 | E55: CESAR FELIPE MACHADO RIBEIRO LOPES | G55: 1302.92 | I55: =I54+G55-H55 -> 0
A56: adig/1769 | B56: 45987 | C56: 3957 | D56: =+A56 -> adig/1769 | E56: CESAR FELIPE MACHADO RIBEIRO LOPES | H56: 743.45 | I56: =I55+G56-H56 -> -743.45 | K56: =+I46+J53+J56 -> -1303416
A57: adig/1834 | B57: 46017 | C57: 4128 | D57: Glosa : TDC CESAR MACHADO | E57: CESAR FELIPE MACHADO RIBEIRO LOPES | G57: 743.45 | I57: =I56+G57-H57 -> 0
A58: adig/1834 | B58: 46017 | C58: 4128 | D58: Glosa : TDC CESAR MACHADO | E58: CESAR FELIPE MACHADO RIBEIRO LOPES | H58: 88.56 | I58: =I57+G58-H58 -> -88.56 | J58: =-H58*907.13 -> -80335.433 | K58: =+J58+I48 -> -800325.43

Sheet 14_X
A1: Account Code | B1: Account | C1: Date | D1: Source | E1: Description | F1: Reference | G1: Debit | H1: Credit
A2: 2114-14 | B2: CC Cesar Machado | C2: 45809 | D2: Spend Money | E2: Banco De Chile | G2: 0 | H2: 51519 | I2: =+G2-H2 -> -51519
A3: 2114-14 | B3: CC Cesar Machado | C3: 45809 | D3: Spend Money | E3: Banco De Chile | G3: 0 | H3: 3173 | I3: =I2+G3-H3 -> -54692
A4: 2114-14 | B4: CC Cesar Machado | C4: 45809 | D4: Spend Money | E4: Banco De Chile | G4: 0 | H4: 14678 | I4: =I3+G4-H4 -> -69370
A5: 2114-14 | B5: CC Cesar Machado | C5: 45809 | D5: Spend Money | E5: Provision Expenses CC | G5: 0 | H5: 578390.25 | I5: =I4+G5-H5 -> -647760.25
A6: 2114-14 | B6: CC Cesar Machado | C6: 45809 | D6: Spend Money | E6: Provision Expenses CC | G6: 0 | H6: 1744614.3 | I6: =I5+G6-H6 -> -2392374.5
A7: 2114-14 | B7: CC Cesar Machado | C7: 45809 | D7: Spend Money | E7: Provision Expenses CC | G7: 0 | H7: 125099.08 | I7: =I6+G7-H7 -> -2517473.6
A8: 2114-14 | B8: CC Cesar Machado | C8: 45809 | D8: Spend Money | E8: Provision Expenses CC | G8: 0 | H8: 120677.01 | I8: =I7+G8-H8 -> -2638150.6
A9: 2114-14 | B9: CC Cesar Machado | C9: 45834 | D9: Spend Money | E9: Banco De Chile | G9: 0 | H9: 1281 | I9: =I8+G9-H9 -> -2639431.6
A10: 2114-14 | B10: CC Cesar Machado | C10: 45834 | D10: Spend Money | E10: Banco De Chile | G10: 0 | H10: 3926 | I10: =I9+G10-H10 -> -2643357.6
A11: 2114-14 | B11: CC Cesar Machado | C11: 45834 | D11: Spend Money | E11: Banco De Chile | G11: 0 | H11: 48640 | I11: =I10+G11-H11 -> -2691997.6
A12: 2114-14 | B12: CC Cesar Machado | C12: 45834 | D12: Spend Money | E12: Banco De Chile | G12: 0 | H12: 122 | I12: =I11+G12-H12 -> -2692119.6
A13: 2114-14 | B13: CC Cesar Machado | C13: 45838 | D13: Spend Money | E13: Banco De Chile | G13: 0 | H13: 25132.33 | I13: =I12+G13-H13 -> -2717252
A14: 2114-14 | B14: CC Cesar Machado | C14: 45848 | D14: Spend Money | E14: Banco De Chile | G14: 0 | H14: 24241.03 | I14: =I13+G14-H14 -> -2741493
... A19: 2114-14 | B19: CC Cesar Machado | C19: 45867 | D19: Spend Money | E19: banco | G19: 0 | H19: 2849 | I19: =I18+G19-H19 -> -2831745
A20: 2114-14 | B20: CC Cesar Machado | C20: 45891 | D20: Bank Transfer | E20: Bank Transfer from Citibank - CLP to CC Cesar Machado | F20: CM´s credit card payment | G20: 2831745 | H20: 0 | I20: =I19+G20-H20 -> 4.6566129e-10
A21: 2114-14 | B21: CC Cesar Machado | C21: 45894 | D21: Spend Money | E21: Provision Expenses CC | G21: 0 | H21: 357939 | I21: =I20+G21-H21 -> -357939
A22: 2114-14 | B22: CC Cesar Machado | C22: 45895 | D22: Spend Money | E22: Provision Expenses CC | G22: 0 | H22: 106258 | I22: =I21+G22-H22 -> -464197
A23: 2114-14 | B23: CC Cesar Machado | C23: 45896 | D23: Spend Money | E23: Banco De Chile | G23: 0 | H23: 3934 | I23: =I22+G23-H23 -> -468131
A24: 2114-14 | B24: CC Cesar Machado | C24: 45896 | D24: Spend Money | E24: Banco De Chile | G24: 0 | H24: 9111 | I24: =I23+G24-H24 -> -477242
A25: 2114-14 | B25: CC Cesar Machado | C25: 45896 | D25: Spend Money | E25: Banco De Chile | G25: 0 | H25: 2709 | I25: =I24+G25-H25 -> -479951
A26: 2114-14 | B26: CC Cesar Machado | C26: 45896 | D26: Spend Money | E26: Banco De Chile | G26: 0 | H26: 1868 | I26: =I25+G26-H26 -> -481819
A27: 2114-14 | B27: CC Cesar Machado | C27: 45896 | D27: Spend Money | E27: Banco De Chile | G27: 0 | H27: 17758 | I27: =I26+G27-H27 -> -499577
A28: 2114-14 | B28: CC Cesar Machado | C28: 45896 | D28: Spend Money | E28: Banco De Chile | G28: 0 | H28: 1586 | I28: =I27+G28-H28 -> -501163
A29: 2114-14 | B29: CC Cesar Machado | C29: 45901 | D29: Spend Money | E29: Banco De Chile | G29: 0 | H29: 1931 | I29: =I28+G29-H29 -> -503094
A30: 2114-14 | B30: CC Cesar Machado | C30: 45901 | D30: Spend Money | E30: CC Expense | F30: Hotel Expenses | G30: 0 | H30: 8020 | I30: =I29+G30-H30 -> -511114
A31: 2114-14 | B31: CC Cesar Machado | C31: 45901 | D31: Spend Money | E31: CC Expense | F31: Taxi in Belo | G31: 0 | H31: 28308 | I31: =I30+G31-H31 -> -539422
A32: 2114-14 | B32: CC Cesar Machado | C32: 45901 | D32: Spend Money | E32: CC Expense | F32: Taxi in Lima | G32: 0 | H32: 19340 | I32: =I31+G32-H32 -> -558762
A33: 2114-14 | B33: CC Cesar Machado | C33: 45901 | D33: Receive Money | E33: Provision Expenses CC | G33: 28308 | H33: 0 | I33: =I32+G33-H33 -> -530454
A34: 2114-14 | B34: CC Cesar Machado | C34: 45901 | D34: Receive Money | E34: Provision Expenses CC | G34: 8020 | H34: 0 | I34: =I33+G34-H34 -> -522434
A35: 2114-14 | B35: CC Cesar Machado | C35: 45901 | D35: Receive Money | E35: Provision Expenses CC | G35: 19340 | H35: 0 | I35: =I34+G35-H35 -> -503094
A36: 2114-14 | B36: CC Cesar Machado | C36: 45901 | D36: Spend Money | E36: CC Expense | F36: Taxi in Medellin | G36: 0 | H36: 38641 | I36: =I35+G36-H36 -> -541735
A37: 2114-14 | B37: CC Cesar Machado | C37: 45901 | D37: Spend Money | E37: CC Expense | F37: Dinner with the team | G37: 0 | H37: 55427 | I37: =I36+G37-H37 -> -597162
A38: 2114-14 | B38: CC Cesar Machado | C38: 45901 | D38: Spend Money | E38: CC Expense | F38: Snack in the airport | G38: 0 | H38: 28057 | I38: =I37+G38-H38 -> -625219
A39: 2114-14 | B39: CC Cesar Machado | C39: 45901 | D39: Spend Money | E39: CC Expense | F39: Hotel expenses | G39: 0 | H39: 7101 | I39: =I38+G39-H39 -> -632320
A40: 2114-14 | B40: CC Cesar Machado | C40: 45901 | D40: Spend Money | E40: CC Expense | F40: Dinner with the team | G40: 0 | H40: 97154 | I40: =I39+G40-H40 -> -729474
A41: 2114-14 | B41: CC Cesar Machado | C41: 45901 | D41: Spend Money | E41: CC Expense | F41: Lunch with the team | G41: 0 | H41: 64811 | I41: =I40+G41-H41 -> -794285
A42: 2114-14 | B42: CC Cesar Machado | C42: 45901 | D42: Spend Money | E42: CC Expense | F42: Dinner with the team | G42: 0 | H42: 68507 | I42: =I41+G42-H42 -> -862792
A43: 2114-14 | B43: CC Cesar Machado | C43: 45901 | D43: Spend Money | E43: CC Expense | F43: Taxi in Medellin | G43: 0 | H43: 38264 | I43: =I42+G43-H43 -> -901056
A44: 2114-14 | B44: CC Cesar Machado | C44: 45901 | D44: Receive Money | E44: Provision Expenses CC | G44: 38264 | H44: 0 | I44: =I43+G44-H44 -> -862792
A45: 2114-14 | B45: CC Cesar Machado | C45: 45901 | D45: Receive Money | E45: Provision Expenses CC | G45: 38641 | H45: 0 | I45: =I44+G45-H45 -> -824151
A46: 2114-14 | B46: CC Cesar Machado | C46: 45901 | D46: Receive Money | E46: Provision Expenses CC | G46: 55427 | H46: 0 | I46: =I45+G46-H46 -> -768724
A47: 2114-14 | B47: CC Cesar Machado | C47: 45901 | D47: Receive Money | E47: Provision Expenses CC | G47: 28057 | H47: 0 | I47: =I46+G47-H47 -> -740667
A48: 2114-14 | B48: CC Cesar Machado | C48: 45901 | D48: Receive Money | E48: Provision Expenses CC | G48: 22852 | H48: 0 | I48: =I47+G48-H48 -> -717815
A49: 2114-14 | B49: CC Cesar Machado | C49: 45901 | D49: Receive Money | E49: Provision Expenses CC | G49: 7101 | H49: 0 | I49: =I48+G49-H49 -> -710714
A50: 2114-14 | B50: CC Cesar Machado | C50: 45901 | D50: Receive Money | E50: Provision Expenses CC | G50: 97154 | H50: 0 | I50: =I49+G50-H50 -> -613560
A51: 2114-14 | B51: CC Cesar Machado | C51: 45901 | D51: Receive Money | E51: Provision Expenses CC | G51: 64811 | H51: 0 | I51: =I50+G51-H51 -> -548749
A52: 2114-14 | B52: CC Cesar Machado | C52: 45901 | D52: Receive Money | E52: Provision Expenses CC | G52: 68507 | H52: 0 | I52: =I51+G52-H52 -> -480242
A53: 2114-14 | B53: CC Cesar Machado | C53: 45901 | D53: Spend Money | E53: CC Expense | F53: Dinner with the Team in Lima | G53: 0 | H53: 106258 | I53: =I52+G53-H53 -> -586500
A54: 2114-14 | B54: CC Cesar Machado | C54: 45901 | D54: Spend Money | E54: Provision Expenses CC | G54: 357939 | H54: 0 | I54: =I53+G54-H54 -> -228561
A55: 2114-14 | B55: CC Cesar Machado | C55: 45901 | D55: Spend Money | E55: Provision Expenses CC | G55: 106258 | H55: 0 | I55: =I54+G55-H55 -> -122303
A56: 2114-14 | B56: CC Cesar Machado | C56: 45901 | D56: Spend Money | E56: CC Expense | G56: 0 | H56: 76274.4 | I56: =I55+G56-H56 -> -198577.4
A57: 2114-14 | B57: CC Cesar Machado | C57: 45901 | D57: Spend Money | E57: CC Expense | F57: Lunch with the team | G57: 0 | H57: 22852 | I57: =I56+G57-H57 -> -221429.4
A58: 2114-14 | B58: CC Cesar Machado | C58: 45901 | D58: Spend Money | E58: CC Expense | F58: Happy Hour with the Team at the Hotel | G58: 0 | H58: 357939 | I58: =I57+G58-H58 -> -579368.4
A59: 2114-14 | B59: CC Cesar Machado | C59: 45911 | D59: Bank Transfer | E59: Bank Transfer from Citibank - CLP to CC Cesar Machado | F59: Cesars credit card paymenbt | G59: 36966 | H59: 0 | I59: =I58+G59-H59 -> -542402.4
A60: 2114-14 | B60: CC Cesar Machado | C60: 45911 | D60: Spend Money | E60: Banco De Chile | G60: 0 | H60: 311 | I60: =I59+G60-H60 -> -542713.4
A61: 2114-14 | B61: CC Cesar Machado | C61: 45911 | D61: Spend Money | E61: Banco De Chile | G61: 0 | H61: 7446 | I61: =I60+G61-H61 -> -550159.4
A62: 2114-14 | B62: CC Cesar Machado | C62: 45926 | D62: Spend Money | E62: Banco De Chile | G62: 0 | H62: 3949 | I62: =I61+G62-H62 -> -554108.4
A63: 2114-14 | B63: CC Cesar Machado | C63: 45926 | D63: Spend Money | E63: Banco De Chile | G63: 0 | H63: 13842 | I63: =I62+G63-H63 -> -567950.4
A64: 2114-14 | B64: CC Cesar Machado | C64: 45931 | D64: Spend Money | E64: Provision Expenses CC | G64: 0 | H64: 280424.99 | I64: =I63+G64-H64 -> -848375.39
A65: 2114-14 | B65: CC Cesar Machado | C65: 45933 | D65: Spend Money | E65: Banco De Chile | G65: 0 | H65: 7209 | I65: =I64+G65-H65 -> -855584.39
A66: 2114-14 | B66: CC Cesar Machado | C66: 45933 | D66: Spend Money | E66: Provision Expenses CC | G66: 0 | H66: 366194.32 | I66: =I65+G66-H66 -> -1221778.7
A67: 2114-14 | B67: CC Cesar Machado | C67: 45933 | D67: Spend Money | E67: Provision Expenses CC | G67: 0 | H67: 575767.2 | I67: =I66+G67-H67 -> -1797545.9
A68: 2114-14 | B68: CC Cesar Machado | C68: 45936 | D68: Spend Money | E68: Banco De Chile | G68: 0 | H68: 9418 | I68: =I67+G68-H68 -> -1806963.9
A69: 2114-14 | B69: CC Cesar Machado | C69: 45936 | D69: Spend Money | E69: Banco De Chile | G69: 0 | H69: 14803 | I69: =I68+G69-H69 -> -1821766.9
A70: 2114-14 | B70: CC Cesar Machado | C70: 45944 | D70: Bank Transfer | E70: Bank Transfer from Citibank - CLP to CC Cesar Machado | F70: CM´s credit card payment | G70: 491676 | H70: 0 | I70: =I69+G70-H70 -> -1330090.9
A71: 2114-14 | B71: CC Cesar Machado | C71: 45944 | D71: Spend Money | E71: Banco De Chile | G71: 0 | H71: 2123.6 | I71: =I70+G71-H71 -> -1332214.5
A72: 2114-14 | B72: CC Cesar Machado | C72: 45958 | D72: Spend Money | E72: Banco De Chile | G72: 0 | H72: 52 | I72: =I71+G72-H72 -> -1332266.5
A73: 2114-14 | B73: CC Cesar Machado | C73: 45958 | D73: Spend Money | E73: Banco De Chile | G73: 0 | H73: 3958 | I73: =I72+G73-H73 -> -1336224.5
A74: 2114-14 | B74: CC Cesar Machado | C74: 45958 | D74: Spend Money | E74: Banco De Chile | G74: 0 | H74: 2007 | I74: =I73+G74-H74 -> -1338231.5
A75: 2114-14 | B75: CC Cesar Machado | C75: 45974 | D75: Bank Transfer | E75: Bank Transfer from Citibank - CLP to CC Cesar Machado | F75: Credit Card payment CM | G75: 115845 | H75: 0 | I75: =I74+G75-H75 -> -1222386.5
A76: 2114-14 | B76: CC Cesar Machado | C76: 45986 | D76: Spend Money | E76: Provision Expenses CC | G76: 0 | H76: 690769.13 | I76: =I75+G76-H76 -> -1913155.6
A77: 2114-14 | B77: CC Cesar Machado | C77: 45986 | D77: Receive Money | E77: Banco De Chile | G77: 23205.49 | H77: 0 | I77: =I76+G77-H77 -> -1889950.1
A78: 2114-14 | B78: CC Cesar Machado | C78: 45987 | D78: Spend Money | E78: Banco De Chile | G78: 0 | H78: 17828 | I78: =I77+G78-H78 -> -1907778.1
A79: 2114-14 | B79: CC Cesar Machado | C79: 45987 | D79: Spend Money | E79: Banco De Chile | G79: 0 | H79: 822 | I79: =I78+G79-H79 -> -1908600.1
A80: 2114-14 | B80: CC Cesar Machado | C80: 45987 | D80: Spend Money | E80: Banco De Chile | G80: 0 | H80: 3964 | I80: =I79+G80-H80 -> -1912564.1
A81: 2114-14 | B81: CC Cesar Machado | C81: 45987 | D81: Spend Money | E81: Banco De Chile | G81: 0 | H81: 35210 | I81: =I80+G81-H81 -> -1947774.1
A82: 2114-14 | B82: CC Cesar Machado | C82: 45992 | D82: Spend Money | E82: Banco De Chile | G82: 0 | H82: 2046 | I82: =I81+G82-H82 -> -1949820.1
A83: 2114-14 | B83: CC Cesar Machado | C83: 45992 | D83: Spend Money | E83: Provision Expenses CC | G83: 0 | H83: 80150.34 | I83: =I82+G83-H83 -> -2029970.5
A84: 2114-14 | B84: CC Cesar Machado | C84: 45992 | D84: Spend Money | E84: CC Expense | F84: Dinner with the team | G84: 0 | H84: 367537 | I84: =I83+G84-H84 -> -2397507.5
A85: 2114-14 | B85: CC Cesar Machado | C85: 45992 | D85: Spend Money | E85: CC Expense | F85: Hotel in Medellin | G85: 0 | H85: 577538 | I85: =I84+G85-H85 -> -2975045.5
A86: 2114-14 | B86: CC Cesar Machado | C86: 45992 | D86: Spend Money | E86: CC Expense | F86: Drinks with the team | G86: 0 | H86: 129342 | I86: =I85+G86-H86 -> -3104387.5
A87: 2114-14 | B87: CC Cesar Machado | C87: 45992 | D87: Spend Money | E87: CC Expense | F87: Dinner with the team - Angatu Restaurant | G87: 0 | H87: 598009 | I87: =I86+G87-H87 -> -3702396.5
A88: 2114-14 | B88: CC Cesar Machado | C88: 45992 | D88: Spend Money | E88: CC Expense | F88: Snacks | G88: 0 | H88: 66737 | I88: =I87+G88-H88 -> -3769133.5
A89: 2114-14 | B89: CC Cesar Machado | C89: 45992 | D89: Spend Money | E89: CC Expense | F89: Coffee on the road | G89: 0 | H89: 2700 | I89: =I88+G89-H89 -> -3771833.5
A90: 2114-14 | B90: CC Cesar Machado | C90: 45992 | D90: Spend Money | E90: CC Expense | F90: Dinner with the team - Pacco Bacco Restaurant | G90: 0 | H90: 556069 | I90: =I89+G90-H90 -> -4327902.5
A91: 2114-14 | B91: CC Cesar Machado | C91: 45992 | D91: Spend Money | E91: CC Expense | F91: Dinner with the team - Tragaluz | G91: 0 | H91: 823229 | I91: =I90+G91-H91 -> -5151131.5
A92: 2114-14 | B92: CC Cesar Machado | C92: 45992 | D92: Spend Money | E92: CC Expense | F92: Happy Hour with the team | G92: 0 | H92: 281453 | I92: =I91+G92-H92 -> -5432584.5
A93: 2114-14 | B93: CC Cesar Machado | C93: 46004 | D93: Spend Money | E93: Banco De Chile | G93: 0 | H93: 50767.85 | I93: =I92+G93-H93 -> -5483352.3
A94: 2114-14 | B94: CC Cesar Machado | C94: 46006 | D94: Bank Transfer | E94: Bank Transfer from Citibank - CLP to CC Cesar Machado | F94: CMs credit card payment | G94: 1303416 | H94: 0 | I94: =I93+G94-H94 -> -4179936.3
A95: 2114-14 | B95: CC Cesar Machado | C95: 46017 | D95: Spend Money | E95: Banco De Chile | G95: 0 | H95: 459 | I95: =I94+G95-H95 -> -4180395.3
A96: 2114-14 | B96: CC Cesar Machado | C96: 46017 | D96: Spend Money | E96: Banco De Chile | G96: 0 | H96: 3971 | I96: =I95+G96-H96 -> -4184366.3
A97: 2114-14 | B97: CC Cesar Machado | C97: 46017 | D97: Spend Money | E97: Banco De Chile | G97: 0 | H97: 18388 | I97: =I96+G97-H97 -> -4202754.3
A98: 2114-14 | B98: CC Cesar Machado | C98: 46022 | D98: Spend Money | E98: Provision Expenses CC | F98: Rev 120,677.01 | G98: 129342 | H98: 0 | I98: =I97+G98-H98 -> -4073412.3
A99: 2114-14 | B99: CC Cesar Machado | C99: 46022 | D99: Spend Money | E99: Provision Expenses CC | F99: Rev 366,194.32 | G99: 367537 | H99: 0 | I99: =I98+G99-H99 -> -3705875.3
A100: 2114-14 | B100: CC Cesar Machado | C100: 46022 | D100: Spend Money | E100: Provision Expenses CC | F100: Rev 578,390.25 | G100: 577538 | H100: 0 | I100: =I99+G100-H100 -> -3128337.3
A101: 2114-14 | B101: CC Cesar Machado | C101: 46022 | D101: Spend Money | E101: Provision Expenses CC | G101: 2700 | H101: 0 | I101: =I100+G101-H101 -> -3125637.3
A102: 2114-14 | B102: CC Cesar Machado | C102: 46022 | D102: Spend Money | E102: Provision Expenses CC | G102: 66737 | H102: 0 | I102: =I101+G102-H102 -> -3058900.3
A103: 2114-14 | B103: CC Cesar Machado | C103: 46022 | D103: Spend Money | E103: Provision Expenses CC | G103: 598009 | H103: 0 | I103: =I102+G103-H103 -> -2460891.3
A104: 2114-14 | B104: CC Cesar Machado | C104: 46022 | D104: Spend Money | E104: Provision Expenses CC | G104: 556069 | H104: 0 | I104: =I103+G104-H104 -> -1904822.3
...

Sheet 15
A1: Comprobante | B1: Fec. Doc. | C1: Voucher | E1: Titular | F1: T.Doc/Nro | G1: Debe | H1: Haber | I1: Acumulado
A2: adig/1259 | B2: 45834 | C2: 2915 | D2: Glosa : TDC CLP/USD JORGE MORIS | E2: JORGE MORIS JORDÁN | H2: 39636 | I2: -1649114
C9: 2114-15 - CC Jorge Moris | E9: 44748
B11: Fec. Doc. | C11: Voucher | E11: Titular | G11: Debe | H11: Haber | I11: Acumulado
B12: 45813 | C12: 2812 | D12: Glosa : Payment: ER - Jorge Moris25.4 - Reimbursable Expense - Vacuna Influenza | 25.4 - Reimbursable Expense - Vacuna Influenza | E12: JORGE MORIS JORDÁN | G12: 19500 | I12: -802045
B13: 45834 | C13: 2817 | D13: Glosa : Payment: ER - Jorge Moris25.6 - Reimbursable Expense - Estacionamiento Mine... | E13: JORGE MORIS JORDÁN | G13: 9000 | I13: 1415242
B14: 45834 | C14: 2915 | D14: Glosa : TDC CLP/USD JORGE MORIS | E14: JORGE MORIS JORDÁN | H14: 39636 | I14: -1572388
B15: 45869 | C15: 3462 | D15: Glosa : Spend Money CC Expense - Estacionamiento Mine Planning 2114-15 | E15: JORGE MORIS JORDÁN | H15: 9000 | I15: -27232422
B16: 45869 | C16: 3462 | D16: Glosa : Spend Money CC Expense - Estacionamiento Mine Planning 2114-15 | E16: JORGE MORIS JORDÁN | H16: 19500 | I16: -27251922
B18: Fec. Doc. | C18: Voucher | E18: Titular | F18: T.Doc/Nro | G18: Debe | H18: Haber | I18: Acumulado
B19: 45813 | C19: 2812 | D19: Glosa : Payment: ER - Jorge Moris25.4 - Reimbursable Expense - Vacuna Influenza | 25.4 - Reimbursable Expense - Vacuna Influenza | E19: JORGE MORIS JORDÁN | G19: 19500 | I19: =+G19 -> 19500
B20: 45834 | C20: 2817 | D20: Glosa : Payment: ER - Jorge Moris25.6 - Reimbursable Expense - Estacionamiento Mine... | E20: JORGE MORIS JORDÁN | G20: 9000 | I20: =I19+G20-H20 -> 28500
B21: 45834 | C21: 2915 | D21: Glosa : TDC CLP/USD JORGE MORIS | E21: JORGE MORIS JORDÁN | H21: 39636 | I21: =I20+G21-H21 -> -11136
B22: 45869 | C22: 3462 | D22: Glosa : Spend Money CC Expense - Estacionamiento Mine Planning 2114-15 | E22: JORGE MORIS JORDÁN | H22: 9000 | I22: =I21+G22-H22 -> -20136
B23: 45869 | C23: 3462 | D23: Glosa : Spend Money CC Expense - Estacionamiento Mine Planning 2114-15 | E23: JORGE MORIS JORDÁN | H23: 19500 | I23: =I22+G23-H23 -> -39636
B24: 45869 | C24: 3574 | D24: Glosa : compensa prov | E24: JORGE MORIS JORDÁN | H24: 5112 | I24: =I23+G24-H24 -> -44748
B25: 45891 | C25: 3265 | D25: Glosa : JM´s credit card payment | E25: JORGE MORIS JORDÁN | G25: 44748 | I25: =I24+G25-H25 -> 0
B26: 45896 | C26: 3507 | D26: Glosa : TDC CLP/USD JORGE MORIS | E26: JORGE MORIS JORDÁN | H26: 4267 | I26: =I25+G26-H26 -> -4267
B27: 45911 | C27: 3532 | D27: Glosa : JM´s credit card payment | E27: JORGE MORIS JORDÁN | G27: 4267 | I27: =I26+G27-H27 -> 0
A28: adig/1813 | B28: 46017 | C28: 4062 | D28: Glosa : 25.12 - Reimbursable Expense - Gastos Frigobar Hot... | 25.12 - Reimbursable Expense - Gastos Frigobar Hot... | E28: JORGE MORIS JORDÁN | G28: 71962 | I28: =I27+G28-H28 -> 71962

Sheet 15_x
A1: Account Code | B1: Account | C1: Date | D1: Source | E1: Description | F1: Reference | G1: Debit | H1: Credit
A2: 2114-15 | B2: CC Jorge Moris | C2: 45820 | D2: Spend Money | E2: CC Expense | F2: Cafe equipo Deswik - Mine Planning | G2: 0 | H2: 17710 | I2: =+G2-H2 -> -17710
A3: 2114-15 | B3: CC Jorge Moris | C3: 45820 | D3: Spend Money | E3: CC Expense | F3: Estacionamiento Mine Planning | G3: 0 | H3: 9000 | I3: =I2+G3-H3 -> -26710
A4: 2114-15 | B4: CC Jorge Moris | C4: 45821 | D4: Spend Money | E4: CC Expense | G4: 0 | H4: 9000 | I4: =I3+G4-H4 -> -35710
A5: 2114-15 | B5: CC Jorge Moris | C5: 45834 | D5: Spend Money | E5: Banco De Chile | G5: 0 | H5: 3926 | I5: =I4+G5-H5 -> -39636
A6: 2114-15 | B6: CC Jorge Moris | C6: 45867 | D6: Spend Money | E6: Banco De Chile | G6: 0 | H6: 3919 | I6: =I5+G6-H6 -> -43555
A7: 2114-15 | B7: CC Jorge Moris | C7: 45867 | D7: Spend Money | E7: Banco De Chile | G7: 0 | H7: 26 | I7: =I6+G7-H7 -> -43581
A8: 2114-15 | B8: CC Jorge Moris | C8: 45867 | D8: Spend Money | E8: Banco De Chile | G8: 0 | H8: 1020 | I8: =I7+G8-H8 -> -44601
A9: 2114-15 | B9: CC Jorge Moris | C9: 45867 | D9: Spend Money | E9: Banco De Chile | G9: 0 | H9: 147 | I9: =I8+G9-H9 -> -44748
A10: 2114-15 | B10: CC Jorge Moris | C10: 45891 | D10: Bank Transfer | E10: Bank Transfer from Citibank - CLP to CC Jorge Moris | F10: JM´s credit card payment | G10: 44748 | H10: 0 | I10: =I9+G10-H10 -> 0
A11: 2114-15 | B11: CC Jorge Moris | C11: 45896 | D11: Spend Money | E11: Banco De Chile | G11: 0 | H11: 3934 | I11: =I10+G11-H11 -> -3934
A12: 2114-15 | B12: CC Jorge Moris | C12: 45896 | D12: Spend Money | E12: Banco De Chile | G12: 0 | H12: 29 | I12: =I11+G12-H12 -> -3963
A13: 2114-15 | B13: CC Jorge Moris | C13: 45896 | D13: Spend Money | E13: Banco De Chile | G13: 0 | H13: 232 | I13: =I12+G13-H13 -> -4195
A14: 2114-15 | B14: CC Jorge Moris | C14: 45896 | D14: Spend Money | E14: Banco De Chile | G14: 0 | H14: 72 | I14: =I13+G14-H14 -> -4267
A15: 2114-15 | B15: CC Jorge Moris | C15: 45911 | D15: Bank Transfer | E15: Bank Transfer from Citibank - CLP to CC Jorge Moris | F15: Jorge´s credit card payment | G15: 4267 | H15: 0 | I15: =I14+G15-H15 -> 0 | J15: OK Salso 0 en balance y mayor x
G16: =SUM(G2:G15) -> 49015 | H16: =SUM(H2:H15) -> 49015 | I16: =G16-H16 -> 0
J26: ='15'!G28 -> 71962 | K26: mov registrado en magnus | L26: diferencia balance xero y magnus

Sheet 54
A1: Comprobante | B1: Fec. Doc. | C1: Voucher | E1: Titular | F1: T.Doc/Nro | G1: Debe | H1: Haber | I1: Acumulado
A2: adig/1115 | B2: 45772 | C2: 2554 | D2: Glosa : TDC CLP Marcelo PENNA | E2: MARCELO PENNA SANTOS | H2: 494703 | I2: -3565146
A3: adig/1175 | B3: 45792 | C3: 2749 | D3: Glosa : Bank Transfer to CC Marcelo Penna. | E3: MARCELO PENNA SANTOS | G3: 1901018 | I3: 1356555
A4: adig/1254 | B4: 45805 | C4: 2910 | D4: Glosa : TDC CLP/USD Marcelo PENNA | E4: MARCELO PENNA SANTOS | H4: 79021 | I4: -337330
A5: adig/1205 | B5: 45820 | C5: 2861 | D5: Glosa : Bank Transfer to CC Marcelo Penna. | E5: MARCELO PENNA SANTOS | G5: 79021 | I5: -103303
A6: adig/1261 | B6: 45834 | C6: 2917 | D6: Glosa : TDC CLP/USD MARCELO PENNA | E6: MARCELO PENNA SANTOS | H6: 87617 | I6: -3757191
A7: adig/1315 | B7: 45848 | C7: 3052 | D7: Glosa : Bank Transfer to CC Marcelo Penna. | E7: MARCELO PENNA SANTOS | G7: 87617 | I7: -614411
A8: adig/1398 | B8: 45869 | C8: 3287 | D8: Glosa : APERTURA TDC M. PENNA ENERO | E8: MARCELO PENNA SANTOS | H8: 3652188 | I8: -17473122
A9: adig/1413 | B9: 45869 | C9: 3302 | D9: Glosa : APERTURA TDC M. PENNA FEB | E9: MARCELO PENNA SANTOS | H9: 715411 | I9: -20338430
A10: adig/1418 | B10: 45869 | C10: 3307 | D10: Glosa : APERTURA TDC M. PENNA MARZO | E10: MARCELO PENNA SANTOS | H10: 2623654 | I10: -23556473
A11: adig/1533 | B11: 45869 | C11: 3461 | D11: Glosa : ER - Marcelo Penna - Taxis / Trains / Buses - 25-04 Reimbursable Expense - Apr 2025 - Reimbursable | E11: MARCELO PENNA SANTOS | H11: 22780 | I11: -23579253
A12: adig/1115 | B12: 45772 | C12: 2554 | D12: Glosa : TDC CLP Marcelo PENNA | E12: MARCELO PENNA SANTOS | G12: 1499.57 | I12: 1499.57
A13: adig/1115 | B13: 45772 | C13: 2554 | D13: Glosa : TDC CLP Marcelo PENNA | E13: MARCELO PENNA SANTOS | H13: 1499.57 | I13: 0
A14: adig/1254 | B14: 45805 | C14: 2910 | D14: Glosa : TDC CLP/USD Marcelo PENNA | E14: MARCELO PENNA SANTOS | G14: 46.41 | H14: 46.41 | I14: -2300.55
A15: adig/1261 | B15: 45834 | C15: 2917 | D15: Glosa : TDC CLP/USD MARCELO PENNA | E15: MARCELO PENNA SANTOS | G15: 4.48 | H15: 4.48 | I15: -4017.71
D18: 2114-54 - CC Marcelo Penna | F18: 8406
B20: Fec. Doc. | C20: Voucher | E20: Titular | G20: Debe | H20: Haber | I20: Acumulado
B21: 45750 | C21: 2493 | D21: Glosa : reembolso Marcelo Penna | E21: MARCELO PENNA SANTOS | G21: 121678 | I21: 121678
B22: 45772 | C22: 2554 | D22: Glosa : TDC CLP Marcelo PENNA | E22: MARCELO PENNA SANTOS | H22: 1901018 | I22: -3443468
B23: 45785 | C23: 2721 | D23: Glosa : Payment: ER - Marcelo Penna25.4 - Reimbursable Expense - Apr 2025 - Reimbursa... | E23: MARCELO PENNA SANTOS | G23: 22780 | I23: -4454668
B24: 45792 | C24: 2749 | D24: Glosa : Bank Transfer to CC Marcelo Penna. | E24: MARCELO PENNA SANTOS | G24: 1901018 | I24: 1516349
B25: 45805 | C25: 2910 | D25: Glosa : TDC CLP/USD Marcelo PENNA | E25: MARCELO PENNA SANTOS | H25: 79021 | I25: -416242
B26: 45813 | C26: 2815 | D26: Glosa : Payment: ER - Marcelo Penna25.5 - Reimbursable Expense - Candelaria Site Visi... | 25.5 - Reimbursable Expense - Candelaria Site Visi... | E26: MARCELO PENNA SANTOS | G26: 20000 | I26: -736745
B27: 45820 | C27: 2861 | D27: Glosa : Bank Transfer to CC Marcelo Penna. | E27: MARCELO PENNA SANTOS | G27: 79021 | I27: -35577
B28: 45834 | C28: 2917 | D28: Glosa : TDC CLP/USD MARCELO PENNA | E28: MARCELO PENNA SANTOS | H28: 87617 | I28: -3680465
B29: 45848 | C29: 3052 | D29: Glosa : Bank Transfer to CC Marcelo Penna. | E29: MARCELO PENNA SANTOS | G29: 87617 | I29: -416955
B30: 45869 | C30: 3287 | D30: Glosa : APERTURA TDC M. PENNA ENERO | E30: MARCELO PENNA SANTOS | H30: 3652188 | I30: -18739659
B31: 45869 | C31: 3302 | D31: Glosa : APERTURA TDC M. PENNA FEB | E31: MARCELO PENNA SANTOS | H31: 715411 | I31: -21604967 | J31: 2011
B32: 45869 | C32: 3307 | D32: Glosa : APERTURA TDC M. PENNA MARZO | E32: MARCELO PENNA SANTOS | H32: 2623654 | I32: -24823010
B33: 45869 | C33: 3453 | D33: Glosa : reembolso Marcelo Penna | E33: MARCELO PENNA SANTOS | H33: 121678 | I33: -24957725
B34: 45869 | C34: 3460 | D34: Glosa : Spend Money CC Expense ABRIL-JULIO 2114-54 | E34: MARCELO PENNA SANTOS | H34: 384120 | I34: -27191245
B35: 45869 | C35: 3460 | D35: Glosa : Spend Money CC Expense ABRIL-JULIO 2114-54 | E35: MARCELO PENNA SANTOS | H35: 9397 | I35: -27200642 | J35: =H35-8406 -> 991
B36: 45869 | C36: 3461 | D36: Glosa : ER - Marcelo Penna - Taxis / Trains / Buses - 25-04 Reimbursable Expense - Apr 2025 - Reimbursable | E36: MARCELO PENNA SANTOS | H36: 22780 | I36: -27223422
B39: Fec. Doc. | C39: Voucher | E39: Titular | F39: T.Doc/Nro | G39: Debe | H39: Haber | I39: Acumulado
B40: 45693 | C40: 2280 | D40: Glosa : Pago Tarjeta de Credito | E40: MARCELO PENNA SANTOS | G40: 3652188 | I40: =+G40 -> 3652188
B41: 45750 | C41: 2493 | D41: Glosa : reembolso Marcelo Penna | E41: MARCELO PENNA SANTOS | G41: 121678 | I41: =I40+G41-H41 -> 3773866
B42: 45772 | C42: 2554 | D42: Glosa : TDC CLP Marcelo PENNA | E42: MARCELO PENNA SANTOS | H42: 1901018 | I42: =I41+G42-H42 -> 1872848
B43: 45785 | C43: 2721 | D43: Glosa : Payment: ER - Marcelo Penna25.4 - Reimbursable Expense - Apr 2025 - Reimbursa... | E43: MARCELO PENNA SANTOS | G43: 22780 | I43: =I42+G43-H43 -> 1895628
B44: 45792 | C44: 2749 | D44: Glosa : Bank Transfer to CC Marcelo Penna. | E44: MARCELO PENNA SANTOS | G44: 1901018 | I44: =I43+G44-H44 -> 3796646
B45: 45805 | C45: 2910 | D45: Glosa : TDC CLP/USD Marcelo PENNA | E45: MARCELO PENNA SANTOS | H45: 79021 | I45: =I44+G45-H45 -> 3717625
B46: 45813 | C46: 2815 | D46: Glosa : Payment: ER - Marcelo Penna25.5 - Reimbursable Expense - Candelaria Site Visi... | 25.5 - Reimbursable Expense - Candelaria Site Visi... | E46: MARCELO PENNA SANTOS | G46: 20000 | I46: =I45+G46-H46 -> 3737625
B47: 45820 | C47: 2861 | D47: Glosa : Bank Transfer to CC Marcelo Penna. | E47: MARCELO PENNA SANTOS | G47: 79021 | I47: =I46+G47-H47 -> 3816646
B48: 45834 | C48: 2917 | D48: Glosa : TDC CLP/USD MARCELO PENNA | E48: MARCELO PENNA SANTOS | H48: 87617 | I48: =I47+G48-H48 -> 3729029
B49: 45848 | C49: 3052 | D49: Glosa : Bank Transfer to CC Marcelo Penna. | E49: MARCELO PENNA SANTOS | G49: 87617 | I49: =I48+G49-H49 -> 3816646
B50: 45869 | C50: 3287 | D50: Glosa : APERTURA TDC M. PENNA ENERO | E50: MARCELO PENNA SANTOS | H50: 3652188 | I50: =I49+G50-H50 -> 164458
B51: 45869 | C51: 3302 | D51: Glosa : APERTURA TDC M. PENNA FEB | E51: MARCELO PENNA SANTOS | H51: 715411 | I51: =I50+G51-H51 -> -550953
B52: 45869 | C52: 3307 | D52: Glosa : APERTURA TDC M. PENNA MARZO | E52: MARCELO PENNA SANTOS | H52: 2623654 | I52: =I51+G52-H52 -> -3174607
B53: 45869 | C53: 3453 | D53: Glosa : reembolso Marcelo Penna | E53: MARCELO PENNA SANTOS | H53: 121678 | I53: =I52+G53-H53 -> -3296285
B54: 45869 | C54: 3460 | D54: Glosa : Spend Money CC Expense ABRIL-JULIO 2114-54 | E54: MARCELO PENNA SANTOS | H54: 384120 | I54: =I53+G54-H54 -> -3680405
B55: 45869 | C55: 3460 | D55: Glosa : Spend Money CC Expense ABRIL-JULIO 2114-54 | E55: MARCELO PENNA SANTOS | H55: 9397 | I55: =I54+G55-H55 -> -3689802
B56: 45869 | C56: 3461 | D56: Glosa : ER - Marcelo Penna - Taxis / Trains / Buses - 25-04 Reimbursable Expense - Apr 2025 - Reimbursable | E56: MARCELO PENNA SANTOS | H56: 22780 | I56: =I55+G56-H56 -> -3712582
B57: 45869 | C57: 3574 | D57: Glosa : compensa prov | E57: MARCELO PENNA SANTOS | G57: 1080522 | I57: =I56+G57-H57 -> -2632060
B58: 45762 | C58: 2512 | D58: Glosa : Pago Tarjeta de credito Marcelo Penna | E58: MARCELO PENNA SANTOS | G58: 2623654 | I58: =I57+G58-H58 -> -8406
B59: 45882 | C59: 3257 | D59: Glosa : MP´s credit card payment | E59: MARCELO PENNA SANTOS | G59: 8406 | I59: =I58+G59-H59 -> 0
A60: adig/1700 | B60: 45958 | C60: 3803 | D60: MARCELO PENNA SANTOS | H60: 46495 | I60: =I59+G60-H60 -> -46495
A61: adig/1743 | B61: 45974 | C61: 3910 | D61: =+A61 -> adig/1743 | E61: MARCELO PENNA SANTOS | G61: 46495 | I61: =I60+G61-H61 -> 0
A62: adig/1767 | B62: 45987 | C62: 3955 | D62: =+A62 -> adig/1767 | E62: MARCELO PENNA SANTOS | H62: 521349 | I62: =I61+G62-H62 -> -521349
A63: adig/1807 | B63: 46006 | C63: 4056 | D63: Glosa : Credit Card payment MP | E63: MARCELO PENNA SANTOS | G63: 521349 | I63: =I62+G63-H63 -> 0
A64: adig/1837 | B64: 46017 | C64: 4131 | D64: Glosa : TDC M. PENNA | E64: MARCELO PENNA SANTOS | H64: 752789 | I64: =I63+G64-H64 -> -752789
B66: 45958 | C66: 3803 | E66: MARCELO PENNA SANTOS | H66: 111.47 | I66: =I59+G66-H66 -> -111.47 | M66: =+I64+'15'!I28+'14'!I48+'13'!I70+'12'!I47+'11'!I52+'10'!I61+'9'!I64+95990 -> -3657252 | N66: pesos
A67: adig/1767 | B67: 45987 | C67: 3955 | D67: =+A67 -> adig/1767 | E67: MARCELO PENNA SANTOS | G67: 111.47 | I67: =I66+G67 -> 0 | K67: =+J66+I62 -> -521349 | L67: =+I68+'14'!I58+'13'!I73+'12'!I49+'11'!I59+'9'!I75 -> -1153.68 | M67: =L67*907.13 -> -1046537.7 | N67: dólar
A68: adig/1837 | B68: 46017 | C68: 4131 | D68: Glosa : TDC M. PENNA | E68: MARCELO PENNA SANTOS | H68: 103.08 | I68: =I67+G68-H68 -> -103.08 | J68: =-H68*907.13 -> -93506.96 | K68: =+J68+I64 -> -846295.96 | M68: =+K68+'15'!I28+'14'!K58+'13'!K73+'12'!K49+'11'!K59+'10'!I61+'9'!K75 -> -4799779.7 | N68: total

Sheet 54_x
A1: Account Code | B1: Account | C1: Date | D1: Source | E1: Description | F1: Reference | G1: Debit | H1: Credit
A2: 2114-54 | B2: CC Marcelo Penna | C2: 45665 | D2: Payable Payment | E2: Payment: LATAM | F2: F/6253036 | G2: 0 | H2: 1223730 | I2: =+G2-H2 -> -1223730
A3: 2114-54 | B3: CC Marcelo Penna | C3: 45665 | D3: Payable Payment | E3: Payment: LATAM | F3: F/6253360 | G3: 0 | H3: 2152930 | I3: =I2+G3-H3 -> -3376660
A4: 2114-54 | B4: CC Marcelo Penna | C4: 45665 | D4: Payable Payment | E4: Payment: LATAM | F4: F/6253368 | G4: 0 | H4: 1346628 | I4: =I3+G4-H4 -> -4723288
A5: 2114-54 | B5: CC Marcelo Penna | C5: 45666 | D5: Spend Money | E5: CC Expense | F5: Lunch with Andrew | G5: 0 | H5: 127160 | I5: =I4+G5-H5 -> -4850448
A6: 2114-54 | B6: CC Marcelo Penna | C6: 45666 | D6: Spend Money | E6: CC Expense | F6: Uber: Office - Dinner with Andrew | G6: 0 | H6: 13618 | I6: =I5+G6-H6 -> -4864066
A7: 2114-54 | B7: CC Marcelo Penna | C7: 45666 | D7: Spend Money | E7: CC Expense | F7: Uber: Dinner with Andrew - ICON | G7: 0 | H7: 6750 | I7: =I6+G7-H7 -> -4870816
A8: 2114-54 | B8: CC Marcelo Penna | C8: 45670 | D8: Bank Transfer | E8: Bank Transfer from Citibank - CLP to CC Marcelo Penna | F8: CC Automatic Payment | G8: 10525 | H8: 0 | I8: =I7+G8-H8 -> -4860291
A9: 2114-54 | B9: CC Marcelo Penna | C9: 45674 | D9: Payable Credit Note Refund | E9: Payment: LATAM | F9: 1228146 | G9: 1223730 | H9: 0 | I9: =I8+G9-H9 -> -3636561
A10: 2114-54 | B10: CC Marcelo Penna | C10: 45685 | D10: Spend Money | E10: CC Expense | F10: Visa Ecuador - Francisco Miranda (MDM Discovery with Lundin Gold) | G10: 0 | H10: 49100 | I10: =I9+G10-H10 -> -3685661
A11: 2114-54 | B11: CC Marcelo Penna | C11: 45685 | D11: Spend Money | E11: Banco De Chile | G11: 0 | H11: 305 | I11: =I10+G11-H11 -> -3685966
A12: 2114-54 | B12: CC Marcelo Penna | C12: 45686 | D12: Spend Money | E12: Banco De Chile | G12: 0 | H12: 3839 | I12: =I11+G12-H12 -> -3689805
A13: 2114-54 | B13: CC Marcelo Penna | C13: 45686 | D13: Spend Money | E13: Banco De Chile | G13: 0 | H13: 1263 | I13: =I12+G13-H13 -> -3691068
A14: 2114-54 | B14: CC Marcelo Penna | C14: 45687 | D14: Spend Money | E14: uber | G14: 0 | H14: 4997 | I14: =I13+G14-H14 -> -3696065
A15: 2114-54 | B15: CC Marcelo Penna | C15: 45688 | D15: Spend Money | E15: Moloco | G15: 0 | H15: 500610 | I15: =I14+G15-H15 -> -4196675
A16: 2114-54 | B16: CC Marcelo Penna | C16: 45688 | D16: Spend Money | E16: Moloco | G16: 0 | H16: 45540 | I16: =I15+G16-H16 -> -4242215
A17: 2114-54 | B17: CC Marcelo Penna | C17: 45689 | D17: Spend Money | E17: CC Expense | F17: Uber - Office - Siro's Farewell | G17: 0 | H17: 4997 | I17: =I16+G17-H17 -> -4247212
A18: 2114-54 | B18: CC Marcelo Penna | C18: 45689 | D18: Spend Money | E18: CC Expense | F18: Siro's Farewell 1 | G18: 0 | H18: 500610 | I18: =I17+G18-H18 -> -4747822
A19: 2114-54 | B19: CC Marcelo Penna | C19: 45689 | D19: Spend Money | E19: CC Expense | F19: Siro's Farewell 2 | G19: 0 | H19: 45540 | I19: =I18+G19-H19 -> -4793362
A20: 2114-54 | B20: CC Marcelo Penna | C20: 45690 | D20: Spend Money | E20: CC Expense | F20: Uber Home-SCL | G20: 0 | H20: 32706 | I20: =I19+G20-H20 -> -4826068
A21: 2114-54 | B21: CC Marcelo Penna | C21: 45690 | D21: Spend Money | E21: CC Expense | F21: Water - Airport | G21: 0 | H21: 3500 | I21: =I20+G21-H21 -> -4829568
A22: 2114-54 | B22: CC Marcelo Penna | C22: 45690 | D22: Spend Money | E22: CC Expense | F22: NZeTA Visa | G22: 0 | H22: 9264.79 | I22: =I21+G22-H22 -> -4838832.8
A23: 2114-54 | B23: CC Marcelo Penna | C23: 45690 | D23: Receive Money | E23: maloco | G23: 500610 | H23: 0 | I23: =I22+G23-H23 -> -4338222.8
A24: 2114-54 | B24: CC Marcelo Penna | C24: 45690 | D24: Receive Money | E24: maloco | G24: 45540 | H24: 0 | I24: =I23+G24-H24 -> -4292682.8
A25: 2114-54 | B25: CC Marcelo Penna | C25: 45690 | D25: Receive Money | E25: uber | G25: 4997 | H25: 0 | I25: =I24+G25-H25 -> -4287685.8
A26: 2114-54 | B26: CC Marcelo Penna | C26: 45691 | D26: Spend Money | E26: Banco De Chile | G26: 0 | H26: 230 | I26: =I25+G26-H26 -> -4287915.8
A27: 2114-54 | B27: CC Marcelo Penna | C27: 45691 | D27: Spend Money | E27: CC Expense | F27: Water Airport AKL (Vending Machine) | G27: 0 | H27: 2178.27 | I27: =I26+G27-H27 -> -4290094.1
A28: 2114-54 | B28: CC Marcelo Penna | C28: 45692 | D28: Spend Money | E28: Banco De Chile | G28: 0 | H28: 1200 | I28: =I27+G28-H28 -> -4291294.1
A29: 2114-54 | B29: CC Marcelo Penna | C29: 45692 | D29: Spend Money | E29: Banco De Chile | G29: 0 | H29: 509 | I29: =I28+G29-H29 -> -4291803.1
A30: 2114-54 | B30: CC Marcelo Penna | C30: 45692 | D30: Spend Money | E30: Banco De Chile | G30: 0 | H30: 58 | I30: =I29+G30-H30 -> -4291861.1
A31: 2114-54 | B31: CC Marcelo Penna | C31: 45692 | D31: Spend Money | E31: CC Expense | F31: Lunch | G31: 0 | H31: 19975.41 | I31: =I30+G31-H31 -> -4311836.5
A32: 2114-54 | B32: CC Marcelo Penna | C32: 45692 | D32: Spend Money | E32: CC Expense | F32: Inchcolm Hotel | G32: 0 | H32: 1549131.1 | I32: =I31+G32-H32 -> -5860967.6
A33: 2114-54 | B33: CC Marcelo Penna | C33: 45692 | D33: Spend Money | E33: CC Expense | F33: Dinner | G33: 0 | H33: 13754.5 | I33: =I32+G33-H33 -> -5874722.1
A34: 2114-54 | B34: CC Marcelo Penna | C34: 45692 | D34: Spend Money | E34: CC Expense | F34: Taxi BNE-Hotel | G34: 0 | H34: 47389.28 | I34: =I33+G34-H34 -> -5922111.3
A35: 2114-54 | B35: CC Marcelo Penna | C35: 45693 | D35: Bank Transfer | E35: Bank Transfer from Citibank - CLP to CC Marcelo Penna | F35: MP CC payment | G35: 3652188 | H35: 0 | I35: =I34+G35-H35 -> -2269923.3
A36: 2114-54 | B36: CC Marcelo Penna | C36: 45693 | D36: Spend Money | E36: Banco De Chile | G36: 0 | H36: 345 | I36: =I35+G36-H36 -> -2270268.3
A37: 2114-54 | B37: CC Marcelo Penna | C37: 45693 | D37: Spend Money | E37: Banco De Chile | G37: 0 | H37: 288 | I37: =I36+G37-H37 -> -2270556.3
A38: 2114-54 | B38: CC Marcelo Penna | C38: 45693 | D38: Spend Money | E38: Banco De Chile | G38: 0 | H38: 39082 | I38: =I37+G38-H38 -> -2309638.3
A39: 2114-54 | B39: CC Marcelo Penna | C39: 45693 | D39: Spend Money | E39: CC Expense | F39: Breakfast | G39: 0 | H39: 11252.81 | I39: =I38+G39-H39 -> -2320891.1
A40: 2114-54 | B40: CC Marcelo Penna | C40: 45693 | D40: Spend Money | E40: CC Expense | F40: Dinner | G40: 0 | H40: 13611.82 | I40: =I39+G40-H40 -> -2334503
A41: 2114-54 | B41: CC Marcelo Penna | C41: 45694 | D41: Spend Money | E41: Banco De Chile | G41: 0 | H41: 346 | I41: =I40+G41-H41 -> -2334849
A42: 2114-54 | B42: CC Marcelo Penna | C42: 45694 | D42: Spend Money | E42: Banco De Chile | G42: 0 | H42: 346 | I42: =I41+G42-H42 -> -2335195
A43: 2114-54 | B43: CC Marcelo Penna | C43: 45694 | D43: Spend Money | E43: CC Expense | F43: Breakfast | G43: 0 | H43: 13754.5 | I43: =I42+G43-H43 -> -2348949.5
A44: 2114-54 | B44: CC Marcelo Penna | C44: 45695 | D44: Spend Money | E44: Banco De Chile | G44: 0 | H44: 470 | I44: =I43+G44-H44 -> -2349419.5
A45: 2114-54 | B45: CC Marcelo Penna | C45: 45695 | D45: Spend Money | E45: CC Expense | F45: Lunch (Marcelo + Alvaro) | G45: 0 | H45: 18615.18 | I45: =I44+G45-H45 -> -2368034.6
A46: 2114-54 | B46: CC Marcelo Penna | C46: 45695 | D46: Spend Money | E46: uber | G46: 0 | H46: 20393.94 | I46: =I45+G46-H46 -> -2388428.6
A47: 2114-54 | B47: CC Marcelo Penna | C47: 45698 | D47: Spend Money | E47: Banco De Chile | G47: 0 | H47: 230 | I47: =I46+G47-H47 -> -2388658.6
A48: 2114-54 | B48: CC Marcelo Penna | C48: 45698 | D48: Spend Money | E48: CC Expense | F48: Dinner | G48: 0 | H48: 15828.13 | I48: =I47+G48-H48 -> -2404486.7
A49: 2114-54 | B49: CC Marcelo Penna | C49: 45698 | D49: Spend Money | E49: CC Expense | F49: Lunch | G49: 0 | H49: 9103.08 | I49: =I48+G49-H49 -> -2413589.8
A50: 2114-54 | B50: CC Marcelo Penna | C50: 45699 | D50: Spend Money | E50: Banco De Chile | G50: 0 | H50: 403 | I50: =I49+G50-H50 -> -2413992.8
A51: 2114-54 | B51: CC Marcelo Penna | C51: 45700 | D51: Spend Money | E51: Banco De Chile | G51: 0 | H51: 48 | I51: =I50+G51-H51 -> -2414040.8
A52: 2114-54 | B52: CC Marcelo Penna | C52: 45700 | D52: Spend Money | E52: Banco De Chile | G52: 0 | H52: 269 | I52: =I51+G52-H52 -> -2414309.8
A53: 2114-54 | B53: CC Marcelo Penna | C53: 45700 | D53: Spend Money | E53: CC Expense | F53: Water Airport BNE (Vending Machine) | G53: 0 | H53: 2720.46 | I53: =I52+G53-H53 -> -2417030.3
A54: 2114-54 | B54: CC Marcelo Penna | C54: 45700 | D54: Spend Money | E54: CC Expense | F54: Snack | G54: 0 | H54: 1816.81 | I54: =I53+G54-H54 -> -2418847.1
A55: 2114-54 | B55: CC Marcelo Penna | C55: 45700 | D55: Spend Money | E55: CC Expense | F55: Lunch | G55: 0 | H55: 10767.7 | I55: =I54+G55-H55 -> -2429614.8
A56: 2114-54 | B56: CC Marcelo Penna | C56: 45701 | D56: Spend Money | E56: Banco De Chile | G56: 0 | H56: 787 | I56: =I55+G56-H56 -> -2430401.8
A57: 2114-54 | B57: CC Marcelo Penna | C57: 45701 | D57: Spend Money | E57: Banco De Chile | G57: 0 | H57: 518 | I57: =I56+G57-H57 -> -2430919.8
A58: 2114-54 | B58: CC Marcelo Penna | C58: 45701 | D58: Spend Money | E58: Banco De Chile | G58: 0 | H58: 106 | I58: =I57+G58-H58 -> -2431025.8
A59: 2114-54 | B59: CC Marcelo Penna | C59: 45701 | D59: Spend Money | E59: CC Expense | F59: Water - Airport | G59: 0 | H59: 4052.15 | I59: =I58+G59-H59 -> -2435077.9
A60: 2114-54 | B60: CC Marcelo Penna | C60: 45701 | D60: Spend Money | E60: CC Expense | F60: Uber Hotel-BNE | G60: 0 | H60: 31029.06 | I60: =I59+G60-H60 -> -2466107
A61: 2114-54 | B61: CC Marcelo Penna | C61: 45701 | D61: Spend Money | E61: CC Expense | F61: Taxi - SCL-Home | G61: 0 | H61: 29000 | I61: =I60+G61-H61 -> -2495107
A62: 2114-54 | B62: CC Marcelo Penna | C62: 45702 | D62: Spend Money | E62: Banco De Chile | G62: 0 | H62: 67 | I62: =I61+G62-H62 -> -2495174
A63: 2114-54 | B63: CC Marcelo Penna | C63: 45714 | D63: Spend Money | E63: Banco De Chile | G63: 0 | H63: 32 | I63: =I62+G63-H63 -> -2495206
A64: 2114-54 | B64: CC Marcelo Penna | C64: 45714 | D64: Spend Money | E64: Banco De Chile | G64: 0 | H64: 3862 | I64: =I63+G64-H64 -> -2499068
A65: 2114-54 | B65: CC Marcelo Penna | C65: 45714 | D65: Spend Money | E65: Banco De Chile | G65: 0 | H65: 1212 | I65: =I64+G65-H65 -> -2500280
A66: 2114-54 | B66: CC Marcelo Penna | C66: 45716 | D66: Receive Money | E66: Banco De Chile | G66: 612.9 | H66: 0 | I66: =I65+G66-H66 -> -2499667.1
A67: 2114-54 | B67: CC Marcelo Penna | C67: 45717 | D67: Spend Money | E67: CC Expense | F67: Seat Selection | G67: 0 | H67: 168986 | I67: =I66+G67-H67 -> -2668653.1
A68: 2114-54 | B68: CC Marcelo Penna | C68: 45723 | D68: Bank Transfer | E68: Bank Transfer from Citibank - CLP to CC Marcelo Penna | F68: Marcelo CC Payment | G68: 884397 | H68: 0 | I68: =I67+G68-H68 -> -1784256.1
A69: 2114-54 | B69: CC Marcelo Penna | C69: 45729 | D69: Spend Money | E69: CC Expense | F69: Happy Hour Deswik 13/03 | G69: 0 | H69: 571890 | I69: =I68+G69-H69 -> -2356146.1
A70: 2114-54 | B70: CC Marcelo Penna | C70: 45729 | D70: Spend Money | E70: CC Expense | F70: Lunch - Csar, Marcelo, Alexandre | G70: 0 | H70: 37021 | I70: =I69+G70-H70 -> -2393167.1
A71: 2114-54 | B71: CC Marcelo Penna | C71: 45731 | D71: Spend Money | E71: CC Expense | F71: Uber Home-SCL | G71: 0 | H71: 28764 | I71: =I70+G71-H71 -> -2421931.1
A72: 2114-54 | B72: CC Marcelo Penna | C72: 45732 | D72: Spend Money | E72: CC Expense | F72: Water (Vending Machine) | G72: 0 | H72: 2195 | I72: =I71+G72-H72 -> -2424126.1
A73: 2114-54 | B73: CC Marcelo Penna | C73: 45733 | D73: Spend Money | E73: Banco De Chile | G73: 0 | H73: 459 | I73: =I72+G73-H73 -> -2424585.1
A74: 2114-54 | B74: CC Marcelo Penna | C74: 45733 | D74: Spend Money | E74: Banco De Chile | G74: 0 | H74: 1808 | I74: =I73+G74-H74 -> -2426393.1
A75: 2114-54 | B75: CC Marcelo Penna | C75: 45733 | D75: Spend Money | E75: Banco De Chile | G75: 0 | H75: 56 | I75: =I74+G75-H75 -> -2426449.1
A76: 2114-54 | B76: CC Marcelo Penna | C76: 45733 | D76: Spend Money | E76: CC Expense | F76: Taxi BNE-Inchcolm | G76: 0 | H76: 43180 | I76: =I75+G76-H76 -> -2469629.1
A77: 2114-54 | B77: CC Marcelo Penna | C77: 45733 | D77: Spend Money | E77: CC Expense | F77: Lunch 17/03 | G77: 0 | H77: 18383 | I77: =I76+G77-H77 -> -2488012.1
A78: 2114-54 | B78: CC Marcelo Penna | C78: 45733 | D78: Spend Money | E78: CC Expense | F78: Dinner 17/03 (Marcelo and Bruno T.) | G78: 0 | H78: 73048 | I78: =I77+G78-H78 -> -2561060.1
A79: 2114-54 | B79: CC Marcelo Penna | C79: 45734 | D79: Spend Money | E79: Banco De Chile | G79: 0 | H79: 1068 | I79: =I78+G79-H79 -> -2562128.1
A80: 2114-54 | B80: CC Marcelo Penna | C80: 45735 | D80: Spend Money | E80: Banco De Chile | G80: 0 | H80: 94 | I80: =I79+G80-H80 -> -2562222.1
