Workbook

Sheet Centros de costos
A1: nombre | B1: apellido paterno | C1: apellido materno | D1: centro costo nombre | E1: cto cto nombre Ingles
A2: KATHERINNE SILVANA | B2: ALARCON | C2: ESCOBAR | D2: Administración y Gerencia | E2: Admin
A3: CRISTIAN | B3: ANABALON | C3: BARRÍA | D3: Consultoria | E3: Consulting
A4: KATHERINE MARLENE | B4: BOLLMANN | C4: NILIAN | D4: Ventas y marketing | E4: Mkt
A5: Lucas Guilherme | B5: Cardoso | C5: Bittencourt | D5: Consultoria | E5: Consulting
A6: JUAN SEBASTIAN | B6: CARVALLO | C6: JIMÉNEZ | D6: Consultoria | E6: Consulting
A7: Denisse Massiel | B7: Castro | C7: Acuña | D7: Soporte | E7: Support
A8: CAROL TATIANA | B8: CONTRERAS | C8: MUÑOZ | D8: Administración y Gerencia | E8: Admin
A9: ANTONIETA | B9: GONZALEZ | C9: OLIVEROS | D9: Consultoria | E9: Consulting
A10: CESAR FELIPE | B10: MACHADO | C10: RIBEIRO LOPES | D10: Administración y Gerencia | E10: Admin
A11: FRANCISCO | B11: MIRANDA | C11: RIADI | D11: Consultoria | E11: Consulting
A12: JORGE | B12: MORIS | C12: JORDÁN | D12: Consultoria | E12: Consulting
... A15: Caroline | B15: Zorzi | C15: . | D15: Consultoria | E15: Consulting

Sheet 01
E1: =SUM(E2:E25) -> 100539524 | F1: =SUM(F2:F25) -> 100539524
A2: 5011 | B2: Salario | C2: Consulting | D2: 7020201 | E2: 49215265
A3: 5012 | B3: Bono | C3: Consulting | D3: 7020202 | E3: 0
A4: 5013 | B4: AFP | C4: Consulting | D4: 7020203 | E4: 2000739
A5: 5015 | B5: ISAPRE | C5: Consulting | D5: 7020204
A6: 6306 | B6: Salario | C6: Admin | D6: 8050117 | E6: 34741290
A7: 6307 | B7: Bono | C7: Admin | D7: 8050118 | E7: 0
A8: 6308 | B8: AFP | C8: Admin | D8: 8050119 | E8: 1132313
A9: 6326 | B9: ISAPRE | C9: Admin | D9: 8050121
A10: 6306 | B10: Salario | C10: Admin/Sales | E10: 0
A11: 6307 | B11: Bono | C11: Admin/Sales | E11: 0
A12: 6308 | B12: AFP | C12: Admin/Sales | E12: 0
A13: 6326 | B13: ISAPRE | C13: Admin/Sales
A14: 6301 | B14: Salario | C14: Mkt | D14: 8050101 | E14: 10959902
A15: 6302 | B15: Bono | C15: Mkt | D15: 8050102 | E15: 0
A16: 6303 | B16: AFP | C16: Mkt | D16: 8050106 | E16: 252607
A17: 6327 | B17: ISAPRE | C17: Mkt | D17: 8050120
A18: 5211 | B18: Salario | C18: Support | D18: 7020205 | E18: 2113354
A19: 5211 | B19: Bono | C19: Support | D19: 7020206 | E19: 0
A20: 5213 | B20: AFP | C20: Support | D20: 7020207 | E20: 124054
A21: 5215 | B21: ISAPRE | C21: Support | D21: 7020208
A22: 2414 | B22: Previred por pagar | D22: 3031302 | F22: 13644093
A23: 2411 | B23: Remuneraciones por pagar | D23: 3031204 | F23: 75249157
A24: 2554 | B24: Impuesto adicional prestamo | D24: 3031505
A25: 2554 | B25: Impuesto unico trabajador | D25: 3031501 | F25: 11646274

Sheet 02
E1: =SUM(E2:E25) -> 196089720 | F1: =SUM(F2:F25) -> 196089720
A2: 5011 | B2: Salario | C2: Consulting | D2: 7020201 | E2: 50315265
A3: 5012 | B3: Bono | C3: Consulting | D3: 7020202 | E3: 55191458
A4: 5013 | B4: AFP | C4: Consulting | D4: 7020203 | E4: 2174907
A5: 5015 | B5: ISAPRE | C5: Consulting | D5: 7020204
A6: 6306 | B6: Salario | C6: Admin | D6: 8050117 | E6: 17481562
A7: 6307 | B7: Bono | C7: Admin | D7: 8050118 | E7: 21694582
A8: 6308 | B8: AFP | C8: Admin | D8: 8050119 | E8: 1126679
A9: 6326 | B9: ISAPRE | C9: Admin | D9: 8050121
A10: 6306 | C10: Admin/Sales | E10: 0
A11: 6307 | C11: Admin/Sales | E11: 0
A12: 6308 | C12: Admin/Sales | E12: 0
A13: 6326 | C13: Admin/Sales
A14: 6301 | B14: Salario | C14: Mkt | D14: 8050101 | E14: 11391516
A15: 6302 | B15: Bono | C15: Mkt | D15: 8050102 | E15: 31628122
A16: 6303 | B16: AFP | C16: Mkt | D16: 8050106 | E16: 319200
A17: 6327 | B17: ISAPRE | C17: Mkt | D17: 8050120
A18: 5211 | B18: Salario | C18: Support | D18: 7020205 | E18: 2113354
A19: 5211 | B19: Bono | C19: Support | D19: 7020206 | E19: 2399540
A20: 5213 | B20: AFP | C20: Support | D20: 7020207 | E20: 253535
A21: 5215 | B21: ISAPRE | C21: Support | D21: 7020208
A22: 2414 | B22: Previred por pagar | D22: 3031302 | F22: 14744693
A23: 2411 | B23: Remuneraciones por pagar | D23: 3031204 | F23: 144401605
A24: 2554 | B24: Impuesto adicional prestamo | D24: 3031505
A25: 2554 | B25: Impuesto unico trabajador | D25: 3031501 | F25: 36943422

Sheet 03
E1: =SUM(E2:E25) -> 88032281 | F1: =SUM(F2:F26) -> 88032281
A2: 5011 | B2: Salario | C2: Consulting | D2: 7020201 | E2: 49765265
A3: 5012 | B3: Bono | C3: Consulting | D3: 7020202 | E3: 800000
A4: 5013 | B4: AFP | C4: Consulting | D4: 7020203 | E4: 2010093
A5: 5015 | B5: ISAPRE | C5: Consulting | D5: 7020204 | E5: 0
A6: 6306 | B6: Salario | C6: Admin | D6: 8050117 | E6: 18845134
A7: 6307 | B7: Bono | C7: Admin | D7: 8050118 | E7: 0
A8: 6308 | B8: AFP | C8: Admin | D8: 8050119 | E8: 891590
A9: 6326 | B9: ISAPRE | C9: Admin | D9: 8050121 | E9: 0
A10: 6306 | C10: Admin/Sales | E10: 0
A11: 6307 | C11: Admin/Sales | E11: 0
A12: 6308 | C12: Admin/Sales | E12: 0
A13: 6326 | C13: Admin/Sales | E13: 0
A14: 6301 | B14: Salario | C14: Mkt | D14: 8050101 | E14: 13093345
A15: 6302 | B15: Bono | C15: Mkt | D15: 8050102 | E15: 0
A16: 6303 | B16: AFP | C16: Mkt | D16: 8050106 | E16: 389446
A17: 6327 | B17: ISAPRE | C17: Mkt | D17: 8050120
A18: 5211 | B18: Salario | C18: Support | D18: 7020205 | E18: 2113354
A19: 5211 | B19: Bono | C19: Support | D19: 7020206 | E19: 0
A20: 5213 | B20: AFP | C20: Support | D20: 7020207 | E20: 124054
A21: 5215 | B21: ISAPRE | C21: Support | D21: 7020208
A22: 2414 | B22: Previred por pagar | D22: 3031302 | F22: 13690227
A23: 2411 | B23: Remuneraciones por pagar | D23: 3031204 | F23: 58789176
A24: 2554 | B24: Impuesto adicional prestamo | D24: 3031505
A25: 2554 | B25: Impuesto unico trabajador | D25: 3031501 | F25: 7837686
A26: 2411 | B26: Anticipo de sueldos | D26: 3031204 | F26: 7715192

Sheet 04
A1: cta Deswik | B1: Remuneraciones Deswik abril 2025 | D1: cta magnus | E1: =SUM(E2:E27) -> 90199043 | F1: =SUM(F2:F28) -> 90199043
A2: 5011 | B2: Salario | C2: Consulting | D2: 7020201 | E2: 51556832
A3: 5012 | B3: Bono | C3: Consulting | D3: 7020202 | E3: 100000
A4: 5013 | B4: AFP | C4: Consulting | D4: 7020203 | E4: 2062013
A5: 5015 | B5: ISAPRE | C5: Consulting | D5: 7020204 | E5: 0
A6: 6306 | B6: Salario | C6: Admin | D6: 8050117 | E6: 19578416
A7: 6307 | B7: Bono | C7: Admin | D7: 8050118 | E7: 0
A8: 8018 | B8: Bono LTI | C8: Mkt | D8: 8050122
A9: 6308 | B9: AFP | C9: Admin | D9: 8050119 | E9: 913115
A10: 6326 | B10: ISAPRE | C10: Admin | D10: 8050121
C11: Admin/Sales
C12: Admin/Sales
C13: Admin/Sales
C14: Admin/Sales
A15: 6301 | B15: Salario | C15: Mkt | D15: 8050101 | E15: 13088910
A16: 6302 | B16: Bono | C16: Mkt | D16: 8050102 | E16: 0
A17: 6303 | B17: AFP | C17: Mkt | D17: 8050106 | E17: 395784
A18: 6327 | B18: ISAPRE | C18: Mkt | D18: 8050120
A19: 5211 | B19: Salario | C19: Support | D19: 7020205 | E19: 2363354
A20: 5211 | B20: Bono | C20: Support | D20: 7020206 | E20: 0
A21: 5213 | B21: AFP | C21: Support | D21: 7020207 | E21: 140619
A22: 5215 | B22: ISAPRE | C22: Support | D22: 7020208
A23: 2414 | B23: Previred por pagar | D23: 3031302 | F23: 13992865
A24: 2414 | B24: Seguro complementario | D24: 8050305
A25: 2411 | B25: Remuneraciones por pagar | D25: 3031204 | F25: 68100432
A26: 2554 | B26: Impuesto adicional prestamo | D26: 3031505
A27: 2554 | B27: Impuesto unico trabajador | D27: 3031501 | F27: 8105746
A28: 2411 | B28: Anticipo de sueldos | D28: 3031204

Sheet 05
A1: cta Deswik | B1: Remuneraciones Deswik mayo 2025 | D1: cta magnus | E1: =SUM(E2:E27) -> 0 | F1: =SUM(F2:F27) -> 0
A2: 5011 | B2: Salario | C2: Consulting | D2: 7020201
A3: 5012 | B3: Bono | C3: Consulting | D3: 7020202
A4: 5013 | B4: AFP | C4: Consulting | D4: 7020203
A5: 5015 | B5: ISAPRE | C5: Consulting | D5: 7020204
A6: 6306 | B6: Salario | C6: Admin | D6: 8050117
A7: 6307 | B7: Bono | C7: Admin | D7: 8050118
A8: 6308 | B8: AFP | C8: Admin | D8: 8050119
A9: 6326 | B9: ISAPRE | C9: Admin | D9: 8050121
C10: Admin/Sales
C11: Admin/Sales
C12: Admin/Sales
C13: Admin/Sales
A14: 6301 | B14: Salario | C14: Mkt | D14: 8050101
A15: 6302 | B15: Bono | C15: Mkt | D15: 8050102
A16: 6303 | B16: AFP | C16: Mkt | D16: 8050106
A17: 6327 | B17: ISAPRE | C17: Mkt | D17: 8050120
A18: 5211 | B18: Salario | C18: Support | D18: 7020205
A19: 5211 | B19: Bono | C19: Support | D19: 7020206
A20: 5213 | B20: AFP | C20: Support | D20: 7020207
A21: 5215 | B21: ISAPRE | C21: Support | D21: 7020208
A22: 2414 | B22: Previred por pagar | D22: 3031302
A23: 2414 | B23: Seguro complementario | D23: 8050305
A24: 2411 | B24: Remuneraciones por pagar | D24: 3031204
A25: 2554 | B25: Impuesto adicional prestamo | D25: 3031505
A26: 2554 | B26: Impuesto unico trabajador | D26: 3031501
A27: 2411 | B27: Anticipo de sueldos | D27: 3031204

Sheet 06
A1: cta Deswik | B1: Remuneraciones Deswik mayo 2025 | D1: cta magnus | E1: =SUM(E2:E27) -> 0 | F1: =SUM(F2:F27) -> 0
A2: 5011 | B2: Salario | C2: Consulting | D2: 7020201
A3: 5012 | B3: Bono | C3: Consulting | D3: 7020202
A4: 5013 | B4: AFP | C4: Consulting | D4: 7020203
A5: 5015 | B5: ISAPRE | C5: Consulting | D5: 7020204
A6: 6306 | B6: Salario | C6: Admin | D6: 8050117
A7: 6307 | B7: Bono | C7: Admin | D7: 8050118
A8: 6308 | B8: AFP | C8: Admin | D8: 8050119
A9: 6326 | B9: ISAPRE | C9: Admin | D9: 8050121
C10: Admin/Sales
C11: Admin/Sales
C12: Admin/Sales
C13: Admin/Sales
A14: 6301 | B14: Salario | C14: Mkt | D14: 8050101
A15: 6302 | B15: Bono | C15: Mkt | D15: 8050102
A16: 6303 | B16: AFP | C16: Mkt | D16: 8050106
A17: 6327 | B17: ISAPRE | C17: Mkt | D17: 8050120
A18: 5211 | B18: Salario | C18: Support | D18: 7020205
A19: 5211 | B19: Bono | C19: Support | D19: 7020206
A20: 5213 | B20: AFP | C20: Support | D20: 7020207
A21: 5215 | B21: ISAPRE | C21: Support | D21: 7020208
A22: 2414 | B22: Previred por pagar | D22: 3031302
A23: 2414 | B23: Seguro complementario | D23: 8050305
A24: 2411 | B24: Remuneraciones por pagar | D24: 3031204
A25: 2554 | B25: Impuesto adicional prestamo | D25: 3031505
A26: 2554 | B26: Impuesto unico trabajador | D26: 3031501
A27: 2411 | B27: Anticipo de sueldos | D27: 3031204

Sheet 07
A1: cta Deswik | B1: Remuneraciones Deswik mayo 2025 | D1: cta magnus | E1: =SUM(E2:E27) -> 0 | F1: =SUM(F2:F27) -> 0
A2: 5011 | B2: Salario | C2: Consulting | D2: 7020201
A3: 5012 | B3: Bono | C3: Consulting | D3: 7020202
A4: 5013 | B4: AFP | C4: Consulting | D4: 7020203
A5: 5015 | B5: ISAPRE | C5: Consulting | D5: 7020204
A6: 6306 | B6: Salario | C6: Admin | D6: 8050117
A7: 6307 | B7: Bono | C7: Admin | D7: 8050118
A8: 6308 | B8: AFP | C8: Admin | D8: 8050119
A9: 6326 | B9: ISAPRE | C9: Admin | D9: 8050121
C10: Admin/Sales
C11: Admin/Sales
C12: Admin/Sales
C13: Admin/Sales
A14: 6301 | B14: Salario | C14: Mkt | D14: 8050101
A15: 6302 | B15: Bono | C15: Mkt | D15: 8050102
A16: 6303 | B16: AFP | C16: Mkt | D16: 8050106
A17: 6327 | B17: ISAPRE | C17: Mkt | D17: 8050120
A18: 5211 | B18: Salario | C18: Support | D18: 7020205
A19: 5211 | B19: Bono | C19: Support | D19: 7020206
A20: 5213 | B20: AFP | C20: Support | D20: 7020207
A21: 5215 | B21: ISAPRE | C21: Support | D21: 7020208
A22: 2414 | B22: Previred por pagar | D22: 3031302
A23: 2414 | B23: Seguro complementario | D23: 8050305
A24: 2411 | B24: Remuneraciones por pagar | D24: 3031204
A25: 2554 | B25: Impuesto adicional prestamo | D25: 3031505
A26: 2554 | B26: Impuesto unico trabajador | D26: 3031501
A27: 2411 | B27: Anticipo de sueldos | D27: 3031204

Sheet 08
A1: cta Deswik | B1: Remuneraciones Deswik mayo 2025 | D1: cta magnus | E1: =SUM(E2:E27) -> 0 | F1: =SUM(F2:F27) -> 0
A2: 5011 | B2: Salario | C2: Consulting | D2: 7020201
A3: 5012 | B3: Bono | C3: Consulting | D3: 7020202
A4: 5013 | B4: AFP | C4: Consulting | D4: 7020203
A5: 5015 | B5: ISAPRE | C5: Consulting | D5: 7020204
A6: 6306 | B6: Salario | C6: Admin | D6: 8050117
A7: 6307 | B7: Bono | C7: Admin | D7: 8050118
A8: 6308 | B8: AFP | C8: Admin | D8: 8050119
A9: 6326 | B9: ISAPRE | C9: Admin | D9: 8050121
C10: Admin/Sales
C11: Admin/Sales
C12: Admin/Sales
C13: Admin/Sales
A14: 6301 | B14: Salario | C14: Mkt | D14: 8050101
A15: 6302 | B15: Bono | C15: Mkt | D15: 8050102
A16: 6303 | B16: AFP | C16: Mkt | D16: 8050106
A17: 6327 | B17: ISAPRE | C17: Mkt | D17: 8050120
A18: 5211 | B18: Salario | C18: Support | D18: 7020205
A19: 5211 | B19: Bono | C19: Support | D19: 7020206
A20: 5213 | B20: AFP | C20: Support | D20: 7020207
A21: 5215 | B21: ISAPRE | C21: Support | D21: 7020208
A22: 2414 | B22: Previred por pagar | D22: 3031302
A23: 2414 | B23: Seguro complementario | D23: 8050305
A24: 2411 | B24: Remuneraciones por pagar | D24: 3031204
A25: 2554 | B25: Impuesto adicional prestamo | D25: 3031505
A26: 2554 | B26: Impuesto unico trabajador | D26: 3031501
A27: 2411 | B27: Anticipo de sueldos | D27: 3031204

Sheet 09
A1: cta Deswik | B1: Remuneraciones Deswik mayo 2025 | D1: cta magnus | E1: =SUM(E2:E27) -> 0 | F1: =SUM(F2:F27) -> 0
A2: 5011 | B2: Salario | C2: Consulting | D2: 7020201
A3: 5012 | B3: Bono | C3: Consulting | D3: 7020202
A4: 5013 | B4: AFP | C4: Consulting | D4: 7020203
A5: 5015 | B5: ISAPRE | C5: Consulting | D5: 7020204
A6: 6306 | B6: Salario | C6: Admin | D6: 8050117
A7: 6307 | B7: Bono | C7: Admin | D7: 8050118
A8: 6308 | B8: AFP | C8: Admin | D8: 8050119
A9: 6326 | B9: ISAPRE | C9: Admin | D9: 8050121
C10: Admin/Sales
C11: Admin/Sales
C12: Admin/Sales
C13: Admin/Sales
A14: 6301 | B14: Salario | C14: Mkt | D14: 8050101
A15: 6302 | B15: Bono | C15: Mkt | D15: 8050102
A16: 6303 | B16: AFP | C16: Mkt | D16: 8050106
A17: 6327 | B17: ISAPRE | C17: Mkt | D17: 8050120
A18: 5211 | B18: Salario | C18: Support | D18: 7020205
A19: 5211 | B19: Bono | C19: Support | D19: 7020206
A20: 5213 | B20: AFP | C20: Support | D20: 7020207
A21: 5215 | B21: ISAPRE | C21: Support | D21: 7020208
A22: 2414 | B22: Previred por pagar | D22: 3031302
A23: 2414 | B23: Seguro complementario | D23: 8050305
A24: 2411 | B24: Remuneraciones por pagar | D24: 3031204
A25: 2554 | B25: Impuesto adicional prestamo | D25: 3031505
A26: 2554 | B26: Impuesto unico trabajador | D26: 3031501
A27: 2411 | B27: Anticipo de sueldos | D27: 3031204

Sheet 09 reliq
A1: cta Deswik | B1: Remuneraciones Deswik mayo 2025 | D1: cta magnus | E1: =SUM(E2:E27) -> 0 | F1: =SUM(F2:F27) -> 0
A2: 5011 | B2: Salario | C2: Consulting | D2: 7020201
A3: 5012 | B3: Bono | C3: Consulting | D3: 7020202
A4: 5013 | B4: AFP | C4: Consulting | D4: 7020203
A5: 5015 | B5: ISAPRE | C5: Consulting | D5: 7020204
A6: 6306 | B6: Salario | C6: Admin | D6: 8050117
A7: 6307 | B7: Bono | C7: Admin | D7: 8050118
A8: 6308 | B8: AFP | C8: Admin | D8: 8050119
A9: 6326 | B9: ISAPRE | C9: Admin | D9: 8050121
C10: Admin/Sales
C11: Admin/Sales
C12: Admin/Sales
C13: Admin/Sales
A14: 6301 | B14: Salario | C14: Mkt | D14: 8050101
A15: 6302 | B15: Bono | C15: Mkt | D15: 8050102
A16: 6303 | B16: AFP | C16: Mkt | D16: 8050106
A17: 6327 | B17: ISAPRE | C17: Mkt | D17: 8050120
A18: 5211 | B18: Salario | C18: Support | D18: 7020205
A19: 5211 | B19: Bono | C19: Support | D19: 7020206
A20: 5213 | B20: AFP | C20: Support | D20: 7020207
A21: 5215 | B21: ISAPRE | C21: Support | D21: 7020208
A22: 2414 | B22: Previred por pagar | D22: 3031302
A23: 2414 | B23: Seguro complementario | D23: 8050305
A24: 2411 | B24: Remuneraciones por pagar | D24: 3031204
A25: 2554 | B25: Impuesto adicional prestamo | D25: 3031505
A26: 2554 | B26: Impuesto unico trabajador | D26: 3031501
A27: 2411 | B27: Anticipo de sueldos | D27: 3031204

Sheet 10
A1: cta Deswik | B1: Remuneraciones Deswik mayo 2025 | D1: cta magnus | E1: =SUM(E2:E27) -> 0 | F1: =SUM(F2:F27) -> 0
A2: 5011 | B2: Salario | C2: Consulting | D2: 7020201
A3: 5012 | B3: Bono | C3: Consulting | D3: 7020202
A4: 5013 | B4: AFP | C4: Consulting | D4: 7020203
A5: 5015 | B5: ISAPRE | C5: Consulting | D5: 7020204
A6: 6306 | B6: Salario | C6: Admin | D6: 8050117
A7: 6307 | B7: Bono | C7: Admin | D7: 8050118
A8: 6308 | B8: AFP | C8: Admin | D8: 8050119
A9: 6326 | B9: ISAPRE | C9: Admin | D9: 8050121
C10: Admin/Sales
C11: Admin/Sales
C12: Admin/Sales
C13: Admin/Sales
A14: 6301 | B14: Salario | C14: Mkt | D14: 8050101
A15: 6302 | B15: Bono | C15: Mkt | D15: 8050102
A16: 6303 | B16: AFP | C16: Mkt | D16: 8050106
A17: 6327 | B17: ISAPRE | C17: Mkt | D17: 8050120
A18: 5211 | B18: Salario | C18: Support | D18: 7020205
A19: 5211 | B19: Bono | C19: Support | D19: 7020206
A20: 5213 | B20: AFP | C20: Support | D20: 7020207
A21: 5215 | B21: ISAPRE | C21: Support | D21: 7020208
A22: 2414 | B22: Previred por pagar | D22: 3031302
A23: 2414 | B23: Seguro complementario | D23: 8050305
A24: 2411 | B24: Remuneraciones por pagar | D24: 3031204
A25: 2554 | B25: Impuesto adicional prestamo | D25: 3031505
A26: 2554 | B26: Impuesto unico trabajador | D26: 3031501
A27: 2411 | B27: Anticipo de sueldos | D27: 3031204

Sheet 11
A1: cta Deswik | B1: Remuneraciones Deswik mayo 2025 | D1: cta magnus | E1: =SUM(E2:E27) -> 0 | F1: =SUM(F2:F27) -> 0
A2: 5011 | B2: Salario | C2: Consulting | D2: 7020201
A3: 5012 | B3: Bono | C3: Consulting | D3: 7020202
A4: 5013 | B4: AFP | C4: Consulting | D4: 7020203
A5: 5015 | B5: ISAPRE | C5: Consulting | D5: 7020204
A6: 6306 | B6: Salario | C6: Admin | D6: 8050117
A7: 6307 | B7: Bono | C7: Admin | D7: 8050118
A8: 6308 | B8: AFP | C8: Admin | D8: 8050119
A9: 6326 | B9: ISAPRE | C9: Admin | D9: 8050121
C10: Admin/Sales
C11: Admin/Sales
C12: Admin/Sales
C13: Admin/Sales
A14: 6301 | B14: Salario | C14: Mkt | D14: 8050101
A15: 6302 | B15: Bono | C15: Mkt | D15: 8050102
A16: 6303 | B16: AFP | C16: Mkt | D16: 8050106
A17: 6327 | B17: ISAPRE | C17: Mkt | D17: 8050120
A18: 5211 | B18: Salario | C18: Support | D18: 7020205
A19: 5211 | B19: Bono | C19: Support | D19: 7020206
A20: 5213 | B20: AFP | C20: Support | D20: 7020207
A21: 5215 | B21: ISAPRE | C21: Support | D21: 7020208
A22: 2414 | B22: Previred por pagar | D22: 3031302
A23: 2414 | B23: Seguro complementario | D23: 8050305
A24: 2411 | B24: Remuneraciones por pagar | D24: 3031204
A25: 2554 | B25: Impuesto adicional prestamo | D25: 3031505
A26: 2554 | B26: Impuesto unico trabajador | D26: 3031501
A27: 2411 | B27: Anticipo de sueldos | D27: 3031204

Sheet 12
A1: cta Deswik | B1: Remuneraciones Deswik mayo 2025 | D1: cta magnus | E1: =SUM(E2:E27) -> 0 | F1: =SUM(F2:F27) -> 0
A2: 5011 | B2: Salario | C2: Consulting | D2: 7020201
A3: 5012 | B3: Bono | C3: Consulting | D3: 7020202
A4: 5013 | B4: AFP | C4: Consulting | D4: 7020203
A5: 5015 | B5: ISAPRE | C5: Consulting | D5: 7020204
A6: 6306 | B6: Salario | C6: Admin | D6: 8050117
A7: 6307 | B7: Bono | C7: Admin | D7: 8050118
A8: 6308 | B8: AFP | C8: Admin | D8: 8050119
A9: 6326 | B9: ISAPRE | C9: Admin | D9: 8050121
C10: Admin/Sales
C11: Admin/Sales
C12: Admin/Sales
C13: Admin/Sales
A14: 6301 | B14: Salario | C14: Mkt | D14: 8050101
A15: 6302 | B15: Bono | C15: Mkt | D15: 8050102
A16: 6303 | B16: AFP | C16: Mkt | D16: 8050106
A17: 6327 | B17: ISAPRE | C17: Mkt | D17: 8050120
A18: 5211 | B18: Salario | C18: Support | D18: 7020205
A19: 5211 | B19: Bono | C19: Support | D19: 7020206
A20: 5213 | B20: AFP | C20: Support | D20: 7020207
A21: 5215 | B21: ISAPRE | C21: Support | D21: 7020208
A22: 2414 | B22: Previred por pagar | D22: 3031302
A23: 2414 | B23: Seguro complementario | D23: 8050305
A24: 2411 | B24: Remuneraciones por pagar | D24: 3031204
A25: 2554 | B25: Impuesto adicional prestamo | D25: 3031505
A26: 2554 | B26: Impuesto unico trabajador | D26: 3031501
A27: 2411 | B27: Anticipo de sueldos | D27: 3031204

Sheet acum
A1: cta Deswik | B1: Remuneraciones Deswik mayo 2025 | D1: cta magnus | E1: =SUM(E2:E28) -> 474860568 | F1: =SUM(F2:F28) -> 474860568
A2: 5011 | B2: Salario | C2: Consulting | D2: 7020201 | E2: =+'01'!E2+'02'!E2+'03'!E2+'04'!E2+'05'!E2+'06'!E2+'07'!E2+'08'!E2+'09'!E2+'10'!E2+'11'!E2+'12'!E2 -> 200852627
A3: 5012 | B3: Bono | C3: Consulting | D3: 7020202 | E3: =+'01'!E3+'02'!E3+'03'!E3+'04'!E3+'05'!E3+'06'!E3+'07'!E3+'08'!E3+'09'!E3+'10'!E3+'11'!E3+'12'!E3 -> 56091458
A4: 5013 | B4: AFP | C4: Consulting | D4: 7020203 | E4: =+'01'!E4+'02'!E4+'03'!E4+'04'!E4+'05'!E4+'06'!E4+'07'!E4+'08'!E4+'09'!E4+'10'!E4+'11'!E4+'12'!E4 -> 8247752
A5: 5015 | B5: ISAPRE | C5: Consulting | D5: 7020204 | E5: =+'01'!E5+'02'!E5+'03'!E5+'04'!E5+'05'!E5+'06'!E5+'07'!E5+'08'!E5+'09'!E5+'10'!E5 -> 0
A6: 6306 | B6: Salario | C6: Admin | D6: 8050117 | E6: =+'01'!E6+'02'!E6+'03'!E6+'04'!E6+'05'!E6+'06'!E6+'07'!E6+'08'!E6+'09'!E6+'10'!E6+'11'!E6+'12'!E6 -> 90646402 | X6: =+E6+E10 -> 90646402
A7: 6307 | B7: Bono | C7: Admin | D7: 8050118 | E7: =+'01'!E7+'02'!E7+'03'!E7+'04'!E7+'05'!E7+'06'!E7+'07'!E7+'08'!E7+'09'!E7+'10'!E7 -> 21694582 | X7: =+E7+E11 -> 21694582
A8: 6308 | B8: AFP | C8: Admin | D8: 8050119 | E8: =+'01'!E8+'02'!E8+'03'!E8+'04'!E9+'05'!E8+'06'!E8+'07'!E8+'08'!E8+'09 reliq'!E8+'10'!E8+'11'!E8+'12'!E8 -> 4063697 | X8: =+E8+E12 -> 4063697
A9: 6326 | B9: ISAPRE | C9: Admin | D9: 8050121 | E9: =+'01'!E9+'02'!E9+'03'!E9+'05'!E9+'06'!E9+'07'!E9+'08'!E9+'09'!E9+'10'!E9 -> 0
A10: 6306 | B10: Salario | C10: Admin/Sales | E10: =+'01'!E10+'02'!E10+'03'!E10+'04'!E10+'05'!E10+'06'!E10+'07'!E10+'08'!E10+'09'!E10+'10'!E10 -> 0
A11: 6307 | B11: Bono | C11: Admin/Sales | E11: =+'01'!E11+'02'!E11+'03'!E11+'04'!E11+'05'!E11+'06'!E11+'07'!E11+'08'!E11+'09'!E11+'10'!E11 -> 0
A12: 6308 | B12: AFP | C12: Admin/Sales | E12: =+'01'!E12+'02'!E12+'03'!E12+'04'!E12+'05'!E12+'06'!E12+'07'!E12+'08'!E12+'09'!E12+'10'!E12 -> 0
A13: 6326 | B13: ISAPRE | C13: Admin/Sales | E13: =+'01'!E13+'02'!E13+'03'!E13+'04'!E13+'05'!E13+'06'!E13+'07'!E13+'08'!E13+'09'!E13+'10'!E13 -> 0
A14: 6301 | B14: Salario | C14: Mkt | D14: 8050101 | E14: =+'01'!E14+'02'!E14+'03'!E14+'04'!E14+'05'!E14+'06'!E14+'07'!E14+'08'!E14+'09'!E14+'10'!E14+'11'!E14+'12'!E14 -> 35444763
A15: 6302 | B15: Bono | C15: Mkt | D15: 8050102 | E15: =+'01'!E15+'02'!E15+'03'!E15+'04'!E15+'05'!E15+'06'!E15+'07'!E15+'08'!E15+'09'!E15+'10'!E15 -> 44717032
A16: 6303 | B16: AFP | C16: Mkt | D16: 8050106 | E16: =+'01'!E16+'02'!E16+'03'!E16+'04'!E16+'05'!E16+'06'!E16+'07'!E16+'08'!E16+'09'!E16+'10'!E16+'11'!E16+'12'!E16 -> 961253
A17: 6327 | B17: ISAPRE | C17: Mkt | D17: 8050120 | E17: =+'01'!E17+'02'!E17+'03'!E17+'04'!E17+'05'!E17+'06'!E17+'07'!E17+'08'!E17+'09'!E17+'10'!E17 -> 395784
A18: 5211 | B18: Salario | C18: Support | D18: 7020205 | E18: =+'01'!E18+'02'!E18+'03'!E18+'04'!E18+'05'!E18+'06'!E18+'07'!E18+'08'!E18+'09'!E18+'10'!E18+'11'!E18+'12'!E18 -> 6340062
A19: 5211 | B19: Bono | C19: Support | D19: 7020206 | E19: =+'01'!E19+'02'!E19+'03'!E19+'04'!E19+'05'!E19+'06'!E19+'07'!E19+'08'!E19+'09'!E19+'10'!E19 -> 4762894
A20: 5213 | B20: AFP | C20: Support | D20: 7020207 | E20: =+'01'!E20+'02'!E20+'03'!E20+'04'!E20+'05'!E20+'06'!E20+'07'!E20+'08'!E20+'09'!E20+'10'!E20+'11'!E20+'12'!E20 -> 501643
A21: 5215 | B21: ISAPRE | C21: Support | D21: 7020208 | E21: =+'01'!E21+'02'!E21+'03'!E21+'04'!E21+'05'!E21+'06'!E21+'07'!E21+'08'!E21+'09'!E21+'10'!E21 -> 140619
A22: 8018 | B22: Bono LTI | C22: Mkt | D22: 8050122 | E22: =+'01'!E22+'02'!E22+'03'!E22+'04'!E22+'05'!E22+'06'!E22+'07'!E22+'08'!E22+'09'!E22+'10'!E22 -> 0
A23: 2414 | B23: Previred por pagar | D23: 3031302 | F23: =+'01'!F22+'02'!F22+'03'!F22+'04'!F23+'05'!F22+'06'!F22+'07'!F22+'08'!F22+'09 reliq'!F22+'10'!F22+'11'!F22+'12'!F22 -> 56071878
A24: 2411 | B24: Remuneraciones por pagar | D24: 3031204 | F24: =+'01'!F23+'02'!F23+'03'!F23+'04'!F24+'05'!F23+'06'!F23+'07'!F23+'08'!F23+'09 reliq'!F23+'10'!F23+'11'!F23 -> 278439938
A25: 2554 | B25: Impuesto adicional prestamo | D25: 3031505 | F25: =+'01'!F24+'02'!F24+'03'!F24+'04'!F25+'05'!F24+'06'!F24+'07'!F24+'08'!F24+'09 reliq'!F24+'10'!F24+'11'!F24+'12'!F24 -> 68100432
A26: 2554 | B26: Impuesto unico trabajador | D26: 3031501 | F26: =+'01'!F25+'02'!F25+'03'!F25+'04'!F26+'05'!F25+'06'!F25+'07'!F25+'08'!F25+'09 reliq'!F25+'10'!F25+'11'!F25+'12'!F25 -> 56427382
A27: 2411 | B27: Anticipo de sueldos | D27: 3031204 | F27: =+'01'!F26+'02'!F26+'03'!F26+'04'!F27+'05'!F26+'06'!F26+'07'!F26+'08'!F26+'09 reliq'!F26+'10'!F26+'11'!F26+'12'!F26 -> 15820938
F28: =+'01'!F27+'02'!F27+'03'!F27+'04'!F28+'05'!F27+'06'!F27+'07'!F27+'08'!F27+'09 reliq'!F27+'10'!F27+'12'!F27 -> 0
E30: =+'01'!E1+'02'!E1+'03'!E1+'04'!E1+'05'!E1+'06'!E1+'07'!E1+'08'!E1+'09 reliq'!E1+'10'!E1+'11'!E1+'12'!E1 -> 474860568 | F30: =+'01'!F1+'02'!F1+'03'!F1+'04'!F1+'05'!F1+'06'!F1+'07'!F1+'08'!F1+'09 reliq'!F1+'10'!F1+'11'!F1+'12'!F1 -> 474860568
E31: =E30-E1 -> 0 | F31: =F30-F1 -> 0
